Workbook

Sheet rawdata
A1: mode | B1: paperId | C1: title | D1: publication_date | E1: year | F1: publication_types | G1: fields_of_study | H1: influential_citation_count | I1: citation_count | J1: abstract | K1: external_ids | L1: doi | M1: is_open_access | N1: open_access_pdf_url | O1: journal_pages_range | P1: pages_total | Q1: references_pages | R1: references_count | S1: _max_cited_year | T1: authors_hindex_list | U1: mean_author_hindex
A2: PRECISE | B2: d7d9107de19eba8228bc599f53f013245760caee | C2: A Survey of Data Mining and Machine Learning Methods for Cyber Security Intrusion Detection | D2: 2017-04-13 | E2: 2017 | F2: Review | G2: Engineering | H2: 106 | I2: 1461 | K2: {"CorpusId": 44606951, "MAG": "2605388774"} | M2: FALSE | O2: 406-412 | P2: 7 | R2: 14 | T2: 1; 2; 1; 2 | U2: 1.5
A3: PRECISE | B3: dab11c890b9924c8bfcb09bf8a9b1fbd1e2bbffc | C3: Processing flows of information: From data stream to complex event processing | D3: 2012-06-01 | E3: 2012 | F3: JournalArticle; Review | G3: Computer Science | H3: 84 | I3: 995 | K3: {"CorpusId": 8728283, "DBLP": "journals/csur/CugolaM12", "DOI": "10.1145/2187671.2187677", "MAG": "1973026225"} | L3: 10.1145/2187671.2187677 | M3: FALSE | O3: 15:1-15:62 | R3: 181 | T3: 35; 24 | U3: 29.5
A4: PRECISE | B4: 1dc23940f830a1aede366ac9654b5d499c14bcef | C4: A Survey of Defense Mechanisms Against Distributed Denial of Service (DDoS) Flooding Attacks | D4: 2013-03-28 | E4: 2013 | F4: JournalArticle; Review | G4: Computer Science | H4: 77 | I4: 1307 | K4: {"CorpusId": 206584087, "DBLP": "journals/comsur/ZargarJT13", "DOI": "10.1109/SURV.2013.031413.00127", "MAG": "2162969618"} | L4: 10.1109/surv.2013.031413.00127 | M4: TRUE | N4: http://d-scholarship.pitt.edu/19225/1/FinalVersion.pdf | O4: 2046-2069 | P4: 24 | R4: 147 | T4: 9; 39; 33 | U4: 27
A5: PRECISE | B5: 4db2f23a5ad2259b90aa9b0545d27cd44337515a | C5: Intrusion detection system: A comprehensive review | F5: JournalArticle; Review | G5: Computer Science | H5: 71 | I5: 1426 | K5: {"CorpusId": 18434328, "DBLP": "journals/jnca/LiaoLLT13", "DOI": "10.1016/j.jnca.2012.09.004", "MAG": "433644524"} | L5: 10.1016/j.jnca.2012.09.004 | M5: FALSE | O5: 16-24 | P5: 9 | R5: 71 | T5: 2; 15; 4; 4 | U5: 6.25
A6: PRECISE | B6: e467ff1ea3a0c535a0cef87f7e0daa414d524d9d | C6: Network Anomaly Detection: Methods, Systems and Tools | D6: 2014-01-21 | E6: 2014 | F6: JournalArticle; Review | G6: Computer Science | H6: 71 | I6: 1184 | K6: {"CorpusId": 4937576, "DBLP": "journals/comsur/BhuyanBK14", "DOI": "10.1109/SURV.2013.052213.00046", "MAG": "1966809779"} | L6: 10.1109/surv.2013.052213.00046 | M6: FALSE | O6: 303-336 | P6: 34 | R6: 227 | T6: 21; 39; 44 | U6: 34.66666666666666
A7: PRECISE | B7: 38e81867da601ae6877dd9ce2c1e1aa085852ecb | C7: Survey of intrusion detection systems: techniques, datasets and challenges | D7: 2019-07-01 | E7: 2019 | F7: JournalArticle; Review | G7: Computer Science | H7: 63 | I7: 1287 | J7: Cyber-attacks are becoming more sophisticated and thereby presenting increasing challenges in accurately detecting intrusions. Failure to prevent the intrusions could degrade the credibility of security services, e.g. data confidentiality, integrity, and availability. Numerous intrusion detection methods have been proposed in the literature to tackle computer security threats, which can be broadly classified into Signature-based Intrusion Detection Systems (SIDS) and Anomaly-based Intrusion Detection Systems (AIDS). This survey paper presents a taxonomy of contemporary IDS, a comprehensive review of notable recent works, and an overview of the datasets commonly used for evaluation purposes. It also presents evasion techniques used by attackers to avoid detection and discusses future research challenges to counter such techniques so as to make computer systems more secure. | K7: {"CorpusId": 197645932, "DBLP": "journals/cybersec/KhraisatGVK19", "DOI": "10.1186/s42400-019-0038-7", "MAG": "2958285686"} | L7: 10.1186/s42400-019-0038-7 | M7: TRUE | N7: https://cybersecurity.springeropen.com/track/pdf/10.1186/s42400-019-0038-7 | R7: 124 | S7: 2018 | T7: 14; 27; 27; 36 | U7: 26
A8: PRECISE | B8: 1c65649ffb61144f867aa1dc526ddaac19b3cecd | C8: A survey of intrusion detection in Internet of Things | D8: 2017-04-15 | E8: 2017 | F8: JournalArticle; Review | G8: Computer Science | H8: 47 | I8: 891 | K8: {"CorpusId": 31714, "DBLP": "journals/jnca/ZarpelaoMKA17", "DOI": "10.1016/j.jnca.2017.02.009", "MAG": "2590373591"} | L8: 10.1016/j.jnca.2017.02.009 | M8: FALSE | O8: 25-37 | P8: 13 | R8: 90 | T8: 16; 11; 3; 3 | U8: 8.25
A9: PRECISE | B9: 2eea41136efeea6e1426c631fa1ac0a221fe6978 | C9: Deep learning approach for Network Intrusion Detection in Software Defined Networking | D9: 2016-10-01 | E9: 2016 | F9: Conference; JournalArticle; Review | G9: Computer Science | H9: 47 | I9: 635 | K9: {"CorpusId": 15987982, "DBLP": "conf/wincom/TangMMZG16", "DOI": "10.1109/WINCOM.2016.7777224", "MAG": "2560162835"} | L9: 10.1109/wincom.2016.7777224 | M9: TRUE | N9: http://eprints.whiterose.ac.uk/106836/8/Tuan%20Tang_WINCOM16.pdf | O9: 258-263 | P9: 6 | R9: 20 | T9: 5; 17; 28; 25; 39 | U9: 22.8
A10: PRECISE | B10: 8e2527113c652a25dad5a8af72a67f2d0bbb2706 | C10: A Survey of Intrusion Detection Systems in Wireless Sensor Networks | D10: 2014-01-21 | E10: 2014 | F10: JournalArticle; Review | G10: Computer Science | H10: 41 | I10: 922 | K10: {"CorpusId": 14636557, "DBLP": "journals/comsur/ButunMS14", "DOI": "10.1109/SURV.2013.050113.00191", "MAG": "2011778831"} | L10: 10.1109/surv.2013.050113.00191 | M10: FALSE | O10: 266-282 | P10: 17 | R10: 73 | T10: 22; 23; 23 | U10: 22.66666666666667
A11: PRECISE | B11: 971766088dfaf63fb55e6f0190b14f28f2c98ad0 | C11: A Survey of Data Mining and Machine Learning Methods for Cyber Security Intrusion Detection | D11: 2016-01-22 | E11: 2016 | F11: JournalArticle; Review | G11: Computer Science | H11: 38 | I11: 1021 | K11: {"CorpusId": 206577177, "DBLP": "journals/comsur/BuczakG16", "DOI": "10.1109/COMST.2015.2494502", "MAG": "2342408547"} | L11: 10.1109/comst.2015.2494502 | M11: TRUE | N11: https://doi.org/10.1109/comst.2015.2494502 | O11: 1153-1176 | P11: 24 | R11: 110 | T11: 20; 6 | U11: 13
A12: PRECISE | B12: c9dbf8068d03b9ac6c5f02d40b75af182ca69699 | C12: A survey of intrusion detection techniques in Cloud | F12: JournalArticle; Review | G12: Computer Science | H12: 38 | I12: 918 | K12: {"CorpusId": 12815020, "DBLP": "journals/jnca/ModiPBPPR13", "DOI": "10.1016/j.jnca.2012.05.003", "MAG": "1489073918"} | L12: 10.1016/j.jnca.2012.05.003 | M12: TRUE | N12: https://openaccess.city.ac.uk/id/eprint/1737/1/A%20survey%20of%20intrusion%20detection%20techniques%20in%20Cloud.pdf | O12: 42-57 | P12: 16 | R12: 75 | T12: 21; 19; 10; 6; 8; 41 | U12: 17.5
A13: PRECISE | B13: 6bd85cfce9eeee059b1ee73851711e9ec847a31b | C13: The Evolution of MAC Protocols in Wireless Sensor Networks: A Survey | D13: 2013-01-21 | E13: 2013 | F13: JournalArticle; Review | G13: Computer Science | H13: 37 | I13: 602 | K13: {"CorpusId": 25576812, "DBLP": "journals/comsur/HuangXSMX13", "DOI": "10.1109/SURV.2012.040412.00105", "MAG": "2170044052"} | L13: 10.1109/surv.2012.040412.00105 | M13: FALSE | O13: 101-120 | P13: 20 | R13: 78 | T13: 14; 39; 5; 32; 42 | U13: 26.4
A14: PRECISE | B14: c42c29c793f3b8518a313d03fa101b1201a8ad14 | C14: Network intrusion detection system: A systematic study of machine learning and deep learning approaches | D14: 2020-10-16 | E14: 2020 | F14: JournalArticle; Review | G14: Computer Science | H14: 37 | I14: 832 | J14: The rapid advances in the internet and communication fields have resulted in a huge increase in the network size and the corresponding data. As a result, many novel attacks are being generated and have posed challenges for network security to accurately detect intrusions. Furthermore, the presence of the intruders with the aim to launch various attacks within the network cannot be ignored. An intrusion detection system (IDS) is one such tool that prevents the network from possible intrusions by inspecting the network traffic, to ensure its confidentiality, integrity, and availability. Despite enormous efforts by the researchers, IDS still faces challenges in improving detection accuracy while reducing false alarm rates and in detecting novel intrusions. Recently, machine learning (ML) and deep learning (DL)‐based IDS systems are being deployed as potential solutions to detect intrusions across the network in an efficient manner. This article first clarifies the concept of IDS and then provides the taxonomy based on the notable ML and DL techniques adopted in designing network‐based IDS (NIDS) systems. A comprehensive review of the recent NIDS‐based articles is provided by discussing the strengths and limitations of the proposed solutions. Then, recent trends and advancements of ML and DL‐based NIDS are provided in terms of the proposed methodology, evaluation metrics, and dataset selection. Using the shortcomings of the proposed methods, we highlighted various research challenges and provided the future scope for the research in improving ML and DL‐based NIDS. | K14: {"CorpusId": 225153435, "DBLP": "journals/ett/AhmadKSAA21", "DOI": "10.1002/ett.4150", "MAG": "3093410479"} | L14: 10.1002/ett.4150 | M14: TRUE | N14: https://onlinelibrary.wiley.com/doi/pdfdirect/10.1002/ett.4150 | R14: 150 | S14: 2020 | T14: 11; 16; 8; 14; 6 | U14: 11
A15: PRECISE | B15: 67f3df0846e89da5dfc7c25980d9189c7df50292 | C15: CoSDEO 2016 Keynote: A decade later — Challenges: Device-free passive localization for wireless environments | D15: 2016-03-14 | E15: 2016 | F15: Conference; JournalArticle; Review | G15: Computer Science | H15: 34 | I15: 417 | K15: {"CorpusId": 34643949, "DBLP": "conf/percom/Youssef16", "DOI": "10.1109/PERCOMW.2016.7457113", "MAG": "2337900948"} | L15: 10.1109/percomw.2016.7457113 | M15: FALSE | O15: 1-2 | P15: 2 | R15: 45 | T15: 43 | U15: 43
A16: PRECISE | B16: cbe3fda28a29052fb82dcaca66be1edf549180d4 | C16: A Survey of Network-based Intrusion Detection Data Sets | D16: 2019-03-06 | E16: 2019 | F16: JournalArticle; Review | G16: Computer Science | H16: 33 | I16: 586 | K16: {"ArXiv": "1903.02460", "CorpusId": 70349997, "DBLP": "journals/compsec/RingWSLH19", "DOI": "10.1016/j.cose.2019.06.005", "MAG": "2950955939"} | L16: 10.1016/j.cose.2019.06.005 | M16: TRUE | N16: http://arxiv.org/pdf/1903.02460 | O16: 147-167 | P16: 21 | R16: 101 | S16: 2019 | T16: 11; 5; 1; 19; 53 | U16: 17.8
A17: PRECISE | B17: 22b56df45e2ff1aafca278253c24c6abafd0d0c7 | C17: A survey of intrusion detection techniques for cyber-physical systems | D17: 2014-03-01 | E17: 2014 | F17: JournalArticle; Review | G17: Computer Science | H17: 30 | I17: 645 | K17: {"CorpusId": 207209718, "DBLP": "journals/csur/MitchellC13", "DOI": "10.1145/2542049", "MAG": "2161630727"} | L17: 10.1145/2542049 | M17: TRUE | N17: http://people.cs.vt.edu/~irchen/ps/Mitchell-CSUR14.pdf | O17: 1 - 29 | P17: 29 | R17: 95 | T17: 12; 46 | U17: 29
A18: PRECISE | B18: 236dfdeb4511754cf71ba220ac569b11973502cd | C18: Machine Learning and Deep Learning Methods for Intrusion Detection Systems: A Survey | D18: 2019-10-17 | E18: 2019 | F18: Review | G18: Engineering | H18: 30 | I18: 776 | J18: Networks play important roles in modern life, and cyber security has become a vital research area. An intrusion detection system (IDS) which is an important cyber security technique, monitors the state of software and hardware running in the network. Despite decades of development, existing IDSs still face challenges in improving the detection accuracy, reducing the false alarm rate and detecting unknown attacks. To solve the above problems, many researchers have focused on developing IDSs that capitalize on machine learning methods. Machine learning methods can automatically discover the essential differences between normal data and abnormal data with high accuracy. In addition, machine learning methods have strong generalizability, so they are also able to detect unknown attacks. Deep learning is a branch of machine learning, whose performance is remarkable and has become a research hotspot. This survey proposes a taxonomy of IDS that takes data objects as the main dimension to classify and summarize machine learning-based and deep learning-based IDS literature. We believe that this type of taxonomy framework is fit for cyber security researchers. The survey first clarifies the concept and taxonomy of IDSs. Then, the machine learning algorithms frequently used in IDSs, metrics, and benchmark datasets are introduced. Next, combined with the representative literature, we take the proposed taxonomic system as a baseline and explain how to solve key IDS issues with machine learning and deep learning techniques. Finally, challenges and future developments are discussed by reviewing recent representative studies. | K18: {"CorpusId": 208843362, "DOI": "10.3390/app9204396", "MAG": "2980576170"} | L18: 10.3390/app9204396 | M18: TRUE | N18: https://www.mdpi.com/2076-3417/9/20/4396/pdf?version=1571308126 | R18: 91 | S18: 2019 | T18: 8; 8 | U18: 8
A19: PRECISE | B19: cead00c7b3384653ce8013139a5d4543d96fcd07 | C19: Fault Injection Attacks on Cryptographic Devices: Theory, Practice, and Countermeasures | D19: 2012-04-05 | E19: 2012 | F19: JournalArticle; Review | G19: Computer Science; Engineering | H19: 30 | I19: 553 | K19: {"CorpusId": 1762526, "DBLP": "journals/pieee/BarenghiBKN12", "DOI": "10.1109/JPROC.2012.2188769", "MAG": "2085992264"} | L19: 10.1109/jproc.2012.2188769 | M19: TRUE | N19: http://euler.ecs.umass.edu/research/bbkn-IEEEP-2012.pdf | O19: 3056-3076 | P19: 21 | R19: 94 | T19: 26; 27; 44; 39 | U19: 34
A20: PRECISE | B20: 25cd96cc105927efa772f690426e955f080f72ff | C20: A Scheme for Generating a Dataset for Anomalous Activity Detection in IoT Networks | D20: 2020-05-13 | E20: 2020 | F20: Conference; JournalArticle; Review | G20: Computer Science | H20: 27 | I20: 218 | K20: {"CorpusId": 218539986, "DBLP": "conf/ai/UllahM20", "DOI": "10.1007/978-3-030-47358-7_52", "MAG": "3022604549"} | L20: 10.1007/978-3-030-47358-7_52 | M20: FALSE | O20: 508-520 | P20: 13 | R20: 15 | T20: 13; 38 | U20: 25.5
A21: PRECISE | B21: f4ba147e57beee5e57cc4548feb130cbe16c9192 | C21: Network Intrusion Detection for IoT Security Based on Learning Techniques | D21: 2019-01-30 | E21: 2019 | F21: JournalArticle; Review | G21: Computer Science | H21: 27 | I21: 666 | J21: Pervasive growth of Internet of Things (IoT) is visible across the globe. The 2016 Dyn cyberattack exposed the critical fault-lines among smart networks. Security of IoT has become a critical concern. The danger exposed by infested Internet-connected Things not only affects the security of IoT but also threatens the complete Internet eco-system which can possibly exploit the vulnerable Things (smart devices) deployed as botnets. Mirai malware compromised the video surveillance devices and paralyzed Internet via distributed denial of service attacks. In the recent past, security attack vectors have evolved bothways, in terms of complexity and diversity. Hence, to identify and prevent or detect novel attacks, it is important to analyze techniques in IoT context. This survey classifies the IoT security threats and challenges for IoT networks by evaluating existing defense techniques. Our main focus is on network intrusion detection systems (NIDSs); hence, this paper reviews existing NIDS implementation tools and datasets as well as free and open-source network sniffing software. Then, it surveys, analyzes, and compares state-of-the-art NIDS proposals in the IoT context in terms of architecture, detection methodologies, validation strategies, treated threats, and algorithm deployments. The review deals with both traditional and machine learning (ML) NIDS techniques and discusses future directions. In this survey, our focus is on IoT NIDS deployed via ML since learning algorithms have a good success rate in security and privacy. The survey provides a comprehensive review of NIDSs deploying different aspects of learning techniques for IoT, unlike other top surveys targeting the traditional systems. We believe that, this paper will be useful for academia and industry research, first, to identify IoT threats and challenges, second, to implement their own NIDS and finally to propose new smart techniques in IoT context considering IoT limitations. Moreover, the survey will enable security individuals differentiate IoT NIDS from traditional ones. | K21: {"CorpusId": 86720272, "DBLP": "journals/comsur/ChaabouniMZSF19", "DOI": "10.1109/COMST.2019.2896380", "MAG": "2911505293"} | L21: 10.1109/comst.2019.2896380 | M21: FALSE | O21: 2671-2701 | P21: 31 | R21: 134 | T21: 3; 21; 16; 3; 16 | U21: 11.8
A22: PRECISE | B22: 39361b3507c9f8b0a97780568b645f80a208d78a | C22: Machine Learning and Deep Learning Methods for Cybersecurity | D22: 2018-05-15 | E22: 2018 | F22: JournalArticle; Review | G22: Computer Science | H22: 26 | I22: 826 | J22: With the development of the Internet, cyber-attacks are changing rapidly and the cyber security situation is not optimistic. This survey report describes key literature surveys on machine learning (ML) and deep learning (DL) methods for network analysis of intrusion detection and provides a brief tutorial description of each ML/DL method. Papers representing each method were indexed, read, and summarized based on their temporal or thermal correlations. Because data are so important in ML/DL methods, we describe some of the commonly used network datasets used in ML/DL, discuss the challenges of using ML/DL for cybersecurity and provide suggestions for research directions. | K22: {"CorpusId": 49866160, "DBLP": "journals/access/XinK0CLZGHW18", "DOI": "10.1109/ACCESS.2018.2836950", "MAG": "2803881474"} | L22: 10.1109/access.2018.2836950 | M22: TRUE | N22: https://doi.org/10.1109/access.2018.2836950 | O22: 35365-35381 | P22: 17 | R22: 76 | S22: 2018 | T22: 7; 3; 15; 17; 5; 11; 6; 7; 2 | U22: 8.11111111111111
A23: PRECISE | B23: 6083bd8cdb810ce3d4f4bb9a004cac2a58b424eb | C23: Demystifying IoT Security: An Exhaustive Survey on IoT Vulnerabilities and a First Empirical Look on Internet-Scale IoT Exploitations | D23: 2019-04-11 | E23: 2019 | F23: JournalArticle; Review | G23: Computer Science | H23: 26 | I23: 592 | J23: The security issue impacting the Internet-of-Things (IoT) paradigm has recently attracted significant attention from the research community. To this end, several surveys were put forward addressing various IoT-centric topics, including intrusion detection systems, threat modeling, and emerging technologies. In contrast, in this paper, we exclusively focus on the ever-evolving IoT vulnerabilities. In this context, we initially provide a comprehensive classification of state-of-the-art surveys, which address various dimensions of the IoT paradigm. This aims at facilitating IoT research endeavors by amalgamating, comparing, and contrasting dispersed research contributions. Subsequently, we provide a unique taxonomy, which sheds the light on IoT vulnerabilities, their attack vectors, impacts on numerous security objectives, attacks which exploit such vulnerabilities, corresponding remediation methodologies and currently offered operational cyber security capabilities to infer and monitor such weaknesses. This aims at providing the reader with a multidimensional research perspective related to IoT vulnerabilities, including their technical details and consequences, which is postulated to be leveraged for remediation objectives. Additionally, motivated by the lack of empirical (and malicious) data related to the IoT paradigm, this paper also presents a first look on Internet-scale IoT exploitations by drawing upon more than 1.2 GB of macroscopic, passive measurements’ data. This aims at practically highlighting the severity of the IoT problem, while providing operational situational awareness capabilities, which undoubtedly would aid in the mitigation task, at large. Insightful findings, inferences and outcomes in addition to open challenges and research problems are also disclosed in this paper, which we hope would pave the way for future research endeavors addressing theoretical and empirical aspects related to the imperative topic of IoT security. | K23: {"CorpusId": 201741566, "DBLP": "journals/comsur/NeshenkoBCKG19", "DOI": "10.1109/COMST.2019.2910750", "MAG": "2969468102"} | L23: 10.1109/comst.2019.2910750 | M23: TRUE | N23: https://doi.org/10.1109/comst.2019.2910750 | O23: 2702-2733 | P23: 32 | R23: 206 | T23: 8; 30; 19; 56; 29 | U23: 28.4
A24: PRECISE | B24: cf003fbb1609c1457701cb7d698a5361be1d16b1 | C24: An intrusion detection and prevention system in cloud computing: A systematic review | F24: JournalArticle; Review | G24: Computer Science | H24: 24 | I24: 443 | K24: {"CorpusId": 34668439, "DBLP": "journals/jnca/PatelTBJ13", "DOI": "10.1016/j.jnca.2012.08.007", "MAG": "2139836766"} | L24: 10.1016/j.jnca.2012.08.007 | M24: FALSE | O24: 25-41 | P24: 17 | R24: 90 | T24: 22; 14; 14; 16 | U24: 16.5
A25: PRECISE | B25: 2313d55f4e7739de529e966521018c9043c3fe45 | C25: Survey on Misbehavior Detection in Cooperative Intelligent Transportation Systems | D25: 2016-10-21 | E25: 2016 | F25: JournalArticle; Review | G25: Computer Science | H25: 23 | I25: 218 | J25: Cooperative intelligent transportation systems (cITS) are a promising technology to enhance driving safety and efficiency. Vehicles communicate wirelessly with other vehicles and infrastructure, thereby creating a highly dynamic and heterogeneously managed ad-hoc network. It is these network properties that make it a challenging task to protect integrity of the data and guarantee its correctness. A major component is the problem that traditional security mechanisms like public key infrastructure (PKI)-based asymmetric cryptography only exclude outsider attackers that do not possess key material. However, because attackers can be insiders within the network (i.e., possess valid key material), this approach cannot detect all possible attacks. In this survey, we present misbehavior detection mechanisms that can detect such insider attacks based on attacker behavior and information analysis. In contrast to well-known intrusion detection for classical IT systems, these misbehavior detection mechanisms analyze information semantics to detect attacks, which aligns better with highly application-tailored communication protocols foreseen for cITS. In our survey, we provide an extensive introduction to the cITS ecosystem and discuss shortcomings of PKI-based security. We derive and discuss a classification for misbehavior detection mechanisms, provide an in-depth overview of seminal papers on the topic, and highlight open issues and possible future research trends. | K25: {"ArXiv": "1610.06810", "CorpusId": 8876979, "DBLP": "journals/comsur/HeijdenDLK19", "DOI": "10.1109/COMST.2018.2873088", "MAG": "2963030364"} | L25: 10.1109/comst.2018.2873088 | M25: TRUE | N25: https://arxiv.org/pdf/1610.06810 | O25: 779-811 | P25: 33 | R25: 138 | S25: 2016 | T25: 3; 15; 21; 47 | U25: 21.5
A26: PRECISE | B26: 4a8c332b09bb99333a8bce6a4640a20c1352aa63 | C26: A Survey on Security Threats and Defensive Techniques of Machine Learning: A Data Driven View | D26: 2018-02-13 | E26: 2018 | F26: JournalArticle; Review | G26: Computer Science | H26: 23 | I26: 357 | J26: Machine learning is one of the most prevailing techniques in computer science, and it has been widely applied in image processing, natural language processing, pattern recognition, cybersecurity, and other fields. Regardless of successful applications of machine learning algorithms in many scenarios, e.g., facial recognition, malware detection, automatic driving, and intrusion detection, these algorithms and corresponding training data are vulnerable to a variety of security threats, inducing a significant performance decrease. Hence, it is vital to call for further attention regarding security threats and corresponding defensive techniques of machine learning, which motivates a comprehensive survey in this paper. Until now, researchers from academia and industry have found out many security threats against a variety of learning algorithms, including naive Bayes, logistic regression, decision tree, support vector machine (SVM), principle component analysis, clustering, and prevailing deep neural networks. Thus, we revisit existing security threats and give a systematic survey on them from two aspects, the training phase and the testing/inferring phase. After that, we categorize current defensive techniques of machine learning into four groups: security assessment mechanisms, countermeasures in the training phase, those in the testing or inferring phase, data security, and privacy. Finally, we provide five notable trends in the research on security threats and defensive techniques of machine learning, which are worth doing in-depth studies in future. | K26: {"CorpusId": 4111957, "DBLP": "journals/access/LiuLZCYL18", "DOI": "10.1109/ACCESS.2018.2805680", "MAG": "2791319131"} | L26: 10.1109/access.2018.2805680 | M26: TRUE | N26: https://doi.org/10.1109/access.2018.2805680 | O26: 12103-12117 | P26: 15 | R26: 106 | S26: 2018 | T26: 20; 6; 13; 20; 56; 99 | U26: 35.66666666666666
A27: PRECISE | B27: 922b6fb164f5b9d774d16cb14c31f5cb68a02046 | C27: Game theory meets network security and privacy | D27: 2013-06-01 | E27: 2013 | F27: JournalArticle; Review | G27: Computer Science | H27: 23 | I27: 797 | K27: {"CorpusId": 207203993, "DBLP": "journals/csur/ManshaeiZABH13", "DOI": "10.1145/2480741.2480742", "MAG": "2067064328"} | L27: 10.1145/2480741.2480742 | M27: TRUE | N27: http://infoscience.epfl.ch/record/151965/files/Game%20Sec-ACM%20Survey.pdf | O27: 25:1-25:39 | R27: 136 | T27: 24; 51; 48; 96; 87 | U27: 61.2
A28: PRECISE | B28: de3ddfdb3c8c995cff057e010db6ac70e06ef5b5 | C28: Data stream clustering: A survey | D28: 2013-10-01 | E28: 2013 | F28: JournalArticle; Review | G28: Computer Science | H28: 23 | I28: 547 | K28: {"CorpusId": 3346652, "DBLP": "journals/csur/SilvaFBHCG13", "DOI": "10.1145/2522968.2522981", "MAG": "2088340225"} | L28: 10.1145/2522968.2522981 | M28: TRUE | N28: http://repositorio.inesctec.pt/bitstreams/5cd9346a-c309-4fdb-b2b2-20148318a05c/download | O28: 13:1-13:31 | R28: 134 | T28: 15; 10; 29; 33; 47; 61 | U28: 32.5
A29: PRECISE | B29: 246ba747471461dd30f8d3491d711c54ca515eb3 | C29: Routing Attacks and Mitigation Methods for RPL-Based Internet of Things | F29: JournalArticle; Review | G29: Computer Science | H29: 20 | I29: 188 | J29: The recent bloom of Internet of Things (IoT) and its prevalence in many security-sensitive environments made the security of these networks a crucial requirement. Routing in many of IoT networks has been performed using the routing protocol for low power and lossy networks (RPL), due to its energy-efficient mechanisms, secure modes availability, and its adaptivity to work in various environments; hence, RPL security has been the focus of many researchers. This paper presents a comprehensive study of RPL, its known attacks, and the mitigation methods proposed to counter these attacks. We conducted a detailed review of the RPL standard, including a recently proposed modification. Also, we investigated all recently published attacks on RPL and their mitigation methods through the literature. Based on this investigation, and to the best of our knowledge, we introduced a first-of-its-kind classification scheme for the mitigation methods that is based on the techniques used for the mitigation. Furthermore, we thoroughly discussed RPL-based intrusion detection systems (IDSs) and their classifications, highlighting the most recently proposed IDSs. | K29: {"CorpusId": 69422280, "DBLP": "journals/comsur/RaoofML19", "DOI": "10.1109/COMST.2018.2885894", "MAG": "2904959125"} | L29: 10.1109/comst.2018.2885894 | M29: FALSE | O29: 1582-1606 | P29: 25 | R29: 95 | T29: 7; 23; 35 | U29: 21.66666666666667
A30: PRECISE | B30: e11d5a4edec55f5d5dc8ea25621ecbf89e9bccb7 | C30: Taxonomy and Survey of Collaborative Intrusion Detection | D30: 2015-05-11 | E30: 2015 | F30: JournalArticle; Review | G30: Computer Science | H30: 20 | I30: 299 | K30: {"CorpusId": 207223163, "DBLP": "journals/csur/Vasilomanolakis15", "DOI": "10.1145/2716260", "MAG": "1772700132"} | L30: 10.1145/2716260 | M30: FALSE | O30: 1 - 33 | P30: 33 | R30: 93 | T30: 17; 17; 48; 18 | U30: 25
A31: PRECISE | B31: 36cf949aca4d0b93383ec2756717404b37ef3852 | C31: A Survey of MANET Intrusion Detection & Prevention Approaches for Network Layer Attacks | D31: 2013-03-28 | E31: 2013 | F31: JournalArticle; Review | G31: Computer Science | H31: 19 | I31: 263 | K31: {"CorpusId": 18189153, "DBLP": "journals/comsur/NadeemH13", "DOI": "10.1109/SURV.2013.030713.00201", "MAG": "2036584242"} | L31: 10.1109/surv.2013.030713.00201 | M31: TRUE | N31: https://openresearch.surrey.ac.uk/view/delivery/44SUR_INST/12139983090002346/13140370410002346 | O31: 2027-2045 | P31: 19 | R31: 98 | T31: 17; 19 | U31: 18
A32: PRECISE | B32: 6edf7ed0e68bcf98ebcb600343c1e08f27c1c62f | C32: Deep Learning for Encrypted Traffic Classification: An Overview | D32: 2018-10-18 | E32: 2018 | F32: JournalArticle; Review | G32: Computer Science | H32: 19 | I32: 435 | J32: Traffic classification has been studied for two decades and applied to a wide range of applications from QoS provisioning and billing in ISPs to security-related applications in firewalls and intrusion detection systems. Port-based, data packet inspection, and classical machine learning methods have been used extensively in the past, but their accuracy has declined due to the dramatic changes in Internet traffic, particularly the increase in encrypted traffic. With the proliferation of deep learning methods, researchers have recently investigated these methods for traffic classification and reported high accuracy. In this article, we introduce a general framework for deep-learning-based traffic classification. We present commonly used deep learning methods and their application in traffic classification tasks. Then we discuss open problems, challenges, and opportunities for traffic classification. | K32: {"ArXiv": "1810.07906", "CorpusId": 53016938, "DBLP": "journals/corr/abs-1810-07906", "DOI": "10.1109/MCOM.2019.1800819", "MAG": "2897202622"} | L32: 10.1109/mcom.2019.1800819 | M32: TRUE | N32: https://arxiv.org/pdf/1810.07906 | O32: 76-81 | P32: 6 | R32: 21 | S32: 2018 | T32: 10; 9 | U32: 9.5
A33: PRECISE | B33: d3703f5faf73869110dea101109f60b4c1566c76 | C33: A Survey on Industrial Control System Testbeds and Datasets for Security Research | D33: 2021-02-10 | E33: 2021 | F33: JournalArticle; Review | G33: Computer Science | H33: 19 | I33: 154 | J33: The increasing digitization and interconnection of legacy Industrial Control Systems (ICSs) open new vulnerability surfaces, exposing such systems to malicious attackers. Furthermore, since ICSs are often employed in critical infrastructures (e.g., nuclear plants) and manufacturing companies (e.g., chemical industries), attacks can lead to devastating physical damages. In dealing with this security requirement, the research community focuses on developing new security mechanisms such as Intrusion Detection Systems (IDSs), facilitated by leveraging modern machine learning techniques. However, these algorithms require a testing platform and a considerable amount of data to be trained and tested accurately. To satisfy this prerequisite, Academia, Industry, and Government are increasingly proposing testbed (i.e., scaled-down versions of ICSs or simulations) to test the performances of the IDSs. Furthermore, to enable researchers to cross-validate security systems (e.g., security-by-design concepts or anomaly detectors), several datasets have been collected from testbeds and shared with the community. In this paper, we provide a deep and comprehensive overview of ICSs, presenting the architecture design, the employed devices, and the security protocols implemented. We then collect, compare, and describe testbeds and datasets in the literature, highlighting key challenges and design guidelines to keep in mind in the design phases. Furthermore, we enrich our work by reporting the best performing IDS algorithms tested on every dataset to create a baseline in state of the art for this field. Finally, driven by knowledge accumulated during this survey’s development, we report advice and good practices on the development, the choice, and the utilization of testbeds, datasets, and IDSs. | K33: {"ArXiv": "2102.05631", "CorpusId": 231861910, "DBLP": "journals/corr/abs-2102-05631", "DOI": "10.1109/COMST.2021.3094360"} | L33: 10.1109/comst.2021.3094360 | M33: TRUE | N33: https://arxiv.org/pdf/2102.05631 | O33: 2248-2294 | P33: 47 | R33: 234 | S33: 2020 | T33: 73; 6; 10 | U33: 29.66666666666667
A34: PRECISE | B34: 3ef1e8599ea27cafb9ccbc44619ce18729a86801 | C34: Toward Proactive, Adaptive Defense: A Survey on Moving Target Defense | D34: 2019-09-12 | E34: 2019 | F34: JournalArticle; Review | G34: Computer Science | H34: 17 | I34: 237 | J34: Reactive defense mechanisms, such as intrusion detection systems, have made significant efforts to secure a system or network for the last several decades. However, the nature of reactive security mechanisms has limitations because potential attackers cannot be prevented in advance. We are facing a reality with the proliferation of persistent, advanced, intelligent attacks while defenders are often way behind attackers in taking appropriate actions to thwart potential attackers. The concept of moving target defense (MTD) has emerged as a proactive defense mechanism aiming to prevent attacks. In this work, we conducted a comprehensive, in-depth survey to discuss the following aspects of MTD: key roles, design principles, classifications, common attacks, key methodologies, important algorithms, metrics, evaluation methods, and application domains. We discuss the pros and cons of all aspects of MTD surveyed in this work. Lastly, we highlight insights and lessons learned from this study and suggest future work directions. The aim of this paper is to provide the overall trends of MTD research in terms of critical aspects of defense systems for researchers who seek to develop proactive, adaptive MTD mechanisms. | K34: {"ArXiv": "1909.08092", "CorpusId": 202660686, "DBLP": "journals/corr/abs-1909-08092", "DOI": "10.1109/COMST.2019.2963791", "MAG": "2996903041"} | L34: 10.1109/comst.2019.2963791 | M34: TRUE | N34: http://arxiv.org/pdf/1909.08092 | O34: 709-745 | P34: 37 | R34: 195 | S34: 2019 | T34: 32; 6; 12; 10; 16; 18; 35; 27; 3 | U34: 17.66666666666667
A35: PRECISE | B35: 8b6e8d71d17a1fb5a7172c5d44ebba1cf06a7dd4 | C35: Shallow and Deep Networks Intrusion Detection System: A Taxonomy and Survey | D35: 2017-01-09 | E35: 2017 | F35: JournalArticle; Review | G35: Computer Science | H35: 17 | I35: 239 | J35: Intrusion detection has attracted a considerable interest from researchers and industries. The community, after many years of research, still faces the problem of building reliable and efficient IDS that are capable of handling large quantities of data, with changing patterns in real time situations. The work presented in this manuscript classifies intrusion detection systems (IDS). Moreover, a taxonomy and survey of shallow and deep networks intrusion detection systems is presented based on previous and current works. This taxonomy and survey reviews machine learning techniques and their performance in detecting anomalies. Feature selection which influences the effectiveness of machine learning (ML) IDS is discussed to explain the role of feature selection in the classification and training phase of ML IDS. Finally, a discussion of the false and true positive alarm rates is presented to help researchers model reliable and efficient machine learning based intrusion detection systems. | K35: {"ArXiv": "1701.02145", "CorpusId": 11381530, "DBLP": "journals/corr/HodoBHTA17", "MAG": "2576897537"} | M35: FALSE | R35: 157 | S35: 2016 | T35: 4; 19; 9; 22; 16 | U35: 14
A36: PRECISE | B36: a9b901fcd68a3715d5ef186a398476bc1e762b0e | C36: Deep Reinforcement Learning for Cyber Security | D36: 2019-06-13 | E36: 2019 | F36: JournalArticle; Review | G36: Computer Science; Mathematics; Medicine | H36: 16 | I36: 360 | J36: The scale of Internet-connected systems has increased considerably, and these systems are being exposed to cyberattacks more than ever. The complexity and dynamics of cyberattacks require protecting mechanisms to be responsive, adaptive, and scalable. Machine learning, or more specifically deep reinforcement learning (DRL), methods have been proposed widely to address these issues. By incorporating deep learning into traditional RL, DRL is highly capable of solving complex, dynamic, and especially high-dimensional cyber defense problems. This article presents a survey of DRL approaches developed for cyber security. We touch on different vital aspects, including DRL-based security methods for cyber–physical systems, autonomous intrusion detection techniques, and multiagent DRL-based game theory simulations for defense strategies against cyberattacks. Extensive discussions and future research directions on DRL-based cyber security are also given. We expect that this comprehensive review provides the foundations for and facilitates future studies on exploring the potential of emerging DRL to cope with increasingly complex cyber security problems. | K36: {"ArXiv": "1906.05799", "CorpusId": 189762438, "DBLP": "journals/corr/abs-1906-05799", "DOI": "10.1109/TNNLS.2021.3121870", "MAG": "2952298682", "PubMed": "34723814"} | L36: 10.1109/tnnls.2021.3121870 | M36: TRUE | N36: https://arxiv.org/pdf/1906.05799 | O36: 3779-3795 | P36: 17 | R36: 217 | S36: 2019 | T36: 30; 44 | U36: 37
A37: PRECISE | B37: be71e47e3247d60398d5a8dfa7d343dc4a7c27d1 | C37: Security aspects of the in-vehicle network in the connected car | D37: 2011-06-05 | E37: 2011 | F37: JournalArticle; Review | G37: Computer Science; Engineering | H37: 16 | I37: 244 | K37: {"CorpusId": 5900712, "DBLP": "conf/ivs/KlebergerOJ11", "DOI": "10.1109/IVS.2011.5940525", "MAG": "2096279841"} | L37: 10.1109/ivs.2011.5940525 | M37: FALSE | O37: 528-533 | P37: 6 | R37: 34 | T37: 7; 18; 25 | U37: 16.66666666666667
A38: PRECISE | B38: 13f5588e5a745e15e4176fd6c47c8f5befc19605 | C38: Intrusion detection and Big Heterogeneous Data: a Survey | D38: 2015-02-27 | E38: 2015 | F38: JournalArticle; Review | G38: Computer Science | H38: 15 | I38: 294 | J38: Intrusion Detection has been heavily studied in both industry and academia, but cybersecurity analysts still desire much more alert accuracy and overall threat analysis in order to secure their systems within cyberspace. Improvements to Intrusion Detection could be achieved by embracing a more comprehensive approach in monitoring security events from many different heterogeneous sources. Correlating security events from heterogeneous sources can grant a more holistic view and greater situational awareness of cyber threats. One problem with this approach is that currently, even a single event source (e.g., network traffic) can experience Big Data challenges when considered alone. Attempts to use more heterogeneous data sources pose an even greater Big Data challenge. Big Data technologies for Intrusion Detection can help solve these Big Heterogeneous Data challenges. In this paper, we review the scope of works considering the problem of heterogeneous data and in particular Big Heterogeneous Data. We discuss the specific issues of Data Fusion, Heterogeneous Intrusion Detection Architectures, and Security Information and Event Management (SIEM) systems, as well as presenting areas where more research opportunities exist. Overall, both cyber threat analysis and cyber intelligence could be enhanced by correlating security events across many diverse heterogeneous sources. | K38: {"CorpusId": 12595430, "DBLP": "journals/jbd/ZuechKW15", "DOI": "10.1186/s40537-015-0013-4", "MAG": "2108142795"} | L38: 10.1186/s40537-015-0013-4 | M38: TRUE | N38: https://journalofbigdata.springeropen.com/counter/pdf/10.1186/s40537-015-0013-4 | O38: 1-41 | P38: 41 | R38: 86 | S38: 2015 | T38: 8; 80; 22 | U38: 36.66666666666666
A39: PRECISE | B39: 260a8c49efed69f969327f4151237a38e184270b | C39: A Review of Intrusion Detection Systems Using Machine and Deep Learning in Internet of Things: Challenges, Solutions and Future Directions | D39: 2020-07-20 | E39: 2020 | F39: Review | G39: Computer Science | H39: 15 | I39: 237 | J39: The Internet of Things (IoT) is poised to impact several aspects of our lives with its fast proliferation in many areas such as wearable devices, smart sensors and home appliances. IoT devices are characterized by their connectivity, pervasiveness and limited processing capability. The number of IoT devices in the world is increasing rapidly and it is expected that there will be 50 billion devices connected to the Internet by the end of the year 2020. This explosion of IoT devices, which can be easily increased compared to desktop computers, has led to a spike in IoT-based cyber-attack incidents. To alleviate this challenge, there is a requirement to develop new techniques for detecting attacks initiated from compromised IoT devices. Machine and deep learning techniques are in this context the most appropriate detective control approach against attacks generated from IoT devices. This study aims to present a comprehensive review of IoT systems-related technologies, protocols, architecture and threats emerging from compromised IoT devices along with providing an overview of intrusion detection models. This work also covers the analysis of various machine learning and deep learning-based techniques suitable to detect IoT systems related to cyber-attacks. | K39: {"CorpusId": 225563015, "DOI": "10.3390/electronics9071177", "MAG": "3043799819"} | L39: 10.3390/electronics9071177 | M39: TRUE | N39: https://www.mdpi.com/2079-9292/9/7/1177/pdf | R39: 213 | S39: 2020 | T39: 1; 50; 4; 13; 12; 4 | U39: 14
A40: PRECISE | B40: 0fd2596df662912e293ff5efb21392581ecf0d65 | C40: On the Vital Areas of Intrusion Detection Systems in Wireless Sensor Networks | D40: 2013-01-09 | E40: 2013 | F40: JournalArticle; Review | G40: Computer Science | H40: 14 | I40: 230 | K40: {"CorpusId": 7170677, "DBLP": "journals/comsur/AbduvaliyevPZRW13", "DOI": "10.1109/SURV.2012.121912.00006", "MAG": "2121720842"} | L40: 10.1109/surv.2012.121912.00006 | M40: FALSE | O40: 1223-1237 | P40: 15 | R40: 101 | T40: 2; 30; 52; 30; 24 | U40: 27.6
A41: PRECISE | B41: 274a0c1b9bbf1f7e3f4ba3fc63b1061c2f709b85 | C41: Machine Learning-Based Network Vulnerability Analysis of Industrial Internet of Things | D41: 2019-04-18 | E41: 2019 | F41: JournalArticle; Review | G41: Computer Science | H41: 14 | I41: 323 | J41: It is critical to secure the Industrial Internet of Things (IIoT) devices because of potentially devastating consequences in case of an attack. Machine learning (ML) and big data analytics are the two powerful leverages for analyzing and securing the Internet of Things (IoT) technology. By extension, these techniques can help improve the security of the IIoT systems as well. In this paper, we first present common IIoT protocols and their associated vulnerabilities. Then, we run a cyber-vulnerability assessment and discuss the utilization of ML in countering these susceptibilities. Following that, a literature review of the available intrusion detection solutions using ML models is presented. Finally, we discuss our case study, which includes details of a real-world testbed that we have built to conduct cyber-attacks and to design an intrusion detection system (IDS). We deploy backdoor, command injection, and Structured Query Language (SQL) injection attacks against the system and demonstrate how a ML-based anomaly detection system can perform well in detecting these attacks. We have evaluated the performance through representative metrics to have a fair point of view on the effectiveness of the methods. | K41: {"ArXiv": "1911.05771", "CorpusId": 149841214, "DBLP": "journals/corr/abs-1911-05771", "DOI": "10.1109/JIOT.2019.2912022", "MAG": "2987845355"} | L41: 10.1109/jiot.2019.2912022 | M41: TRUE | N41: https://ieeexplore.ieee.org/ielx7/6488907/8784345/08693904.pdf | O41: 6822-6834 | P41: 13 | R41: 40 | S41: 2019 | T41: 12; 8; 14; 15; 60 | U41: 21.8
A42: PRECISE | B42: 662b2e2497b55bc6c14ffe96f1fcf2430b1bc7f6 | C42: Adversarial Machine Learning for Network Intrusion Detection Systems: A Comprehensive Survey | F42: JournalArticle; Review | G42: Computer Science | H42: 14 | I42: 216 | J42: Network-based Intrusion Detection System (NIDS) forms the frontline defence against network attacks that compromise the security of the data, systems, and networks. In recent years, Deep Neural Networks (DNNs) have been increasingly used in NIDS to detect malicious traffic due to their high detection accuracy. However, DNNs are vulnerable to adversarial attacks that modify an input example with imperceivable perturbation, which causes a misclassification by the DNN. In security-sensitive domains, such as NIDS, adversarial attacks pose a severe threat to network security. However, existing studies in adversarial learning against NIDS directly implement adversarial attacks designed for Computer Vision (CV) tasks, ignoring the fundamental differences in the detection pipeline and feature spaces between CV and NIDS. It remains a major research challenge to launch and detect adversarial attacks against NIDS. This article surveys the recent literature on NIDS, adversarial attacks, and network defences since 2015 to examine the differences in adversarial learning against deep neural networks in CV and NIDS. It provides the reader with a thorough understanding of DL-based NIDS, adversarial attacks and defences, and research trends in this field. We first present a taxonomy of DL-based NIDS and discuss the impact of taxonomy on adversarial learning. Next, we review existing white-box and black-box adversarial attacks on DNNs and their applicability in the NIDS domain. Finally, we review existing defence mechanisms against adversarial examples and their characteristics. | K42: {"CorpusId": 255718190, "DBLP": "journals/comsur/HeKA23", "DOI": "10.1109/COMST.2022.3233793"} | L42: 10.1109/comst.2022.3233793 | M42: FALSE | O42: 538-566 | P42: 29 | R42: 165 | T42: 11; 3; 22 | U42: 12
A43: PRECISE | B43: 8ec4b08a83faf5622fea30888a7fe14b7b0baf9b | C43: Internet of Things: A survey on machine learning-based intrusion detection approaches | D43: 2019-03-14 | E43: 2019 | F43: JournalArticle; Review | G43: Computer Science | H43: 14 | I43: 422 | K43: {"CorpusId": 86773526, "DBLP": "journals/cn/CostaPLMA19", "DOI": "10.1016/J.COMNET.2019.01.023", "MAG": "2913497771"} | L43: 10.1016/j.comnet.2019.01.023 | M43: FALSE | O43: 147-157 | P43: 11 | R43: 102 | T43: 14; 53; 1; 15; 55 | U43: 27.6
A44: PRECISE | B44: a0574a8958e9cfc5fc49bb40bc95cbfd0c190eb1 | C44: Intrusion Detection Systems in Wireless Sensor Networks: A Review | D44: 2013-05-01 | E44: 2013 | F44: JournalArticle; Review | G44: Computer Science | H44: 14 | I44: 189 | J44: Wireless Sensor Networks (WSNs) consist of sensor nodes deployed in a manner to collect information about surrounding environment. Their distributed nature, multihop data forwarding, and open wireless medium are the factors that make WSNs highly vulnerable to security attacks at various levels. Intrusion Detection Systems (IDSs) can play an important role in detecting and preventing security attacks. This paper presents current Intrusion Detection Systems and some open research problems related to WSN security. | K44: {"CorpusId": 28628245, "DBLP": "journals/ijdsn/AlrajehKS13", "DOI": "10.1155/2013/167575", "MAG": "2133140680"} | L44: 10.1155/2013/167575 | M44: TRUE | N44: https://journals.sagepub.com/doi/pdf/10.1155/2013/167575 | R44: 53 | S44: 2012 | T44: 38; 22; 28 | U44: 29.33333333333333
A45: PRECISE | B45: a30b4b52b1e7b0aff4a5085cdc43ace30ca66f5e | C45: When Intrusion Detection Meets Blockchain Technology: A Review | D45: 2018-01-30 | E45: 2018 | F45: JournalArticle; Review | G45: Computer Science | H45: 14 | I45: 405 | J45: With the purpose of identifying cyber threats and possible incidents, intrusion detection systems (IDSs) are widely deployed in various computer networks. In order to enhance the detection capability of a single IDS, collaborative intrusion detection networks (or collaborative IDSs) have been developed, which allow IDS nodes to exchange data with each other. However, data and trust management still remain two challenges for current detection architectures, which may degrade the effectiveness of such detection systems. In recent years, blockchain technology has shown its adaptability in many fields, such as supply chain management, international payment, interbanking, and so on. As blockchain can protect the integrity of data storage and ensure process transparency, it has a potential to be applied to intrusion detection domain. Motivated by this, this paper provides a review regarding the intersection of IDSs and blockchains. In particular, we introduce the background of intrusion detection and blockchain, discuss the applicability of blockchain to intrusion detection, and identify open challenges in this direction. | K45: {"CorpusId": 3932531, "DBLP": "journals/access/MengTWWH18", "DOI": "10.1109/ACCESS.2018.2799854", "MAG": "2792850657"} | L45: 10.1109/access.2018.2799854 | M45: TRUE | N45: https://doi.org/10.1109/access.2018.2799854 | O45: 10179-10188 | P45: 10 | R45: 37 | S45: 2018 | T45: 36; 16; 16; 13; 23 | U45: 20.8
A46: PRECISE | B46: ab200f31fe7c50f8b468cb3ed9274883140167d9 | C46: Feature selection for high-dimensional data | D46: 2016-02-15 | E46: 2016 | F46: JournalArticle; Review | G46: Computer Science | H46: 14 | I46: 340 | K46: {"CorpusId": 15703962, "DBLP": "journals/pai/Bolon-CanedoSA16", "DOI": "10.1007/s13748-015-0080-y"} | L46: 10.1007/s13748-015-0080-y | M46: TRUE | N46: https://link.springer.com/content/pdf/10.1007/s13748-015-0080-y.pdf | O46: 65 - 75 | P46: 11 | R46: 75 | T46: 35; 21; 36 | U46: 30.66666666666667
A47: PRECISE | B47: cffaf4cddfc4b2715b4c7900d4694d2f455530b6 | C47: 6LoWPAN: a study on QoS security threats and countermeasures using intrusion detection system approach | D47: 2012-09-01 | E47: 2012 | F47: JournalArticle; Review | G47: Computer Science | H47: 14 | I47: 150 | K47: {"CorpusId": 205738992, "DBLP": "journals/ijcomsys/LeLLAL12", "DOI": "10.1002/dac.2356", "MAG": "1816889752"} | L47: 10.1002/dac.2356 | M47: FALSE | R47: 59 | T47: 9; 30; 16; 17; 3 | U47: 15
A48: PRECISE | B48: f97424b7026d344ccab301da4da81ef292a89aee | C48: A Survey of Intrusion Detection for In-Vehicle Networks | D48: 2020-03-01 | E48: 2020 | F48: JournalArticle; Review | G48: Computer Science | H48: 14 | I48: 260 | J48: The development of the complexity and connectivity of modern automobiles has caused a massive rise in the security risks of in-vehicle networks (IVNs). Nevertheless, existing IVN designs (e.g., controller area network) lack cybersecurity consideration. Intrusion detection, an effective method for defending against cyberattacks on IVNs while providing functional safety and real-time communication guarantees, aims to address this issue. Therefore, the necessity of its research has risen. In this paper, an IVN environment is introduced, and the constraints and characteristics of an intrusion detection system (IDS) design for IVNs are presented. A survey of the proposed IDS designs for the IVNs is conducted, and the corresponding drawbacks are highlighted. Various optimization objectives are considered and comprehensively compared. Lastly, the trend, open issues, and emerging research directions are described. | K48: {"CorpusId": 181378262, "DBLP": "journals/tits/WuLXABZL20", "DOI": "10.1109/TITS.2019.2908074", "MAG": "2945012921"} | L48: 10.1109/tits.2019.2908074 | M48: FALSE | O48: 919-933 | P48: 15 | R48: 99 | T48: 5; 37; 32; 10; 7; 6; 63 | U48: 22.85714285714286
A49: PRECISE | B49: 182df25859a1e1c7ad84e846e2255f797f2b5fbd | C49: Cyberattacks and Countermeasures for In-Vehicle Networks | D49: 2020-04-22 | E49: 2020 | F49: JournalArticle; Review | G49: Computer Science | H49: 13 | I49: 156 | J49: As connectivity between and within vehicles increases, so does concern about safety and security. Various automotive serial protocols are used inside vehicles such as Controller Area Network (CAN), Local Interconnect Network (LIN), and FlexRay. CAN Bus is the most used in-vehicle network protocol to support exchange of vehicle parameters between Electronic Control Units (ECUs). This protocol lacks security mechanisms by design and is therefore vulnerable to various attacks. Furthermore, connectivity of vehicles has made the CAN Bus vulnerable not only from within the vehicle but also from outside. With the rise of connected cars, more entry points and interfaces have been introduced on board vehicles, thereby also leading to a wider potential attack surface. Existing security mechanisms focus on the use of encryption, authentication, and vehicle Intrusion Detection Systems (IDS), which operate under various constraints such as low bandwidth, small frame size (e.g., in the CAN protocol), limited availability of computational resources, and real-time sensitivity. We survey and classify current cryptographic and IDS approaches and compare these approaches based on criteria such as real-time constraints, types of hardware used, changes in CAN Bus behaviour, types of attack mitigation, and software/ hardware used to validate these approaches. We conclude with mitigation strategies limitations and research challenges for the future. | K49: {"ArXiv": "2004.10781", "CorpusId": 216080590, "DBLP": "journals/corr/abs-2004-10781", "DOI": "10.1145/3431233", "MAG": "3020635636"} | L49: 10.1145/3431233 | M49: TRUE | N49: https://arxiv.org/pdf/2004.10781 | O49: 1 - 37 | P49: 37 | R49: 176 | S49: 2020 | T49: 1; 57; 35; 42 | U49: 33.75
A50: PRECISE | B50: 18ca24000345036ce084e33a74f86693809f98a3 | C50: Deep learning methods in network intrusion detection: A survey and an objective comparison | D50: 2020-11-01 | E50: 2020 | F50: JournalArticle; Review | G50: Computer Science | H50: 13 | I50: 287 | K50: {"CorpusId": 222137305, "DBLP": "journals/jnca/GamageS20", "DOI": "10.1016/j.jnca.2020.102767", "MAG": "3047132966"} | L50: 10.1016/j.jnca.2020.102767 | M50: FALSE | O50: 102767 | R50: 76 | T50: 3; 25 | U50: 14
A51: PRECISE | B51: a7eea1d6dfbcee9a434e9ab6c9a7f67f1506d3db | C51: Intrusion detection systems for IoT-based smart environments: a survey | D51: 2018-12-01 | E51: 2018 | F51: JournalArticle; Review | G51: Computer Science | H51: 13 | I51: 350 | J51: One of the goals of smart environments is to improve the quality of human life in terms of comfort and efficiency. The Internet of Things (IoT) paradigm has recently evolved into a technology for building smart environments. Security and privacy are considered key issues in any real-world smart environment based on the IoT model. The security vulnerabilities in IoT-based systems create security threats that affect smart environment applications. Thus, there is a crucial need for intrusion detection systems (IDSs) designed for IoT environments to mitigate IoT-related security attacks that exploit some of these security vulnerabilities. Due to the limited computing and storage capabilities of IoT devices and the specific protocols used, conventional IDSs may not be an option for IoT environments. This article presents a comprehensive survey of the latest IDSs designed for the IoT model, with a focus on the corresponding methods, features, and mechanisms. This article also provides deep insight into the IoT architecture, emerging security vulnerabilities, and their relation to the layers of the IoT architecture. This work demonstrates that despite previous studies regarding the design and implementation of IDSs for the IoT paradigm, developing efficient, reliable and robust IDSs for IoT-based smart environments is still a crucial task. Key considerations for the development of such IDSs are introduced as a future outlook at the end of this survey. | K51: {"CorpusId": 54444519, "DBLP": "journals/jcloudc/ElrawyAH18", "DOI": "10.1186/s13677-018-0123-6", "MAG": "2902106343"} | L51: 10.1186/s13677-018-0123-6 | M51: TRUE | N51: https://journalofcloudcomputing.springeropen.com/track/pdf/10.1186/s13677-018-0123-6 | R51: 110 | S51: 2018 | T51: 5; 26; 20 | U51: 17
A52: PRECISE | B52: f38a103da4bfc281a811b03099e1c39751722a8c | C52: A comprehensive survey on network anomaly detection | D52: 2018-07-02 | E52: 2018 | F52: JournalArticle; Review | G52: Computer Science | H52: 13 | I52: 318 | K52: {"CorpusId": 67868677, "DBLP": "journals/telsys/FernandesRCAP19", "DOI": "10.1007/s11235-018-0475-8", "MAG": "2810550035"} | L52: 10.1007/s11235-018-0475-8 | M52: FALSE | O52: 447 - 489 | P52: 43 | R52: 174 | T52: 7; 46; 16; 34; 24 | U52: 25.4
A53: PRECISE | B53: f4179593b4b47d8be8cd97e0caced755e16fefbb | C53: A Review of Anomaly based Intrusion Detection Systems | D53: 2011-08-31 | E53: 2011 | F53: Review | G53: Computer Science | H53: 13 | I53: 405 | K53: {"CorpusId": 18977370, "DOI": "10.5120/3399-4730", "MAG": "2133590498"} | L53: 10.5120/3399-4730 | M53: TRUE | N53: http://www.ijcaonline.org/volume28/number7/pxc3874730.pdf | O53: 26-35 | P53: 10 | R53: 60 | T53: 5; 4; 4; 4; 1; 1; 1; 1; 1; 1; 1 | U53: 2.181818181818182
A54: PRECISE | B54: 7a43726fe88a102e187e39493801524e7f66ce5e | C54: Artificial intelligence, cyber-threats and Industry 4.0: challenges and opportunities | D54: 2021-02-04 | E54: 2021 | F54: JournalArticle; Review | G54: Computer Science | H54: 12 | I54: 221 | K54: {"CorpusId": 234041800, "DBLP": "journals/air/BecuePG21", "DOI": "10.1007/s10462-020-09942-2", "MAG": "3128172745"} | L54: 10.1007/s10462-020-09942-2 | M54: FALSE | O54: 3849 - 3886 | P54: 38 | R54: 195 | T54: 6; 27; 11 | U54: 14.66666666666667
A55: PRECISE | B55: 82f305d3cb1a82fb6d4a5fcabb4fda40cb2b05e0 | C55: Federated Deep Learning for Cyber Security in the Internet of Things: Concepts, Applications, and Experimental Analysis | F55: JournalArticle; Review | G55: Computer Science | H55: 12 | I55: 199 | J55: In this article, we present a comprehensive study with an experimental analysis of federated deep learning approaches for cyber security in the Internet of Things (IoT) applications. Specifically, we first provide a review of the federated learning-based security and privacy systems for several types of IoT applications, including, Industrial IoT, Edge Computing, Internet of Drones, Internet of Healthcare Things, Internet of Vehicles, etc. Second, the use of federated learning with blockchain and malware/intrusion detection systems for IoT applications is discussed. Then, we review the vulnerabilities in federated learning-based security and privacy systems. Finally, we provide an experimental analysis of federated deep learning with three deep learning approaches, namely, Recurrent Neural Network (RNN), Convolutional Neural Network (CNN), and Deep Neural Network (DNN). For each deep learning model, we study the performance of centralized and federated learning under three new real IoT traffic datasets, namely, the Bot-IoT dataset, the MQTTset dataset, and the TON_IoT dataset. The goal of this article is to provide important information on federated deep learning approaches with emerging technologies for cyber security. In addition, it demonstrates that federated deep learning approaches outperform the classic/centralized versions of machine learning (non-federated learning) in assuring the privacy of IoT device data and provide the higher accuracy in detecting attacks. | K55: {"CorpusId": 238994219, "DBLP": "journals/access/FerragFMJS21", "DOI": "10.1109/access.2021.3118642"} | L55: 10.1109/access.2021.3118642 | M55: TRUE | N55: https://ieeexplore.ieee.org/ielx7/6287639/6514899/09562531.pdf | O55: 1-1 | P55: 1 | R55: 164 | S55: 2023 | T55: 41; 8; 41; 33 | U55: 30.75
A56: PRECISE | B56: 86337602a24dfdfb65f3c26a81bb3f1f417f36a4 | C56: A review paper on IDS classification using KDD 99 and NSL KDD dataset in WEKA | D56: 2017-07-01 | E56: 2017 | F56: Conference; Review | G56: Computer Science | H56: 12 | I56: 119 | K56: {"CorpusId": 23063250, "DOI": "10.1109/COMPTELIX.2017.8004032", "MAG": "2744338514"} | L56: 10.1109/comptelix.2017.8004032 | M56: FALSE | O56: 553-558 | P56: 6 | R56: 16 | T56: 16; 5 | U56: 10.5
A57: PRECISE | B57: 9196214e8f81b4a6efda6c8891a6365bccf865df | C57: Explainable Artificial Intelligence in CyberSecurity: A Survey | F57: JournalArticle; Review | G57: Computer Science | H57: 12 | I57: 138 | J57: Nowadays, Artificial Intelligence (AI) is widely applied in every area of human being’s daily life. Despite the AI benefits, its application suffers from the opacity of complex internal mechanisms and doesn’t satisfy by design the principles of Explainable Artificial Intelligence (XAI). The lack of transparency further exacerbates the problem in the field of CyberSecurity because entrusting crucial decisions to a system that cannot explain itself presents obvious dangers. There are several methods in the literature capable of providing explainability of AI results. Anyway, the application of XAI in CyberSecurity can be a double-edged sword. It substantially improves the CyberSecurity practices but simultaneously leaves the system vulnerable to adversary attacks. Therefore, there is a need to analyze the state-of-the-art of XAI methods in CyberSecurity to provide a clear vision for future research. This study presents an in-depth examination of the application of XAI in CyberSecurity. It considers more than 300 papers to comprehensively analyze the main CyberSecurity application fields, like Intrusion Detection Systems, Malware detection, Phishing and Spam detection, BotNets detection, Fraud detection, Zero-Day vulnerabilities, Digital Forensics and Crypto-Jacking. Specifically, this study focuses on the explainability methods adopted or proposed in these fields, pointing out promising works and new challenges. | K57: {"CorpusId": 252107164, "DBLP": "journals/access/CapuanoFLS22", "DOI": "10.1109/ACCESS.2022.3204171"} | L57: 10.1109/access.2022.3204171 | M57: TRUE | N57: https://ieeexplore.ieee.org/ielx7/6287639/6514899/09877919.pdf | O57: 93575-93600 | P57: 26 | R57: 235 | S57: 2022 | T57: 5; 23; 11; 5 | U57: 11
A58: PRECISE | B58: 2925a374d23127cc58027b4437a3f1dea8f02844 | C58: A Survey of Distance and Similarity Measures Used Within Network Intrusion Anomaly Detection | F58: JournalArticle; Review | G58: Computer Science | H58: 11 | I58: 192 | K58: {"CorpusId": 26690303, "DBLP": "journals/comsur/Weller-FahyBS15", "DOI": "10.1109/COMST.2014.2336610", "MAG": "2093859880"} | L58: 10.1109/comst.2014.2336610 | M58: TRUE | N58: https://ieeexplore.ieee.org/ielx7/9739/7061782/06853338.pdf | O58: 70-91 | P58: 22 | R58: 124 | T58: 3; 14; 7 | U58: 8
A59: PRECISE | B59: 6a0e4209529b827cd86a52a4766968001a3f187c | C59: Deep learning approaches for anomaly-based intrusion detection systems: A survey, taxonomy, and open issues | D59: 2020-02-01 | E59: 2020 | F59: JournalArticle; Review | G59: Computer Science | H59: 11 | I59: 465 | K59: {"CorpusId": 208103146, "DBLP": "journals/kbs/AldweeshDE20", "DOI": "10.1016/j.knosys.2019.105124", "MAG": "2981025625"} | L59: 10.1016/j.knosys.2019.105124 | M59: FALSE | R59: 101 | T59: 2; 35; 15 | U59: 17.33333333333333
A60: PRECISE | B60: b6550136304974682bde7ca9b2a8e21c2ea91982 | C60: Evaluating Federated Learning for Intrusion Detection in Internet of Things: Review and Challenges | D60: 2021-08-02 | E60: 2021 | F60: JournalArticle; Review | G60: Computer Science | H60: 11 | I60: 177 | K60: {"ArXiv": "2108.00974", "CorpusId": 236772273, "DBLP": "journals/corr/abs-2108-00974", "DOI": "10.1016/j.comnet.2021.108661"} | L60: 10.1016/j.comnet.2021.108661 | M60: TRUE | N60: https://doi.org/10.1016/j.comnet.2021.108661 | R60: 103 | S60: 2021 | T60: 3; 2; 19; 24; 26; 26; 54 | U60: 22
A61: PRECISE | B61: bfab9d89e492baa47b4fce6bc5d6be6e6def6842 | C61: Performance Analysis of Machine Learning Algorithms in Intrusion Detection System: A Review | F61: Review | G61: Computer Science | H61: 11 | I61: 275 | K61: {"CorpusId": 226450892, "DOI": "10.1016/j.procs.2020.04.133", "MAG": "3033403042"} | L61: 10.1016/j.procs.2020.04.133 | M61: TRUE | N61: https://doi.org/10.1016/j.procs.2020.04.133 | R61: 15 | S61: 2019 | T61: 3; 7; 9; 12; 3 | U61: 6.8
A62: PRECISE | B62: d09c60cd3e493923b63ae170ad1daaf9f6cb1a69 | C62: A review of KDD99 dataset usage in intrusion detection and machine learning between 2010 and 2015 | D62: 2016-04-14 | E62: 2016 | F62: JournalArticle; Review | G62: Computer Science | H62: 11 | I62: 158 | K62: {"CorpusId": 12395887, "DBLP": "journals/peerjpre/OzgurE16", "DOI": "10.7287/peerj.preprints.1954v1", "MAG": "2336023257"} | L62: 10.7287/peerj.preprints.1954v1 | M62: TRUE | N62: https://doi.org/10.7287/peerj.preprints.1954v1 | O62: e1954 | R62: 24 | T62: 7; 11 | U62: 9
A63: PRECISE | B63: 0a9f0b436b610d4cef1a022ab6083ac2278dc7e2 | C63: Data preprocessing for anomaly based network intrusion detection: A review | D63: 2011-05-25 | E63: 2011 | F63: JournalArticle; Review | G63: Computer Science | H63: 10 | I63: 316 | K63: {"CorpusId": 5989195, "DBLP": "journals/compsec/DavisC11", "DOI": "10.1016/J.COSE.2011.05.008", "MAG": "1528764835"} | L63: 10.1016/j.cose.2011.05.008 | M63: FALSE | O63: 353-375 | P63: 23 | R63: 81 | T63: 3; 29 | U63: 16
A64: PRECISE | B64: 310a06c774cfdef1f011a44920638ad52658c860 | C64: AI-Based Intrusion Detection Systems for In-Vehicle Networks: A Survey | D64: 2022-11-09 | E64: 2022 | F64: JournalArticle; Review | G64: Computer Science | H64: 10 | I64: 136 | J64: The Controller Area Network (CAN) is the most widely used in-vehicle communication protocol, which still lacks the implementation of suitable security mechanisms such as message authentication and encryption. This makes the CAN bus vulnerable to numerous cyber attacks. Various Intrusion Detection Systems (IDSs) have been developed to detect these attacks. However, the high generalization capabilities of Artificial Intelligence (AI) make AI-based IDS an excellent countermeasure against automotive cyber attacks. This article surveys AI-based in-vehicle IDS from 2016 to 2022 (August) with a novel taxonomy. It reviews the detection techniques, attack types, features, and benchmark datasets. Furthermore, the article discusses the security of AI models, necessary steps to develop AI-based IDSs in the CAN bus, identifies the limitations of existing proposals, and gives recommendations for future research directions. | K64: {"CorpusId": 253399087, "DBLP": "journals/csur/RajapakshaKAPMC23", "DOI": "10.1145/3570954"} | L64: 10.1145/3570954 | M64: TRUE | N64: https://dl.acm.org/doi/pdf/10.1145/3570954 | O64: 1 - 40 | P64: 40 | R64: 187 | T64: 6; 11; 11; 19; 7; 11 | U64: 10.83333333333333
A65: PRECISE | B65: 3ba55ec932c20e95f21e1fef1471ab6a5767758b | C65: A critical review of intrusion detection systems in the internet of things: techniques, deployment strategy, validation strategy, attacks, public datasets and challenges | D65: 2021-03-08 | E65: 2021 | F65: JournalArticle; Review | G65: Computer Science | H65: 10 | I65: 321 | J65: The Internet of Things (IoT) has been rapidly evolving towards making a greater impact on everyday life to large industrial systems. Unfortunately, this has attracted the attention of cybercriminals who made IoT a target of malicious activities, opening the door to a possible attack on the end nodes. To this end, Numerous IoT intrusion detection Systems (IDS) have been proposed in the literature to tackle attacks on the IoT ecosystem, which can be broadly classified based on detection technique, validation strategy, and deployment strategy. This survey paper presents a comprehensive review of contemporary IoT IDS and an overview of techniques, deployment Strategy, validation strategy and datasets that are commonly applied for building IDS. We also review how existing IoT IDS detect intrusive attacks and secure communications on the IoT. It also presents the classification of IoT attacks and discusses future research challenges to counter such IoT attacks to make IoT more secure. These purposes help IoT security researchers by uniting, contrasting, and compiling scattered research efforts. Consequently, we provide a unique IoT IDS taxonomy, which sheds light on IoT IDS techniques, their advantages and disadvantages, IoT attacks that exploit IoT communication systems, corresponding advanced IDS and detection capabilities to detect IoT attacks. | K65: {"CorpusId": 232145452, "DBLP": "journals/cybersec/KhraisatA21", "DOI": "10.1186/s42400-021-00077-7"} | L65: 10.1186/s42400-021-00077-7 | M65: TRUE | N65: https://cybersecurity.springeropen.com/counter/pdf/10.1186/s42400-021-00077-7 | R65: 103 | S65: 2020 | T65: 14; 16 | U65: 15
A66: PRECISE | B66: 4c30d041c137948aa75e40912f14558234bf1ce2 | C66: A Survey on Machine Learning Techniques for Cyber Security in the Last Decade | F66: JournalArticle; Review | G66: Computer Science | H66: 10 | I66: 297 | J66: Pervasive growth and usage of the Internet and mobile applications have expanded cyberspace. The cyberspace has become more vulnerable to automated and prolonged cyberattacks. Cyber security techniques provide enhancements in security measures to detect and react against cyberattacks. The previously used security systems are no longer sufficient because cybercriminals are smart enough to evade conventional security systems. Conventional security systems lack efficiency in detecting previously unseen and polymorphic security attacks. Machine learning (ML) techniques are playing a vital role in numerous applications of cyber security. However, despite the ongoing success, there are significant challenges in ensuring the trustworthiness of ML systems. There are incentivized malicious adversaries present in the cyberspace that are willing to game and exploit such ML vulnerabilities. This paper aims to provide a comprehensive overview of the challenges that ML techniques face in protecting cyberspace against attacks, by presenting a literature on ML techniques for cyber security including intrusion detection, spam detection, and malware detection on computer networks and mobile networks in the last decade. It also provides brief descriptions of each ML method, frequently used security datasets, essential ML tools, and evaluation metrics to evaluate a classification model. It finally discusses the challenges of using ML techniques in cyber security. This paper provides the latest extensive bibliography and the current trends of ML in cyber security. | K66: {"CorpusId": 229375374, "DBLP": "journals/access/ShaukatLVHX20", "DOI": "10.1109/ACCESS.2020.3041951", "MAG": "3108671495"} | L66: 10.1109/access.2020.3041951 | M66: TRUE | N66: https://ieeexplore.ieee.org/ielx7/6287639/6514899/09277523.pdf | O66: 222310-222354 | P66: 45 | R66: 629 | S66: 2022 | T66: 32; 44; 44; 36; 12 | U66: 33.6
A67: PRECISE | B67: 5e2ef6abd77e9d3512e4f9ba694d7c6ad35c8db5 | C67: Explainable Artificial Intelligence Applications in Cyber Security: State-of-the-Art in Research | D67: 2022-08-31 | E67: 2022 | F67: JournalArticle; Review | G67: Computer Science | H67: 10 | I67: 191 | J67: This survey presents a comprehensive review of current literature on Explainable Artificial Intelligence (XAI) methods for cyber security applications. Due to the rapid development of Internet-connected systems and Artificial Intelligence in recent years, Artificial Intelligence including Machine Learning (ML) and Deep Learning (DL) has been widely utilized in the fields of cyber security including intrusion detection, malware detection, and spam filtering. However, although Artificial Intelligence-based approaches for the detection and defense of cyber attacks and threats are more advanced and efficient compared to the conventional signature-based and rule-based cyber security strategies, most ML-based techniques and DL-based techniques are deployed in the “black-box” manner, meaning that security experts and customers are unable to explain how such procedures reach particular conclusions. The deficiencies of transparencies and interpretability of existing Artificial Intelligence techniques would decrease human users’ confidence in the models utilized for the defense against cyber attacks, especially in current situations where cyber attacks become increasingly diverse and complicated. Therefore, it is essential to apply XAI in the establishment of cyber security models to create more explainable models while maintaining high accuracy and allowing human users to comprehend, trust, and manage the next generation of cyber defense mechanisms. Although there are papers reviewing Artificial Intelligence applications in cyber security areas and the vast literature on applying XAI in many fields including healthcare, financial services, and criminal justice, the surprising fact is that there are currently no survey research articles that concentrate on XAI applications in cyber security. Therefore, the motivation behind the survey is to bridge the research gap by presenting a detailed and up-to-date survey of XAI approaches applicable to issues in the cyber security field. Our work is the first to propose a clear roadmap for navigating the XAI literature in the context of applications in cyber security. | K67: {"ArXiv": "2208.14937", "CorpusId": 251953638, "DBLP": "journals/corr/abs-2208-14937", "DOI": "10.1109/ACCESS.2022.3204051"} | L67: 10.1109/access.2022.3204051 | M67: TRUE | N67: https://ieeexplore.ieee.org/ielx7/6287639/6514899/09875264.pdf | O67: 93104-93139 | P67: 36 | R67: 279 | S67: 2022 | T67: 6; 15; 19; 34; 7 | U67: 16.2
A68: PRECISE | B68: 60913732461b3054f4a6b95869f2e14bc5137514 | C68: A survey on Intrusion Detection Systems and Honeypot based proactive security mechanisms in VANETs and VANET Cloud | D68: 2018-04-01 | E68: 2018 | F68: JournalArticle; Review | G68: Computer Science | H68: 10 | I68: 165 | K68: {"CorpusId": 49326208, "DBLP": "journals/vcomm/SharmaK18a", "DOI": "10.1016/J.VEHCOM.2018.04.005", "MAG": "2801555828"} | L68: 10.1016/j.vehcom.2018.04.005 | M68: FALSE | O68: 138-164 | P68: 27 | R68: 67 | T68: 17; 14 | U68: 15.5
A69: PRECISE | B69: b42590f5f9bf7802d453dbe89544f27cc3f1b058 | C69: Wireless Sensing for Human Activity: A Survey | D69: 2020-07-01 | E69: 2020 | F69: JournalArticle; Review | G69: Computer Science | H69: 10 | I69: 306 | J69: With the advancement of wireless technologies and sensing methodologies, many studies have shown the success of re-using wireless signals (e.g., WiFi) to sense human activities and thereby realize a set of emerging applications, ranging from intrusion detection, daily activity recognition, gesture recognition to vital signs monitoring and user identification involving even finer-grained motion sensing. These applications arguably can brace various domains for smart home and office environments, including safety protection, well-being monitoring/management, smart healthcare and smart-appliance interaction. The movements of the human body impact the wireless signal propagation (e.g., reflection, diffraction and scattering), which provide great opportunities to capture human motions by analyzing the received wireless signals. Researchers take the advantage of the existing wireless links among mobile/smart devices (e.g., laptops, smartphones, smart thermostats, smart refrigerators and virtual assistance systems) by either extracting the ready-to-use signal measurements or adopting frequency modulated signals to detect the frequency shift. Due to the low-cost and non-intrusive sensing nature, wireless-based human activity sensing has drawn considerable attention and become a prominent research field over the past decade. In this paper, we survey the existing wireless sensing systems in terms of their basic principles, techniques and system structures. Particularly, we describe how the wireless signals could be utilized to facilitate an array of applications including intrusion detection, room occupancy monitoring, daily activity recognition, gesture recognition, vital signs monitoring, user identification and indoor localization. The future research directions and limitations of using wireless signals for human activity sensing are also discussed. | K69: {"CorpusId": 201885338, "DBLP": "journals/comsur/LiuLCWW20", "DOI": "10.1109/COMST.2019.2934489", "MAG": "2968303571"} | L69: 10.1109/comst.2019.2934489 | M69: TRUE | N69: https://doi.org/10.1109/comst.2019.2934489 | O69: 1629-1645 | P69: 17 | R69: 140 | T69: 32; 36; 63; 26; 17 | U69: 34.8
A70: PRECISE | B70: ef9dbef4909964b78d948de321b60e43e4ea0105 | C70: Cyber Security Intrusion Detection for Agriculture 4.0: Machine Learning-Based Solutions, Datasets, and Future Directions | D70: 2022-03-01 | E70: 2022 | F70: JournalArticle; Review | G70: Computer Science | H70: 10 | I70: 80 | J70: In this paper, we review and analyze intrusion detection systems for Agriculture 4.0 cyber security. Specifically, we present cyber security threats and evaluation metrics used in the performance evaluation of an intrusion detection system for Agriculture 4.0. Then, we evaluate intrusion detection systems according to emerging technologies, including, Cloud computing, Fog/Edge computing, Network virtualization, Autonomous tractors, Drones, Internet of Things, Industrial agriculture, and Smart Grids. Based on the machine learning technique used, we provide a comprehensive classification of intrusion detection systems in each emerging technology. Furthermore, we present public datasets, and the implementation frameworks applied in the performance evaluation of intrusion detection systems for Agriculture 4.0. Finally, we outline challenges and future research directions in cyber security intrusion detection for Agriculture 4.0. | K70: {"CorpusId": 245074394, "DBLP": "journals/ieeejas/FerragSFY22", "DOI": "10.1109/jas.2021.1004344"} | L70: 10.1109/jas.2021.1004344 | M70: FALSE | O70: 407-436 | P70: 30 | R70: 0 | T70: 41; 2; 3; 7 | U70: 13.25
A71: PRECISE | B71: 082be2d2cef8cbc59b887680e767ffdc7bdfbda5 | C71: A Survey of Honeypots and Honeynets for Internet of Things, Industrial Internet of Things, and Cyber-Physical Systems | D71: 2021-08-04 | E71: 2021 | F71: JournalArticle; Review | G71: Computer Science | H71: 9 | I71: 163 | J71: The Internet of Things (IoT), the Industrial Internet of Things (IIoT), and Cyber-Physical Systems (CPS) have become essential for our daily lives in contexts such as our homes, buildings, cities, health, transportation, manufacturing, infrastructure, and agriculture. However, they have become popular targets of attacks, due to their inherent limitations which create vulnerabilities. Honeypots and honeynets can prove essential to understand and defend against attacks on IoT, IIoT, and CPS environments by attracting attackers and deceiving them into thinking that they have gained access to the real systems. Honeypots and honeynets can complement other security solutions (i.e., firewalls, Intrusion Detection Systems - IDS) to form a strong defense against malicious entities. This paper provides a comprehensive survey of the research that has been carried out on honeypots and honeynets for IoT, IIoT, and CPS. It provides a taxonomy and extensive analysis of the existing honeypots and honeynets, states key design factors for the state-of-the-art honeypot/honeynet research and outlines open issues for future honeypots and honeynets for IoT, IIoT, and CPS environments. | K71: {"ArXiv": "2108.02287", "CorpusId": 236924363, "DBLP": "journals/corr/abs-2108-02287", "DOI": "10.1109/comst.2021.3106669"} | L71: 10.1109/comst.2021.3106669 | M71: TRUE | N71: https://doi.org/10.1109/comst.2021.3106669 | O71: 2351-2383 | P71: 33 | R71: 164 | S71: 2021 | T71: 4; 14; 23; 30 | U71: 17.75
A72: PRECISE | B72: 26e67cf3155910f52c27846170cc7f8bbf3caf02 | C72: Survey of Network Intrusion Detection Methods From the Perspective of the Knowledge Discovery in Databases Process | D72: 2020-01-27 | E72: 2020 | F72: JournalArticle; Review | G72: Computer Science | H72: 9 | I72: 86 | J72: The identification of network attacks which target information and communication systems has been a focus of the research community for years. Network intrusion detection is a complex problem which presents a diverse number of challenges. Many attacks currently remain undetected, while newer ones emerge due to the proliferation of connected devices and the evolution of communication technology. In this survey, we review the methods that have been applied to network data with the purpose of developing an intrusion detector, but contrary to previous reviews in the area, we analyze them from the perspective of the Knowledge Discovery in Databases (KDD) process. As such, we discuss the techniques used for the collecion, preprocessing and transformation of the data, as well as the data mining and evaluation methods. We also present the characteristics and motivations behind the use of each of these techniques and propose more adequate and up-to-date taxonomies and definitions for intrusion detectors based on the terminology used in the area of data mining and KDD. Special importance is given to the evaluation procedures followed to assess the detectors, discussing their applicability in current, real networks. Finally, as a result of this literature review, we investigate some open issues which will need to be considered for further research in the area of network security. | K72: {"ArXiv": "2001.09697", "CorpusId": 210920646, "DBLP": "journals/corr/abs-2001-09697", "DOI": "10.1109/TNSM.2020.3016246", "MAG": "3001683812"} | L72: 10.1109/tnsm.2020.3016246 | M72: TRUE | N72: https://arxiv.org/pdf/2001.09697 | O72: 2451-2479 | P72: 29 | R72: 229 | S72: 2020 | T72: 3; 12; 24; 21 | U72: 15
A73: PRECISE | B73: 422820179de6e740294f08652adef3608eb7449d | C73: Intrusion Detection Systems for Intra-Vehicle Networks: A Review | D73: 2019-02-14 | E73: 2019 | F73: JournalArticle; Review | G73: Computer Science | H73: 9 | I73: 145 | J73: A modern vehicle is a complex system of sensors, electronic control units, and actuators connected through different types of intra-vehicle networks to control and monitor the state of the vehicle. In addition, modern vehicles are becoming increasingly connected to the outside world through V2X technologies. However, these provide new attack surfaces that increase the cybersecurity risk to modern vehicles. To this end, there are two distinct and key challenges that need to be addressed to ensure safety and consumer trust. While modern vehicles must be equipped with the best countermeasures against cybersecurity threats, a reliable mechanism shall be also in place to detect the potential intrusions of the system while in operation, which is termed as intrusion detection. This paper provides a structured and comprehensive review of the state of the art of the intra-vehicle intrusion detection systems (IDSs) for passenger vehicles. We first provide an overview of intra-vehicle networks before reviewing contemporary research in intra-vehicle IDSs. The approach employed is to categorize the reviewed works based on their detection technique and to examine the used feature and feature selection methods, evaluation dataset, attack type, performance metrics, and benchmark models. This paper also presents outstanding research challenges and gaps in intra-vehicle IDS research. | K73: {"CorpusId": 86751803, "DBLP": "journals/access/Al-JarrahMDOM19", "DOI": "10.1109/ACCESS.2019.2894183", "MAG": "2914845865"} | L73: 10.1109/access.2019.2894183 | M73: TRUE | N73: https://ieeexplore.ieee.org/ielx7/6287639/8600701/08642311.pdf | O73: 21266-21289 | P73: 24 | R73: 81 | S73: 2018 | T73: 13; 38; 41; 7; 23 | U73: 24.4
A74: PRECISE | B74: 48f2ab8184b9d6abaafc8ee23b292ae775f72128 | C74: Benchmarking of Machine Learning for Anomaly Based Intrusion Detection Systems in the CICIDS2017 Dataset | D74: 2021-02-03 | E74: 2021 | F74: JournalArticle; Review | G74: Computer Science | H74: 9 | I74: 264 | J74: An intrusion detection system (IDS) is an important protection instrument for detecting complex network attacks. Various machine learning (ML) or deep learning (DL) algorithms have been proposed for implementing anomaly-based IDS (AIDS). Our review of the AIDS literature identifies some issues in related work, including the randomness of the selected algorithms, parameters, and testing criteria, the application of old datasets, or shallow analyses and validation of the results. This paper comprehensively reviews previous studies on AIDS by using a set of criteria with different datasets and types of attacks to set benchmarking outcomes that can reveal the suitable AIDS algorithms, parameters, and testing criteria. Specifically, this paper applies 10 popular supervised and unsupervised ML algorithms for identifying effective and efficient ML–AIDS of networks and computers. These supervised ML algorithms include the artificial neural network (ANN), decision tree (DT), k-nearest neighbor (k-NN), naive Bayes (NB), random forest (RF), support vector machine (SVM), and convolutional neural network (CNN) algorithms, whereas the unsupervised ML algorithms include the expectation-maximization (EM), k-means, and self-organizing maps (SOM) algorithms. Several models of these algorithms are introduced, and the turning and training parameters of each algorithm are examined to achieve an optimal classifier evaluation. Unlike previous studies, this study evaluates the performance of AIDS by measuring the true positive and negative rates, accuracy, precision, recall, and F-Score of 31 ML-AIDS models. The training and testing time for ML-AIDS models are also considered in measuring their performance efficiency given that time complexity is an important factor in AIDSs. The ML-AIDS models are tested by using a recent and highly unbalanced multiclass CICIDS2017 dataset that involves real-world network attacks. In general, the k-NN-AIDS, DT-AIDS, and NB-AIDS models obtain the best results and show a greater capability in detecting web attacks compared with other models that demonstrate irregular and inferior results. | K74: {"CorpusId": 231914286, "DBLP": "journals/access/MaseerYBMF21", "DOI": "10.1109/ACCESS.2021.3056614", "MAG": "3126814579"} | L74: 10.1109/access.2021.3056614 | M74: TRUE | N74: https://ieeexplore.ieee.org/ielx7/6287639/9312710/09345704.pdf | O74: 22351-22370 | P74: 20 | R74: 96 | S74: 2020 | T74: 3; 13; 6; 40; 12 | U74: 14.8
A75: PRECISE | B75: 517e3d378692bde221dda5054bbae8a483d8d4f0 | C75: Survey of Intrusion Detection Systems towards an End to End Secure Internet of Things | D75: 2016-08-01 | E75: 2016 | F75: Conference; JournalArticle; Review | G75: Computer Science | H75: 9 | I75: 119 | K75: {"CorpusId": 1366247, "DBLP": "conf/ficloud/GendreauM16", "DOI": "10.1109/FiCloud.2016.20", "MAG": "2523827785"} | L75: 10.1109/ficloud.2016.20 | M75: FALSE | O75: 84-90 | P75: 7 | R75: 35 | T75: 3; 1 | U75: 2
A76: PRECISE | B76: 68457bf1432b6667a8802d2d8c7ed9a145bede6a | C76: A Survey on Smart Agriculture: Development Modes, Technologies, and Security and Privacy Challenges | D76: 2021-02-01 | E76: 2021 | F76: JournalArticle; Review | G76: Business; Computer Science | H76: 9 | I76: 263 | J76: With the deep combination of both modern information technology and traditional agriculture, the era of agriculture 4.0, which takes the form of smart agriculture, has come. Smart agriculture provides solutions for agricultural intelligence and automation. However, information security issues cannot be ignored with the development of agriculture brought by modern information technology. In this paper, three typical development modes of smart agriculture (precision agriculture, facility agriculture, and order agriculture) are presented. Then, 7 key technologies and 11 key applications are derived from the above modes. Based on the above technologies and applications, 6 security and privacy countermeasures (authentication and access control, privacy-preserving, blockchain-based solutions for data integrity, cryptography and key management, physical countermeasures, and intrusion detection systems) are summarized and discussed. Moreover, the security challenges of smart agriculture are analyzed and organized into two aspects: 1) agricultural production, and 2) information technology. Most current research projects have not taken agricultural equipment as potential security threats. Therefore, we did some additional experiments based on solar insecticidal lamps Internet of Things, and the results indicate that agricultural equipment has an impact on agricultural security. Finally, more technologies (5 G communication, fog computing, Internet of Everything, renewable energy management system, software defined network, virtual reality, augmented reality, and cyber security datasets for smart agriculture) are described as the future research directions of smart agriculture. | K76: {"CorpusId": 229624746, "DBLP": "journals/ieeejas/YangSCFWNH21", "DOI": "10.1109/JAS.2020.1003536", "MAG": "3110407708"} | L76: 10.1109/jas.2020.1003536 | M76: TRUE | N76: https://figshare.com/articles/journal_contribution/A_Survey_on_Smart_Agriculture_Development_Modes_Technologies_and_Security_and_Privacy_Challenges/24389191/1/files/42795154.pdf | O76: 273-302 | P76: 30 | R76: 168 | S76: 2021 | T76: 7; 66; 1; 41; 10; 10 | U76: 22.5
A77: PRECISE | B77: 6f5b87e38cfb4a47e3ac7988cca5612ccf0a2946 | C77: Detecting Cybersecurity Attacks in Internet of Things Using Artificial Intelligence Methods: A Systematic Literature Review | D77: 2022-01-10 | E77: 2022 | F77: Review | H77: 9 | I77: 221 | J77: In recent years, technology has advanced to the fourth industrial revolution (Industry 4.0), where the Internet of things (IoTs), fog computing, computer security, and cyberattacks have evolved exponentially on a large scale. The rapid development of IoT devices and networks in various forms generate enormous amounts of data which in turn demand careful authentication and security. Artificial intelligence (AI) is considered one of the most promising methods for addressing cybersecurity threats and providing security. In this study, we present a systematic literature review (SLR) that categorize, map and survey the existing literature on AI methods used to detect cybersecurity attacks in the IoT environment. The scope of this SLR includes an in-depth investigation on most AI trending techniques in cybersecurity and state-of-art solutions. A systematic search was performed on various electronic databases (SCOPUS, Science Direct, IEEE Xplore, Web of Science, ACM, and MDPI). Out of the identified records, 80 studies published between 2016 and 2021 were selected, surveyed and carefully assessed. This review has explored deep learning (DL) and machine learning (ML) techniques used in IoT security, and their effectiveness in detecting attacks. However, several studies have proposed smart intrusion detection systems (IDS) with intelligent architectural frameworks using AI to overcome the existing security and privacy challenges. It is found that support vector machines (SVM) and random forest (RF) are among the most used methods, due to high accuracy detection another reason may be efficient memory. In addition, other methods also provide better performance such as extreme gradient boosting (XGBoost), neural networks (NN) and recurrent neural networks (RNN). This analysis also provides an insight into the AI roadmap to detect threats based on attack categories. Finally, we present recommendations for potential future investigations. | K77: {"CorpusId": 245858079, "DOI": "10.3390/electronics11020198"} | L77: 10.3390/electronics11020198 | M77: TRUE | N77: https://www.mdpi.com/2079-9292/11/2/198/pdf?version=1642487277 | R77: 101 | S77: 2021 | T77: 7; 17; 22; 16; 11; 40; 24 | U77: 19.57142857142857
A78: PRECISE | B78: b1754f209110eb0dd13cf2ccf35b7f113b7e65ef | C78: A Survey of Intrusion Detection Systems Leveraging Host Data | D78: 2019-11-14 | E78: 2019 | F78: JournalArticle; Review | G78: Computer Science | H78: 9 | I78: 121 | J78: This survey focuses on intrusion detection systems (IDS) that leverage host-based data sources for detecting attacks on enterprise network. The host-based IDS (HIDS) literature is organized by the input data source, presenting targeted sub-surveys of HIDS research leveraging system logs, audit data, Windows Registry, file systems, and program analysis. While system calls are generally included in audit data, several publicly available system call datasets have spawned a flurry of IDS research on this topic, which merits a separate section. To accommodate current researchers, a section giving descriptions of publicly available datasets is included, outlining their characteristics and shortcomings when used for IDS evaluation. Related surveys are organized and described. All sections are accompanied by tables concisely organizing the literature and datasets discussed. Finally, challenges, trends, and broader observations are throughout the survey and in the conclusion along with future directions of IDS research. Overall, this survey was designed to allow easy access to the diverse types of data available on a host for sensing intrusion, the progressions of research using each, and the accessible datasets for prototyping in the area. | K78: {"CorpusId": 21690024, "DBLP": "journals/csur/BridgesGIVC20", "DOI": "10.1145/3344382", "MAG": "2988790801"} | L78: 10.1145/3344382 | M78: TRUE | N78: https://dl.acm.org/doi/pdf/10.1145/3344382 | O78: 1 - 35 | P78: 35 | R78: 213 | T78: 20; 1; 13; 2; 14 | U78: 10
A79: PRECISE | B79: ea530e2a2511b04bea962a72b3e4504890a2a882 | C79: From Intrusion Detection to Attacker Attribution: A Comprehensive Survey of Unsupervised Methods | D79: 2018-07-12 | E79: 2018 | F79: JournalArticle; Review | G79: Computer Science | H79: 9 | I79: 169 | K79: {"CorpusId": 53779029, "DBLP": "journals/comsur/NisiotiMYK18", "DOI": "10.1109/COMST.2018.2854724", "MAG": "2870670057"} | L79: 10.1109/comst.2018.2854724 | M79: TRUE | N79: http://eprints.bournemouth.ac.uk/30985/1/IEEE%20COMST%2018%20-%20From_intrusion_detection_to_attribution_.pdf | O79: 3369-3388 | P79: 20 | R79: 99 | T79: 6; 21; 27; 20 | U79: 18.5
A80: PRECISE | B80: 05f35907dd815c9a4d5b431a8367842f19b57830 | C80: The virtual network function placement problem | D80: 2015-08-06 | E80: 2015 | F80: Conference; JournalArticle; Review | G80: Computer Science | H80: 8 | I80: 57 | K80: {"CorpusId": 7046406, "DBLP": "conf/infocom/LiQ15", "DOI": "10.1109/INFCOMW.2015.7179347", "MAG": "1510173822"} | L80: 10.1109/infcomw.2015.7179347 | M80: FALSE | O80: 69-70 | P80: 2 | R80: 10 | T80: 15; 18 | U80: 16.5
A81: PRECISE | B81: 09f3f60a63a03b11c0135cb5fa5aa82365180a4f | C81: Internet of Things Applications, Security Challenges, Attacks, Intrusion Detection, and Future Visions: A Systematic Review | F81: JournalArticle; Review | G81: Computer Science | H81: 8 | I81: 238 | J81: Internet of Things (IoT) technology is prospering and entering every part of our lives, be it education, home, vehicles, or healthcare. With the increase in the number of connected devices, several challenges are also coming up with IoT technology: heterogeneity, scalability, quality of service, security requirements, and many more. Security management takes a back seat in IoT because of cost, size, and power. It poses a significant risk as lack of security makes users skeptical towards using IoT devices. This, in turn, makes IoT vulnerable to security attacks, ultimately causing enormous financial and reputational losses. It makes up for an urgent need to assess present security risks and discuss the upcoming challenges to be ready to face the same. The undertaken study is a multi-fold survey of different security issues present in IoT layers: perception layer, network layer, support layer, application layer, with further focus on Distributed Denial of Service (DDoS) attacks. DDoS attacks are significant threats for the cyber world because of their potential to bring down the victims. Different types of DDoS attacks, DDoS attacks in IoT devices, impacts of DDoS attacks, and solutions for mitigation are discussed in detail. The presented review work compares Intrusion Detection and Prevention models for mitigating DDoS attacks and focuses on Intrusion Detection models. Furthermore, the classification of Intrusion Detection Systems, different anomaly detection techniques, different Intrusion Detection System models based on datasets, various machine learning and deep learning techniques for data pre-processing and malware detection has been discussed. In the end, a broader perspective has been envisioned while discussing research challenges, its proposed solutions, and future visions. | K81: {"CorpusId": 233376685, "DBLP": "journals/access/MishraP21", "DOI": "10.1109/ACCESS.2021.3073408"} | L81: 10.1109/access.2021.3073408 | M81: TRUE | N81: https://ieeexplore.ieee.org/ielx7/6287639/9312710/09405669.pdf | O81: 59353-59377 | P81: 25 | R81: 172 | S81: 2021 | T81: 3; 29 | U81: 16
A82: PRECISE | B82: 143a229923a60370ceb2ad55167cb12ce71d407a | C82: A Comprehensive Review of Cyber Security Vulnerabilities, Threats, Attacks, and Solutions | D82: 2023-03-11 | E82: 2023 | F82: Review | G82: Medicine | H82: 8 | I82: 399 | J82: Internet usage has grown exponentially, with individuals and companies performing multiple daily transactions in cyberspace rather than in the real world. The coronavirus (COVID-19) pandemic has accelerated this process. As a result of the widespread usage of the digital environment, traditional crimes have also shifted to the digital space. Emerging technologies such as cloud computing, the Internet of Things (IoT), social media, wireless communication, and cryptocurrencies are raising security concerns in cyberspace. Recently, cyber criminals have started to use cyber attacks as a service to automate attacks and leverage their impact. Attackers exploit vulnerabilities that exist in hardware, software, and communication layers. Various types of cyber attacks include distributed denial of service (DDoS), phishing, man-in-the-middle, password, remote, privilege escalation, and malware. Due to new-generation attacks and evasion techniques, traditional protection systems such as firewalls, intrusion detection systems, antivirus software, access control lists, etc., are no longer effective in detecting these sophisticated attacks. Therefore, there is an urgent need to find innovative and more feasible solutions to prevent cyber attacks. The paper first extensively explains the main reasons for cyber attacks. Then, it reviews the most recent attacks, attack patterns, and detection techniques. Thirdly, the article discusses contemporary technical and nontechnical solutions for recognizing attacks in advance. Using trending technologies such as machine learning, deep learning, cloud platforms, big data, and blockchain can be a promising solution for current and future cyber attacks. These technological solutions may assist in detecting malware, intrusion detection, spam identification, DNS attack classification, fraud detection, recognizing hidden channels, and distinguishing advanced persistent threats. However, some promising solutions, especially machine learning and deep learning, are not resistant to evasion techniques, which must be considered when proposing solutions against intelligent cyber attacks. | K82: {"CorpusId": 257524278, "DOI": "10.3390/electronics12061333"} | L82: 10.3390/electronics12061333 | M82: TRUE | N82: https://www.mdpi.com/2079-9292/12/6/1333/pdf?version=1678502564 | R82: 162 | S82: 2023 | T82: 11; 2; 7; 6; 6 | U82: 6.4
A83: PRECISE | B83: 1d3273f5b7975ca41ee91008224717eb7b54966d | C83: Performance Comparison and Current Challenges of Using Machine Learning Techniques in Cybersecurity | D83: 2020-05-15 | E83: 2020 | F83: Review | G83: Computer Science | H83: 8 | I83: 216 | J83: Cyberspace has become an indispensable factor for all areas of the modern world. The world is becoming more and more dependent on the internet for everyday living. The increasing dependency on the internet has also widened the risks of malicious threats. On account of growing cybersecurity risks, cybersecurity has become the most pivotal element in the cyber world to battle against all cyber threats, attacks, and frauds. The expanding cyberspace is highly exposed to the intensifying possibility of being attacked by interminable cyber threats. The objective of this survey is to bestow a brief review of different machine learning (ML) techniques to get to the bottom of all the developments made in detection methods for potential cybersecurity risks. These cybersecurity risk detection methods mainly comprise of fraud detection, intrusion detection, spam detection, and malware detection. In this review paper, we build upon the existing literature of applications of ML models in cybersecurity and provide a comprehensive review of ML techniques in cybersecurity. To the best of our knowledge, we have made the first attempt to give a comparison of the time complexity of commonly used ML models in cybersecurity. We have comprehensively compared each classifier’s performance based on frequently used datasets and sub-domains of cyber threats. This work also provides a brief introduction of machine learning models besides commonly used security datasets. Despite having all the primary precedence, cybersecurity has its constraints compromises, and challenges. This work also expounds on the enormous current challenges and limitations faced during the application of machine learning techniques in cybersecurity. | K83: {"CorpusId": 219434523, "DOI": "10.3390/en13102509", "MAG": "3025204993"} | L83: 10.3390/en13102509 | M83: TRUE | N83: https://www.mdpi.com/1996-1073/13/10/2509/pdf | R83: 170 | S83: 2020 | T83: 32; 44; 44; 36; 4; 26; 16 | U83: 28.85714285714286
A84: PRECISE | B84: 24e1f94e0897f4ba0ae90834d589100dae5a9881 | C84: A Critical Review of Practices and Challenges in Intrusion Detection Systems for IoT: Toward Universal and Resilient Systems | D84: 2018-06-07 | E84: 2018 | F84: JournalArticle; Review | G84: Computer Science | H84: 8 | I84: 163 | K84: {"CorpusId": 53740428, "DBLP": "journals/comsur/BenkhelifaWH18", "DOI": "10.1109/COMST.2018.2844742", "MAG": "2806697149"} | L84: 10.1109/comst.2018.2844742 | M84: TRUE | N84: https://eprints.staffs.ac.uk/4758/1/IoT_IDS_Final__Copy_%20%28002%29.pdf | O84: 3496-3509 | P84: 14 | R84: 73 | T84: 28; 11; 29 | U84: 22.66666666666667
A85: PRECISE | B85: 62305fede0eb655d0fcd20ba86b119cc9df09ab5 | C85: Swarm intelligence in intrusion detection: A survey | D85: 2011-11-01 | E85: 2011 | F85: JournalArticle; Review | G85: Computer Science | H85: 8 | I85: 213 | K85: {"CorpusId": 17613760, "DBLP": "journals/compsec/KoliasKM11", "DOI": "10.1016/j.cose.2011.08.009", "MAG": "2034265047"} | L85: 10.1016/j.cose.2011.08.009 | M85: FALSE | O85: 625-642 | P85: 18 | R85: 107 | T85: 18; 43; 18 | U85: 26.33333333333333
A86: PRECISE | B86: 6a43a28fb65baa6198edc9c42bb7d6741bc9fca3 | C86: Advanced Border Intrusion Detection and Surveillance Using Wireless Sensor Network Technology | D86: 2013-05-15 | E86: 2013 | F86: Review | G86: Computer Science | H86: 8 | I86: 91 | J86: Wireless Sensor Network (WSN) has been emerging in the last decade as a powerful tool for connecting physical and digital world. WSN has been used in many applications such habitat monitoring, building monitoring, smart grid and pipeline monitoring. In addition, few researchers have been experimenting with WSN in many mission-critical applications such as military applications. This paper surveys the literature for experimenting work done in border surveillance and intrusion detection using the technology of WSN. The potential benefits of using WSN in border surveillance are huge; however, up to our knowledge very few attempts of solving many critical issues about this application could be found in the literature. | K86: {"CorpusId": 40739558, "DOI": "10.4236/IJCNS.2013.65028", "MAG": "2064909103"} | L86: 10.4236/ijcns.2013.65028 | M86: TRUE | N86: http://www.scirp.org/journal/PaperDownload.aspx?paperID=31336 | O86: 251-259 | P86: 9 | R86: 29 | S86: 2012 | T86: 20 | U86: 20
A87: PRECISE | B87: 85617e640bc534f3bcd6e153bdf7ad37b455df57 | C87: Intrusion Detection Systems for Networked Unmanned Aerial Vehicles: A Survey | D87: 2018-06-01 | E87: 2018 | F87: Conference; JournalArticle; Review | G87: Computer Science | H87: 8 | I87: 95 | J87: Unmanned Aerial Vehicles (UAV)-based civilian or military applications become more critical to serving civilian and/or military missions. The significantly increased attention on UAV applications also has led to security concerns particularly in the context of networked UAVs. Networked UAVs are vulnerable to malicious attacks over open-air radio space and accordingly intrusion detection systems (IDSs) have been naturally derived to deal with the vulnerabilities and/or attacks. In this paper, we briefly survey the state-of-the-art IDS mechanisms that deal with vulnerabilities and attacks under networked UAV environments. In particular, we classify the existing IDS mechanisms according to information gathering sources, deployment strategies, detection methods, detection states, IDS acknowledgment, and intrusion types. We conclude this paper with research challenges, insights, and future research directions to propose a networked UAVIDS system which meets required standards of effectiveness and efficiency in terms of the goals of both security and performance. | K87: {"ArXiv": "1807.00435", "CorpusId": 46940087, "DBLP": "journals/corr/abs-1807-00435", "DOI": "10.1109/IWCMC.2018.8450305", "MAG": "2963270044"} | L87: 10.1109/iwcmc.2018.8450305 | M87: TRUE | N87: http://arxiv.org/pdf/1807.00435 | O87: 560-565 | P87: 6 | R87: 28 | S87: 2018 | T87: 19; 40; 48; 21; 46; 32 | U87: 34.33333333333334
A88: PRECISE | B88: 8fd8fe76b3fc76adb47b1f1597e2e182a8280225 | C88: Survey on SDN based network intrusion detection system using machine learning approaches | D88: 2018-01-12 | E88: 2018 | F88: JournalArticle; Review | G88: Computer Science | H88: 8 | I88: 421 | K88: {"CorpusId": 67279885, "DBLP": "journals/ppna/SultanaCPA19", "DOI": "10.1007/s12083-017-0630-0", "MAG": "2782735691"} | L88: 10.1007/s12083-017-0630-0 | M88: FALSE | O88: 493 - 501 | P88: 9 | R88: 63 | T88: 24; 51; 50; 5 | U88: 32.5
A89: PRECISE | B89: ad075b977c431be556c615d43159cf04a8b96419 | C89: Intelligent feature selection and classification techniques for intrusion detection in networks: a survey | D89: 2013-11-27 | E89: 2013 | F89: JournalArticle; Review | G89: Computer Science | H89: 8 | I89: 230 | J89: Rapid growth in the Internet usage and diverse military applications have led researchers to think of intelligent systems that can assist the users and applications in getting the services by delivering required quality of service in networks. Some kinds of intelligent techniques are appropriate for providing security in communication pertaining to distributed environments such as mobile computing, e-commerce, telecommunication, and network management. In this paper, a survey on intelligent techniques for feature selection and classification for intrusion detection in networks based on intelligent software agents, neural networks, genetic algorithms, neuro-genetic algorithms, fuzzy techniques, rough sets, and particle swarm intelligence has been proposed. These techniques have been useful for effectively identifying and preventing network intrusions in order to provide security to the Internet and to enhance the quality of service. In addition to the survey on existing intelligent techniques for intrusion detection systems, two new algorithms namely intelligent rule-based attribute selection algorithm for effective feature selection and intelligent rule-based enhanced multiclass support vector machine have been proposed in this paper. | K89: {"CorpusId": 13299749, "DBLP": "journals/ejwcn/GanapathyKMVPK13", "DOI": "10.1186/1687-1499-2013-271", "MAG": "2156612354"} | L89: 10.1186/1687-1499-2013-271 | M89: TRUE | N89: https://jwcn-eurasipjournals.springeropen.com/counter/pdf/10.1186/1687-1499-2013-271 | R89: 96 | S89: 2013 | T89: 28; 12; 10; 9; 13; 39 | U89: 18.5
A90: PRECISE | B90: b8a2fb97fb72725210ffd8af52446a88c88f072d | C90: Deep Cybersecurity: A Comprehensive Overview from Neural Network and Deep Learning Perspective | D90: 2021-02-16 | E90: 2021 | F90: JournalArticle; Review | G90: Computer Science | H90: 8 | I90: 187 | J90: Deep learning, which is originated from an artificial neural network (ANN), is one of the major technologies of today’s smart cybersecurity systems or policies to function in an intelligent manner. Popular deep learning techniques, such as multi-layer perceptron, convolutional neural network, recurrent neural network or long short-term memory, self-organizing map, auto-encoder, restricted Boltzmann machine, deep belief networks, generative adversarial network, deep transfer learning, as well as deep reinforcement learning, or their ensembles and hybrid approaches can be used to intelligently tackle the diverse cybersecurity issues. In this paper, we aim to present a comprehensive overview from the perspective of these neural networks and deep learning techniques according to today’s diverse needs. We also discuss the applicability of these techniques in various cybersecurity tasks such as intrusion detection, identification of malware or botnets, phishing, predicting cyberattacks, e.g. denial of service, fraud detection or cyberanomalies, etc. Finally, we highlight several research issues and future directions within the scope of our study in the field. Overall, the ultimate goal of this paper is to serve as a reference point and guidelines for the academia and professionals in the cyber industries, especially from the deep learning point of view. | K90: {"CorpusId": 233329707, "DBLP": "journals/sncs/Sarker21", "DOI": "10.1007/s42979-021-00535-6", "MAG": "3130145150"} | L90: 10.1007/s42979-021-00535-6 | M90: TRUE | N90: https://www.preprints.org/manuscript/202102.0340/v1/download | R90: 145 | S90: 2021 | T90: 37 | U90: 37
A91: PRECISE | B91: bb1031b8fb91650e502397c69aa9ffa68341a084 | C91: Intrusion detection techniques in cloud environment: A survey | F91: JournalArticle; Review | G91: Computer Science | H91: 8 | I91: 205 | K91: {"CorpusId": 206259755, "DBLP": "journals/jnca/MishraPVT17", "DOI": "10.1016/j.jnca.2016.10.015", "MAG": "2531967557"} | L91: 10.1016/j.jnca.2016.10.015 | M91: FALSE | O91: 18-47 | P91: 30 | R91: 139 | T91: 14; 21; 44; 22 | U91: 25.25
A92: PRECISE | B92: 0278bbaf1db5df036f02393679d485260b1daeb7 | C92: Machine Learning Techniques for Anomaly Detection: An Overview | D92: 2013-10-18 | E92: 2013 | F92: Review | G92: Computer Science | H92: 7 | I92: 319 | K92: {"CorpusId": 13287576, "DOI": "10.5120/13715-1478", "MAG": "2107528096"} | L92: 10.5120/13715-1478 | M92: TRUE | N92: https://doi.org/10.5120/13715-1478 | O92: 33-41 | P92: 9 | R92: 69 | T92: 2; 8; 7 | U92: 5.666666666666667
A93: PRECISE | B93: 16cfe78c63a185575b5a1260e06f0df80c193fa3 | C93: ROAD: The Real ORNL Automotive Dynamometer Controller Area Network Intrusion Detection Dataset (with a comprehensive CAN IDS dataset survey & guide) | F93: JournalArticle; Review | G93: Computer Science | H93: 7 | I93: 35 | K93: {"CorpusId": 229923855, "DBLP": "journals/corr/abs-2012-14600"} | M93: FALSE | R93: 43 | T93: 7; 13; 20; 6; 14; 7 | U93: 11.16666666666667
A94: PRECISE | B94: 32062665fcb7e9e3825e4cc73846282155518e51 | C94: A Taxonomy of Network Threats and the Effect of Current Datasets on Intrusion Detection Systems | D94: 2020-06-04 | E94: 2020 | F94: JournalArticle; Review | G94: Computer Science | H94: 7 | I94: 158 | J94: As the world moves towards being increasingly dependent on computers and automation, building secure applications, systems and networks are some of the main challenges faced in the current decade. The number of threats that individuals and businesses face is rising exponentially due to the increasing complexity of networks and services of modern networks. To alleviate the impact of these threats, researchers have proposed numerous solutions for anomaly detection; however, current tools often fail to adapt to ever-changing architectures, associated threats and zero-day attacks. This manuscript aims to pinpoint research gaps and shortcomings of current datasets, their impact on building Network Intrusion Detection Systems (NIDS) and the growing number of sophisticated threats. To this end, this manuscript provides researchers with two key pieces of information; a survey of prominent datasets, analyzing their use and impact on the development of the past decade’s Intrusion Detection Systems (IDS) and a taxonomy of network threats and associated tools to carry out these attacks. The manuscript highlights that current IDS research covers only 33.3% of our threat taxonomy. Current datasets demonstrate a clear lack of real-network threats, attack representation and include a large number of deprecated threats, which together limit the detection accuracy of current machine learning IDS approaches. The unique combination of the taxonomy and the analysis of the datasets provided in this manuscript aims to improve the creation of datasets and the collection of real-world data. As a result, this will improve the efficiency of the next generation IDS and reflect network threats more accurately within new datasets. | K94: {"CorpusId": 219402183, "DBLP": "journals/access/HindyBBSTAB20", "DOI": "10.1109/ACCESS.2020.3000179", "MAG": "3033213260"} | L94: 10.1109/access.2020.3000179 | M94: TRUE | N94: https://ieeexplore.ieee.org/ielx7/6287639/8948470/09108270.pdf | O94: 104650-104675 | P94: 26 | R94: 174 | S94: 2020 | T94: 14; 15; 10; 14; 22; 16; 19 | U94: 15.71428571428571
A95: PRECISE | B95: 4abbd915b3ac89560f81324e6b7f9f8c9ee3d064 | C95: A Survey on Regular Expression Matching for Deep Packet Inspection: Applications, Algorithms, and Hardware Platforms | D95: 2016-10-01 | E95: 2016 | F95: JournalArticle; Review | G95: Computer Science | H95: 7 | I95: 130 | K95: {"CorpusId": 2837864, "DBLP": "journals/comsur/XuCSYH16", "DOI": "10.1109/COMST.2016.2566669", "MAG": "2393727648"} | L95: 10.1109/comst.2016.2566669 | M95: FALSE | O95: 2991-3029 | P95: 39 | R95: 153 | T95: 8; 11; 32; 56; 31 | U95: 27.6
A96: PRECISE | B96: 4bf0fdf066bc9dff6a96b92738843e266ee57873 | C96: Taxonomy of Anomaly Based Intrusion Detection System: A Review | F96: Review | G96: Engineering | H96: 7 | I96: 62 | K96: {"CorpusId": 8241592, "MAG": "2440677330"} | M96: FALSE | R96: 62 | T96: 13; 7 | U96: 10
A97: PRECISE | B97: 721be1fbf687927f3349bdb0ca17e51951cb4a3e | C97: Intrusion Detection Systems | D97: 2011-03-22 | E97: 2011 | F97: Review | G97: Computer Science | H97: 7 | I97: 147 | K97: {"CorpusId": 14156437, "DOI": "10.1007/978-0-387-47653-7_3", "MAG": "2493318994"} | L97: 10.1007/978-0-387-47653-7_3 | M97: TRUE | N97: https://doi.org/10.35940/ijrte.b1540.0982s1119 | R97: 53 | T97: 1 | U97: 1
A98: PRECISE | B98: 7a21bfd3626420a8846803c2aa21c4f1edc72046 | C98: A Survey of CNN-Based Network Intrusion Detection | D98: 2022-08-15 | E98: 2022 | F98: Review | H98: 7 | I98: 121 | J98: Over the past few years, Internet applications have become more advanced and widely used. This has increased the need for Internet networks to be secured. Intrusion detection systems (IDSs), which employ artificial intelligence (AI) methods, are vital to ensuring network security. As a branch of AI, deep learning (DL) algorithms are now effectively applied in IDSs. Among deep learning neural networks, the convolutional neural network (CNN) is a well-known structure designed to process complex data. The CNN overcomes the typical limitations of conventional machine learning approaches and is mainly used in IDSs. Several CNN-based approaches are employed in IDSs to handle privacy issues and security threats. However, there are no comprehensive surveys of IDS schemes that have utilized CNN to the best of our knowledge. Hence, in this study, our primary focus is on CNN-based IDSs so as to increase our understanding of various uses of the CNN in detecting network intrusions, anomalies, and other types of attacks. This paper innovatively organizes the studied CNN-IDS approaches into multiple categories and describes their primary capabilities and contributions. The main features of these approaches, such as the dataset, architecture, input shape, evaluated metrics, performance, feature extraction, and classifier method, are compared. Because different datasets are used in CNN-IDS research, their experimental results are not comparable. Hence, this study also conducted an empirical experiment to compare different approaches based on standard datasets, and the comparative results are presented in detail. | K98: {"CorpusId": 251639940, "DOI": "10.3390/app12168162"} | L98: 10.3390/app12168162 | M98: TRUE | N98: https://www.mdpi.com/2076-3417/12/16/8162/pdf?version=1661216967 | R98: 0 | T98: 5; 12; 18; 7 | U98: 10.5
A99: PRECISE | B99: 88cd352a02b017f8190686271594b62ca464b638 | C99: Cyber security meets artificial intelligence: a survey | D99: 2018-12-01 | E99: 2018 | F99: JournalArticle; Review | G99: Computer Science | H99: 7 | I99: 185 | J99: There is a wide range of interdisciplinary intersections between cyber security and artificial intelligence (AI). On one hand, AI technologies, such as deep learning, can be introduced into cyber security to construct smart models for implementing malware classification and intrusion detection and threating intelligence sensing. On the other hand, AI models will face various cyber threats, which will disturb their sample, learning, and decisions. Thus, AI models need specific cyber security defense and protection technologies to combat adversarial machine learning, preserve privacy in machine learning, secure federated learning, etc. Based on the above two aspects, we review the intersection of AI and cyber security. First, we summarize existing research efforts in terms of combating cyber attacks using AI, including adopting traditional machine learning methods and existing deep learning solutions. Then, we analyze the counterattacks from which AI itself may suffer, dissect their characteristics, and classify the corresponding defense methods. Finally, from the aspects of constructing encrypted neural network and realizing a secure federated deep learning, we expatiate the existing research on how to build a secure AI system. | K99: {"CorpusId": 57765528, "DBLP": "journals/jzusc/Li18", "DOI": "10.1631/FITEE.1800573", "MAG": "2908954810"} | L99: 10.1631/fitee.1800573 | M99: FALSE | O99: 1462-1474 | P99: 13 | R99: 68 | T99: 6 | U99: 6
A100: PRECISE | B100: c3043c6b56c3871eafe08a81ecb8b82f33b322ae | C100: Adversarial Machine Learning Applied to Intrusion and Malware Scenarios: A Systematic Review | D100: 2020-02-18 | E100: 2020 | F100: JournalArticle; Review | G100: Computer Science | H100: 7 | I100: 148 | J100: Cyber-security is the practice of protecting computing systems and networks from digital attacks, which are a rising concern in the Information Age. With the growing pace at which new attacks are developed, conventional signature based attack detection methods are often not enough, and machine learning poses as a potential solution. Adversarial machine learning is a research area that examines both the generation and detection of adversarial examples, which are inputs specially crafted to deceive classifiers, and has been extensively studied specifically in the area of image recognition, where minor modifications are performed on images that cause a classifier to produce incorrect predictions. However, in other fields, such as intrusion and malware detection, the exploration of such methods is still growing. The aim of this survey is to explore works that apply adversarial machine learning concepts to intrusion and malware detection scenarios. We concluded that a wide variety of attacks were tested and proven effective in malware and intrusion detection, although their practicality was not tested in intrusion scenarios. Adversarial defenses were substantially less explored, although their effectiveness was also proven at resisting adversarial attacks. We also concluded that, contrarily to malware scenarios, the variety of datasets in intrusion scenarios is still very small, with the most used dataset being greatly outdated. | K100: {"CorpusId": 212646620, "DBLP": "journals/access/MartinsCCA20", "DOI": "10.1109/ACCESS.2020.2974752", "MAG": "3007481080"} | L100: 10.1109/access.2020.2974752 | M100: TRUE | N100: https://ieeexplore.ieee.org/ielx7/6287639/8948470/09001114.pdf | O100: 35403-35419 | P100: 17 | R100: 69 | S100: 2020 | T100: 2; 3; 22; 3 | U100: 7.5
...

Sheet Metrics (computed)
A1: cites_per_day | B1: recency_delay_years | C1: pages_minus_refs | D1: normalized_pages_minus_refs | E1: normalized_references_count | F1: normalized_recency_delay | G1: normalized_cites_per_day | H1: normalized_mean_author_hindex | I1: composite_score
A2: {=IF(LEN(rawdata!B2:B14026)=0, "", IFERROR( VALUE(rawdata!I2:I14026) / IF( (TODAY() - DATEVALUE(rawdata!D2:D14026)) < 1, 1, (TODAY() - DATEVALUE(rawdata!D2:D14026)) ), "" ) )} -> 0.47235693 | B2: {=IF(LEN(rawdata!B2:B14026)=0, "", IF( (LEN(rawdata!E2:E14026)=0) + (LEN(rawdata!S2:S14026)=0), "", IF( (VALUE(rawdata!E2:E14026) - VALUE(rawdata!S2:S14026)) < 0, 0, VALUE(rawdata!E2:E14026) - VALUE(rawdata!S2:S14026) ) ) )} | C2: {=IF(LEN(rawdata!B2:B14026)=0, "", IF( (LEN(rawdata!P2:P14026)=0) + (LEN(rawdata!Q2:Q14026)=0), "", IFERROR(VALUE(rawdata!P2:P14026),"") - IFERROR(VALUE(rawdata!Q2:Q14026),"") ) )} | D2: =IFERROR(__xludf.DUMMYFUNCTION("ARRAYFORMULA( IF(LEN(rawdata!B2:B14026)=0, """", IF(LEN(C2:C14026)=0, """", IF( PERCENTILE( FILTER(IFERROR(VALUE(C2:C14026),), ISNUMBER(IFERROR(VALUE(C2:C14026),))), 0.05 ) = PERCENTILE( FILTER(IFERROR(VALUE(C2:C14026),), ISNU"&"MBER(IFERROR(VALUE(C2:C14026),))), 0.95 ), 1, IF( ( (IFERROR(VALUE(#REF!),) - PERCENTILE(FILTER(IFERROR(VALUE(#REF!),), ISNUMBER(IFERROR(VALUE(#REF!),))), 0.05)) / ( PERCENTILE(FILTER(IFERROR(VALUE(#REF!),), ISNUMBER(IFERRO"&"R(VALUE(#REF!),))), 0.95) - PERCENTILE(FILTER(IFERROR(VALUE(#REF!),), ISNUMBER(IFERROR(VALUE(#REF!),))), 0.05) ) ) < 0, 0, IF( ( (IFERROR(VALUE(#REF!),) - PERCENTILE(FILTER(IFERROR(VALUE(#REF!),), ISNUMBER(IFERROR(VALUE(#REF!),))"&"), 0.05)) / ( PERCENTILE(FILTER(IFERROR(VALUE(#REF!),), ISNUMBER(IFERROR(VALUE(#REF!),))), 0.95) - PERCENTILE(FILTER(IFERROR(VALUE(#REF!),), ISNUMBER(IFERROR(VALUE(#REF!),))), 0.05) ) ) > 1, 1, ( (IFERROR(VALUE(#REF!),) -"&" PERCENTILE(FILTER(IFERROR(VALUE(#REF!),), ISNUMBER(IFERROR(VALUE(#REF!),))), 0.05)) / ( PERCENTILE(FILTER(IFERROR(VALUE(#REF!),), ISNUMBER(IFERROR(VALUE(#REF!),))), 0.95) - PERCENTILE(FILTER(IFERROR(VALUE(#REF!),), ISNUMBER(IFERROR(VALUE(#REF!)"&",))), 0.05) ) ) ) ) ) ) ) )"),"") | E2: =IFERROR(__xludf.DUMMYFUNCTION("ARRAYFORMULA( IF(LEN(rawdata!B2:B14026)=0, """", IF(LEN(rawdata!R2:R14026)=0, """", IF( PERCENTILE( LN(1+FILTER(IFERROR(VALUE(rawdata!R2:R14026),), ISNUMBER(IFERROR(VALUE(rawdata!R2:R14026),)))), 0.05 ) = PERCENTILE( LN(1+FILT"&"ER(IFERROR(VALUE(rawdata!R2:R14026),), ISNUMBER(IFERROR(VALUE(rawdata!R2:R14026),)))), 0.95 ), 1, IF( ( ( LN(1+IFERROR(VALUE(rawdata!R2:R14026),)) - PERCENTILE(LN(1+FILTER(IFERROR(VALUE(rawdata!R2:R14026),), ISNUMBER(IFERRO"&"R(VALUE(rawdata!R2:R14026),)))), 0.05) ) / ( PERCENTILE(LN(1+FILTER(IFERROR(VALUE(rawdata!R2:R14026),), ISNUMBER(IFERROR(VALUE(rawdata!R2:R14026),)))), 0.95) - PERCENTILE(LN(1+FILTER(IFERROR(VALUE(rawdata!R2:R14026),), ISNUMBER(IFERROR(VALUE(rawda"&"ta!R2:R14026),)))), 0.05) ) ) < 0, 0, IF( ( ( LN(1+IFERROR(VALUE(rawdata!R2:R14026),)) - PERCENTILE(LN(1+FILTER(IFERROR(VALUE(rawdata!R2:R14026),), ISNUMBER(IFERROR(VALUE(rawdata!R2:R14026),)))), 0.05) ) / ( P"&"ERCENTILE(LN(1+FILTER(IFERROR(VALUE(rawdata!R2:R14026),), ISNUMBER(IFERROR(VALUE(rawdata!R2:R14026),)))), 0.95) - PERCENTILE(LN(1+FILTER(IFERROR(VALUE(rawdata!R2:R14026),), ISNUMBER(IFERROR(VALUE(rawdata!R2:R14026),)))), 0.05) ) ) > 1, 1, "&" ( ( LN(1+IFERROR(VALUE(rawdata!R2:R14026),)) - PERCENTILE(LN(1+FILTER(IFERROR(VALUE(rawdata!R2:R14026),), ISNUMBER(IFERROR(VALUE(rawdata!R2:R14026),)))), 0.05) ) / ( PERCENTILE(LN(1+FILTER(IFERROR(VALUE(rawdata!R2:R14026),), ISNUMBER(IFE"&"RROR(VALUE(rawdata!R2:R14026),)))), 0.95) - PERCENTILE(LN(1+FILTER(IFERROR(VALUE(rawdata!R2:R14026),), ISNUMBER(IFERROR(VALUE(rawdata!R2:R14026),)))), 0.05) ) ) ) ) ) ) ) )"),0.07976197121590477) -> 0.079761971 | F2: =IFERROR(__xludf.DUMMYFUNCTION("ARRAYFORMULA( IF(LEN(rawdata!B2:B14026)=0, """", IF(LEN(B2:B14026)=0, """", IF( PERCENTILE(FILTER(IFERROR(VALUE(B2:B14026),), ISNUMBER(IFERROR(VALUE(B2:B14026),))), 0.05) = PERCENTILE(FILTER(IFERROR(VALUE(B2:B14026),), ISNUMBER(IFERROR(VALUE(B2"&":B14026),))), 0.95), 1, 1 - IF( ((IFERROR(VALUE(B2:B14026),) - PERCENTILE(FILTER(IFERROR(VALUE(B2:B14026),), ISNUMBER(IFERROR(VALUE(B2:B14026),))), 0.05)) / (PERCENTILE(FILTER(IFERROR(VALUE(B2:B14026),), ISNUMBER(IFERROR(VALUE(B2:B140"&"26),))), 0.95) - PERCENTILE(FILTER(IFERROR(VALUE(B2:B14026),), ISNUMBER(IFERROR(VALUE(B2:B14026),))), 0.05)) ) < 0, 0, IF( ((IFERROR(VALUE(#REF!),) - PERCENTILE(FILTER(IFERROR(VALUE(#REF!),), ISNUMBER(IFERROR(VALUE(#REF!)"&",))), 0.05)) / (PERCENTILE(FILTER(IFERROR(VALUE(#REF!),), ISNUMBER(IFERROR(VALUE(#REF!),))), 0.95) - PERCENTILE(FILTER(IFERROR(VALUE(#REF!),), ISNUMBER(IFERROR(VALUE(#REF!),))), 0.05)) ) > 1, 1, ((IFERROR(VALUE(#"&"REF!),) - PERCENTILE(FILTER(IFERROR(VALUE(#REF!),), ISNUMBER(IFERROR(VALUE(#REF!),))), 0.05)) / (PERCENTILE(FILTER(IFERROR(VALUE(#REF!),), ISNUMBER(IFERROR(VALUE(#REF!),))), 0.95) - PERCENTILE(FILTER(IFERROR(VALUE(#REF!),), ISNUMBER(IFE"&"RROR(VALUE(#REF!),))), 0.05)) ) ) ) ) ) ) )"),"") | G2: =IFERROR(__xludf.DUMMYFUNCTION("ARRAYFORMULA( IF(LEN(rawdata!B2:B14026)=0, """", IF(LEN(A2:A14026)=0, """", IF( PERCENTILE(FILTER(IFERROR(VALUE(A2:A14026),), ISNUMBER(IFERROR(VALUE(A2:A14026),))), 0.05) = PERCENTILE(FILTER(IFERROR(VALUE(A2:A14026),), ISNUMBER(IFERROR(VALUE(A2"&":A14026),))), 0.95), 1, IF( ((IFERROR(VALUE(A2:A14026),) - PERCENTILE(FILTER(IFERROR(VALUE(A2:A14026),), ISNUMBER(IFERROR(VALUE(A2:A14026),))), 0.05)) / (PERCENTILE(FILTER(IFERROR(VALUE(A2:A14026),), ISNUMBER(IFERROR(VALUE(A2:A14026),"&"))), 0.95) - PERCENTILE(FILTER(IFERROR(VALUE(A2:A14026),), ISNUMBER(IFERROR(VALUE(A2:A14026),))), 0.05)) ) < 0, 0, IF( ((IFERROR(VALUE(#REF!),) - PERCENTILE(FILTER(IFERROR(VALUE(#REF!),), ISNUMBER(IFERROR(VALUE(#REF!),)))"&", 0.05)) / (PERCENTILE(FILTER(IFERROR(VALUE(#REF!),), ISNUMBER(IFERROR(VALUE(#REF!),))), 0.95) - PERCENTILE(FILTER(IFERROR(VALUE(#REF!),), ISNUMBER(IFERROR(VALUE(#REF!),))), 0.05)) ) > 1, 1, ((IFERROR(VALUE(#REF!"&"),) - PERCENTILE(FILTER(IFERROR(VALUE(#REF!),), ISNUMBER(IFERROR(VALUE(#REF!),))), 0.05)) / (PERCENTILE(FILTER(IFERROR(VALUE(#REF!),), ISNUMBER(IFERROR(VALUE(#REF!),))), 0.95) - PERCENTILE(FILTER(IFERROR(VALUE(#REF!),), ISNUMBER(IFERROR"&"(VALUE(#REF!),))), 0.05)) ) ) ) ) ) ) )"),1.0) -> 1 | H2: =IFERROR(__xludf.DUMMYFUNCTION("ARRAYFORMULA( IF(LEN(rawdata!B2:B14026)=0, """", IF(LEN(rawdata!U2:U14026)=0, """", IF( PERCENTILE(LN(1+FILTER(IFERROR(VALUE(rawdata!U2:U14026),), ISNUMBER(IFERROR(VALUE(rawdata!U2:U14026),)))), 0.05) = PERCENTILE(LN(1+FILTER(IFERROR(VALUE(rawd"&"ata!U2:U14026),), ISNUMBER(IFERROR(VALUE(rawdata!U2:U14026),)))), 0.95), 1, IF( ((LN(1+IFERROR(VALUE(rawdata!U2:U14026),)) - PERCENTILE(LN(1+FILTER(IFERROR(VALUE(rawdata!U2:U14026),), ISNUMBER(IFERROR(VALUE(rawdata!U2:U14026),)))), 0.05)) / "&" (PERCENTILE(LN(1+FILTER(IFERROR(VALUE(rawdata!U2:U14026),), ISNUMBER(IFERROR(VALUE(rawdata!U2:U14026),)))), 0.95) - PERCENTILE(LN(1+FILTER(IFERROR(VALUE(rawdata!U2:U14026),), ISNUMBER(IFERROR(VALUE(rawdata!U2:U14026),)))), 0.05)) ) < "&"0, 0, IF( ((LN(1+IFERROR(VALUE(rawdata!U2:U14026),)) - PERCENTILE(LN(1+FILTER(IFERROR(VALUE(rawdata!U2:U14026),), ISNUMBER(IFERROR(VALUE(rawdata!U2:U14026),)))), 0.05)) / (PERCENTILE(LN(1+FILTER(IFERROR(VALUE(rawdata!U2:U14026"&"),), ISNUMBER(IFERROR(VALUE(rawdata!U2:U14026),)))), 0.95) - PERCENTILE(LN(1+FILTER(IFERROR(VALUE(rawdata!U2:U14026),), ISNUMBER(IFERROR(VALUE(rawdata!U2:U14026),)))), 0.05)) ) > 1, 1, ((LN(1+IFERROR(VALUE(rawdata!U2:U140"&"26),)) - PERCENTILE(LN(1+FILTER(IFERROR(VALUE(rawdata!U2:U14026),), ISNUMBER(IFERROR(VALUE(rawdata!U2:U14026),)))), 0.05)) / (PERCENTILE(LN(1+FILTER(IFERROR(VALUE(rawdata!U2:U14026),), ISNUMBER(IFERROR(VALUE(rawdata!U2:U14026),)))), 0.95) - "&" PERCENTILE(LN(1+FILTER(IFERROR(VALUE(rawdata!U2:U14026),), ISNUMBER(IFERROR(VALUE(rawdata!U2:U14026),)))), 0.05)) ) ) ) ) ) ) )"),0.0) -> 0 | I2: {=IF(LEN(rawdata!B2:B14026)=0, "", 0.3*D2:D14026 + 0.25*E2:E14026 + 0.2*F2:F14026 + 0.15*G2:G14026 + 0.1*H2:H14026 )} -> 0.16994049
A3: 0.20431211 | D3: =IFERROR(__xludf.DUMMYFUNCTION("""COMPUTED_VALUE"""),"") | E3: =IFERROR(__xludf.DUMMYFUNCTION("""COMPUTED_VALUE"""),0.9548721026215339) -> 0.9548721 | F3: =IFERROR(__xludf.DUMMYFUNCTION("""COMPUTED_VALUE"""),"") | G3: =IFERROR(__xludf.DUMMYFUNCTION("""COMPUTED_VALUE"""),1.0) -> 1 | H3: =IFERROR(__xludf.DUMMYFUNCTION("""COMPUTED_VALUE"""),0.8059258159859609) -> 0.80592582 | I3: 0.46931061
A4: 0.28599562 | D4: =IFERROR(__xludf.DUMMYFUNCTION("""COMPUTED_VALUE"""),"") | E4: =IFERROR(__xludf.DUMMYFUNCTION("""COMPUTED_VALUE"""),0.882367679076927) -> 0.88236768 | F4: =IFERROR(__xludf.DUMMYFUNCTION("""COMPUTED_VALUE"""),"") | G4: =IFERROR(__xludf.DUMMYFUNCTION("""COMPUTED_VALUE"""),1.0) -> 1 | H4: =IFERROR(__xludf.DUMMYFUNCTION("""COMPUTED_VALUE"""),0.7699084914494659) -> 0.76990849 | I4: 0.44758277
D5: =IFERROR(__xludf.DUMMYFUNCTION("""COMPUTED_VALUE"""),"") | E5: =IFERROR(__xludf.DUMMYFUNCTION("""COMPUTED_VALUE"""),0.6297361753994164) -> 0.62973618 | F5: =IFERROR(__xludf.DUMMYFUNCTION("""COMPUTED_VALUE"""),"") | G5: =IFERROR(__xludf.DUMMYFUNCTION("""COMPUTED_VALUE"""),"") | H5: =IFERROR(__xludf.DUMMYFUNCTION("""COMPUTED_VALUE"""),0.20085468356535413) -> 0.20085468 | I5: 0.17751951
A6: 0.27721845 | D6: =IFERROR(__xludf.DUMMYFUNCTION("""COMPUTED_VALUE"""),"") | E6: =IFERROR(__xludf.DUMMYFUNCTION("""COMPUTED_VALUE"""),1.0) -> 1 | F6: =IFERROR(__xludf.DUMMYFUNCTION("""COMPUTED_VALUE"""),"") | G6: =IFERROR(__xludf.DUMMYFUNCTION("""COMPUTED_VALUE"""),1.0) -> 1 | H6: =IFERROR(__xludf.DUMMYFUNCTION("""COMPUTED_VALUE"""),0.87183090148872) -> 0.8718309 | I6: 0.48718309
A7: 0.56348511 | B7: 1 | D7: =IFERROR(__xludf.DUMMYFUNCTION("""COMPUTED_VALUE"""),"") | E7: =IFERROR(__xludf.DUMMYFUNCTION("""COMPUTED_VALUE"""),0.823149971850111) -> 0.82314997 | F7: =IFERROR(__xludf.DUMMYFUNCTION("""COMPUTED_VALUE"""),1.0) -> 1 | G7: =IFERROR(__xludf.DUMMYFUNCTION("""COMPUTED_VALUE"""),1.0) -> 1 | H7: =IFERROR(__xludf.DUMMYFUNCTION("""COMPUTED_VALUE"""),0.7545924021819583) -> 0.7545924 | I7: 0.63124673
A8: 0.28825623 | D8: =IFERROR(__xludf.DUMMYFUNCTION("""COMPUTED_VALUE"""),"") | E8: =IFERROR(__xludf.DUMMYFUNCTION("""COMPUTED_VALUE"""),0.7118469843264902) -> 0.71184698 | F8: =IFERROR(__xludf.DUMMYFUNCTION("""COMPUTED_VALUE"""),"") | G8: =IFERROR(__xludf.DUMMYFUNCTION("""COMPUTED_VALUE"""),1.0) -> 1 | H8: =IFERROR(__xludf.DUMMYFUNCTION("""COMPUTED_VALUE"""),0.30345515853674393) -> 0.30345516 | I8: 0.35830726
A9: 0.19318528 | D9: =IFERROR(__xludf.DUMMYFUNCTION("""COMPUTED_VALUE"""),"") | E9: =IFERROR(__xludf.DUMMYFUNCTION("""COMPUTED_VALUE"""),0.19773288331254052) -> 0.19773288 | F9: =IFERROR(__xludf.DUMMYFUNCTION("""COMPUTED_VALUE"""),"") | G9: =IFERROR(__xludf.DUMMYFUNCTION("""COMPUTED_VALUE"""),1.0) -> 1 | H9: =IFERROR(__xludf.DUMMYFUNCTION("""COMPUTED_VALUE"""),0.701464288130925) -> 0.70146429 | I9: 0.26957965
A10: 0.2158745 | D10: =IFERROR(__xludf.DUMMYFUNCTION("""COMPUTED_VALUE"""),"") | E10: =IFERROR(__xludf.DUMMYFUNCTION("""COMPUTED_VALUE"""),0.6393425607818837) -> 0.63934256 | F10: =IFERROR(__xludf.DUMMYFUNCTION("""COMPUTED_VALUE"""),"") | G10: =IFERROR(__xludf.DUMMYFUNCTION("""COMPUTED_VALUE"""),1.0) -> 1 | H10: =IFERROR(__xludf.DUMMYFUNCTION("""COMPUTED_VALUE"""),0.6990982929283924) -> 0.69909829 | I10: 0.37974547
A11: 0.28841808 | D11: =IFERROR(__xludf.DUMMYFUNCTION("""COMPUTED_VALUE"""),"") | E11: =IFERROR(__xludf.DUMMYFUNCTION("""COMPUTED_VALUE"""),0.781503141717807) -> 0.78150314 | F11: =IFERROR(__xludf.DUMMYFUNCTION("""COMPUTED_VALUE"""),"") | G11: =IFERROR(__xludf.DUMMYFUNCTION("""COMPUTED_VALUE"""),1.0) -> 1 | H11: =IFERROR(__xludf.DUMMYFUNCTION("""COMPUTED_VALUE"""),0.4779923023475191) -> 0.4779923 | I11: 0.39317502
D12: =IFERROR(__xludf.DUMMYFUNCTION("""COMPUTED_VALUE"""),"") | E12: =IFERROR(__xludf.DUMMYFUNCTION("""COMPUTED_VALUE"""),0.6486927451058364) -> 0.64869275 | F12: =IFERROR(__xludf.DUMMYFUNCTION("""COMPUTED_VALUE"""),"") | G12: =IFERROR(__xludf.DUMMYFUNCTION("""COMPUTED_VALUE"""),"") | H12: =IFERROR(__xludf.DUMMYFUNCTION("""COMPUTED_VALUE"""),0.5953713476386906) -> 0.59537135 | I12: 0.22171032
A13: 0.12985332 | D13: =IFERROR(__xludf.DUMMYFUNCTION("""COMPUTED_VALUE"""),"") | E13: =IFERROR(__xludf.DUMMYFUNCTION("""COMPUTED_VALUE"""),0.6622664840841103) -> 0.66226648 | F13: =IFERROR(__xludf.DUMMYFUNCTION("""COMPUTED_VALUE"""),"") | G13: =IFERROR(__xludf.DUMMYFUNCTION("""COMPUTED_VALUE"""),1.0) -> 1 | H13: =IFERROR(__xludf.DUMMYFUNCTION("""COMPUTED_VALUE"""),0.7607858378948519) -> 0.76078584 | I13: 0.3916452
A14: 0.45941469 | B14: 0 | D14: =IFERROR(__xludf.DUMMYFUNCTION("""COMPUTED_VALUE"""),"") | E14: =IFERROR(__xludf.DUMMYFUNCTION("""COMPUTED_VALUE"""),0.889403590094233) -> 0.88940359 | F14: =IFERROR(__xludf.DUMMYFUNCTION("""COMPUTED_VALUE"""),1.0) -> 1 | G14: =IFERROR(__xludf.DUMMYFUNCTION("""COMPUTED_VALUE"""),1.0) -> 1 | H14: =IFERROR(__xludf.DUMMYFUNCTION("""COMPUTED_VALUE"""),0.4130723542258289) -> 0.41307235 | I14: 0.61365813
A15: 0.11955275 | D15: =IFERROR(__xludf.DUMMYFUNCTION("""COMPUTED_VALUE"""),"") | E15: =IFERROR(__xludf.DUMMYFUNCTION("""COMPUTED_VALUE"""),0.47265371983310933) -> 0.47265372 | F15: =IFERROR(__xludf.DUMMYFUNCTION("""COMPUTED_VALUE"""),"") | G15: =IFERROR(__xludf.DUMMYFUNCTION("""COMPUTED_VALUE"""),1.0) -> 1 | H15: =IFERROR(__xludf.DUMMYFUNCTION("""COMPUTED_VALUE"""),0.9602602357171964) -> 0.96026024 | I15: 0.36418945
A16: 0.24406497 | B16: 0 | D16: =IFERROR(__xludf.DUMMYFUNCTION("""COMPUTED_VALUE"""),"") | E16: =IFERROR(__xludf.DUMMYFUNCTION("""COMPUTED_VALUE"""),0.7518563800998207) -> 0.75185638 | F16: =IFERROR(__xludf.DUMMYFUNCTION("""COMPUTED_VALUE"""),1.0) -> 1 | G16: =IFERROR(__xludf.DUMMYFUNCTION("""COMPUTED_VALUE"""),1.0) -> 1 | H16: =IFERROR(__xludf.DUMMYFUNCTION("""COMPUTED_VALUE"""),0.602145960825503) -> 0.60214596 | I16: 0.59817869
A17: 0.15241021 | D17: =IFERROR(__xludf.DUMMYFUNCTION("""COMPUTED_VALUE"""),"") | E17: =IFERROR(__xludf.DUMMYFUNCTION("""COMPUTED_VALUE"""),0.7306007127585364) -> 0.73060071 | F17: =IFERROR(__xludf.DUMMYFUNCTION("""COMPUTED_VALUE"""),"") | G17: =IFERROR(__xludf.DUMMYFUNCTION("""COMPUTED_VALUE"""),1.0) -> 1 | H17: =IFERROR(__xludf.DUMMYFUNCTION("""COMPUTED_VALUE"""),0.7989645659521445) -> 0.79896457 | I17: 0.41254663
A18: 0.35661765 | B18: 0 | D18: =IFERROR(__xludf.DUMMYFUNCTION("""COMPUTED_VALUE"""),"") | E18: =IFERROR(__xludf.DUMMYFUNCTION("""COMPUTED_VALUE"""),0.715678838128153) -> 0.71567884 | F18: =IFERROR(__xludf.DUMMYFUNCTION("""COMPUTED_VALUE"""),1.0) -> 1 | G18: =IFERROR(__xludf.DUMMYFUNCTION("""COMPUTED_VALUE"""),1.0) -> 1 | H18: =IFERROR(__xludf.DUMMYFUNCTION("""COMPUTED_VALUE"""),0.29191618910194683) -> 0.29191619 | I18: 0.55811133
A19: 0.11223868 | D19: =IFERROR(__xludf.DUMMYFUNCTION("""COMPUTED_VALUE"""),"") | E19: =IFERROR(__xludf.DUMMYFUNCTION("""COMPUTED_VALUE"""),0.7269293584483356) -> 0.72692936 | F19: =IFERROR(__xludf.DUMMYFUNCTION("""COMPUTED_VALUE"""),"") | G19: =IFERROR(__xludf.DUMMYFUNCTION("""COMPUTED_VALUE"""),1.0) -> 1 | H19: =IFERROR(__xludf.DUMMYFUNCTION("""COMPUTED_VALUE"""),0.8638845140738347) -> 0.86388451 | I19: 0.41812079
A20: 0.11082867 | D20: =IFERROR(__xludf.DUMMYFUNCTION("""COMPUTED_VALUE"""),"") | E20: =IFERROR(__xludf.DUMMYFUNCTION("""COMPUTED_VALUE"""),0.10238989523252559) -> 0.1023899 | F20: =IFERROR(__xludf.DUMMYFUNCTION("""COMPUTED_VALUE"""),"") | G20: =IFERROR(__xludf.DUMMYFUNCTION("""COMPUTED_VALUE"""),1.0) -> 1 | H20: =IFERROR(__xludf.DUMMYFUNCTION("""COMPUTED_VALUE"""),0.7467202844151569) -> 0.74672028 | I20: 0.2502695
A21: 0.27339901 | D21: =IFERROR(__xludf.DUMMYFUNCTION("""COMPUTED_VALUE"""),"") | E21: =IFERROR(__xludf.DUMMYFUNCTION("""COMPUTED_VALUE"""),0.8501333696778393) -> 0.85013337 | F21: =IFERROR(__xludf.DUMMYFUNCTION("""COMPUTED_VALUE"""),"") | G21: =IFERROR(__xludf.DUMMYFUNCTION("""COMPUTED_VALUE"""),1.0) -> 1 | H21: =IFERROR(__xludf.DUMMYFUNCTION("""COMPUTED_VALUE"""),0.44025249672534217) -> 0.4402525 | I21: 0.40655859
A22: 0.30637982 | B22: 0 | D22: =IFERROR(__xludf.DUMMYFUNCTION("""COMPUTED_VALUE"""),"") | E22: =IFERROR(__xludf.DUMMYFUNCTION("""COMPUTED_VALUE"""),0.6532759624345169) -> 0.65327596 | F22: =IFERROR(__xludf.DUMMYFUNCTION("""COMPUTED_VALUE"""),1.0) -> 1 | G22: =IFERROR(__xludf.DUMMYFUNCTION("""COMPUTED_VALUE"""),1.0) -> 1 | H22: =IFERROR(__xludf.DUMMYFUNCTION("""COMPUTED_VALUE"""),0.2970836899874542) -> 0.29708369 | I22: 0.54302736
A23: 0.25031712 | D23: =IFERROR(__xludf.DUMMYFUNCTION("""COMPUTED_VALUE"""),"") | E23: =IFERROR(__xludf.DUMMYFUNCTION("""COMPUTED_VALUE"""),1.0) -> 1 | F23: =IFERROR(__xludf.DUMMYFUNCTION("""COMPUTED_VALUE"""),"") | G23: =IFERROR(__xludf.DUMMYFUNCTION("""COMPUTED_VALUE"""),1.0) -> 1 | H23: =IFERROR(__xludf.DUMMYFUNCTION("""COMPUTED_VALUE"""),0.7904562758009703) -> 0.79045628 | I23: 0.47904563
D24: =IFERROR(__xludf.DUMMYFUNCTION("""COMPUTED_VALUE"""),"") | E24: =IFERROR(__xludf.DUMMYFUNCTION("""COMPUTED_VALUE"""),0.7118469843264902) -> 0.71184698 | F24: =IFERROR(__xludf.DUMMYFUNCTION("""COMPUTED_VALUE"""),"") | G24: =IFERROR(__xludf.DUMMYFUNCTION("""COMPUTED_VALUE"""),"") | H24: =IFERROR(__xludf.DUMMYFUNCTION("""COMPUTED_VALUE"""),0.5719683249718881) -> 0.57196833 | I24: 0.23515858
A25: 0.066727885 | B25: 0 | D25: =IFERROR(__xludf.DUMMYFUNCTION("""COMPUTED_VALUE"""),"") | E25: =IFERROR(__xludf.DUMMYFUNCTION("""COMPUTED_VALUE"""),0.8603709183864263) -> 0.86037092 | F25: =IFERROR(__xludf.DUMMYFUNCTION("""COMPUTED_VALUE"""),1.0) -> 1 | G25: =IFERROR(__xludf.DUMMYFUNCTION("""COMPUTED_VALUE"""),1.0) -> 1 | H25: =IFERROR(__xludf.DUMMYFUNCTION("""COMPUTED_VALUE"""),0.6778084008282622) -> 0.6778084 | I25: 0.63287357
A26: 0.12809473 | B26: 0 | D26: =IFERROR(__xludf.DUMMYFUNCTION("""COMPUTED_VALUE"""),"") | E26: =IFERROR(__xludf.DUMMYFUNCTION("""COMPUTED_VALUE"""),0.7686352339046211) -> 0.76863523 | F26: =IFERROR(__xludf.DUMMYFUNCTION("""COMPUTED_VALUE"""),1.0) -> 1 | G26: =IFERROR(__xludf.DUMMYFUNCTION("""COMPUTED_VALUE"""),1.0) -> 1 | H26: =IFERROR(__xludf.DUMMYFUNCTION("""COMPUTED_VALUE"""),0.8834762343634998) -> 0.88347623 | I26: 0.63050643
A27: 0.17691454 | D27: =IFERROR(__xludf.DUMMYFUNCTION("""COMPUTED_VALUE"""),"") | E27: =IFERROR(__xludf.DUMMYFUNCTION("""COMPUTED_VALUE"""),0.8552895086758483) -> 0.85528951 | F27: =IFERROR(__xludf.DUMMYFUNCTION("""COMPUTED_VALUE"""),"") | G27: =IFERROR(__xludf.DUMMYFUNCTION("""COMPUTED_VALUE"""),1.0) -> 1 | H27: =IFERROR(__xludf.DUMMYFUNCTION("""COMPUTED_VALUE"""),1.0) -> 1 | I27: 0.46382238
A28: 0.12480037 | D28: =IFERROR(__xludf.DUMMYFUNCTION("""COMPUTED_VALUE"""),"") | E28: =IFERROR(__xludf.DUMMYFUNCTION("""COMPUTED_VALUE"""),0.8501333696778393) -> 0.85013337 | F28: =IFERROR(__xludf.DUMMYFUNCTION("""COMPUTED_VALUE"""),"") | G28: =IFERROR(__xludf.DUMMYFUNCTION("""COMPUTED_VALUE"""),1.0) -> 1 | H28: =IFERROR(__xludf.DUMMYFUNCTION("""COMPUTED_VALUE"""),0.8454372130709235) -> 0.84543721 | I28: 0.44707706
D29: =IFERROR(__xludf.DUMMYFUNCTION("""COMPUTED_VALUE"""),"") | E29: =IFERROR(__xludf.DUMMYFUNCTION("""COMPUTED_VALUE"""),0.7306007127585364) -> 0.73060071 | F29: =IFERROR(__xludf.DUMMYFUNCTION("""COMPUTED_VALUE"""),"") | G29: =IFERROR(__xludf.DUMMYFUNCTION("""COMPUTED_VALUE"""),"") | H29: =IFERROR(__xludf.DUMMYFUNCTION("""COMPUTED_VALUE"""),0.6809165037794195) -> 0.6809165 | I29: 0.25074183
A30: 0.078767123 | D30: =IFERROR(__xludf.DUMMYFUNCTION("""COMPUTED_VALUE"""),"") | E30: =IFERROR(__xludf.DUMMYFUNCTION("""COMPUTED_VALUE"""),0.7232191531066832) -> 0.72321915 | F30: =IFERROR(__xludf.DUMMYFUNCTION("""COMPUTED_VALUE"""),"") | G30: =IFERROR(__xludf.DUMMYFUNCTION("""COMPUTED_VALUE"""),1.0) -> 1 | H30: =IFERROR(__xludf.DUMMYFUNCTION("""COMPUTED_VALUE"""),0.7386982125651004) -> 0.73869821 | I30: 0.40467461
A31: 0.057549234 | D31: =IFERROR(__xludf.DUMMYFUNCTION("""COMPUTED_VALUE"""),"") | E31: =IFERROR(__xludf.DUMMYFUNCTION("""COMPUTED_VALUE"""),0.7413895988672289) -> 0.7413896 | F31: =IFERROR(__xludf.DUMMYFUNCTION("""COMPUTED_VALUE"""),"") | G31: =IFERROR(__xludf.DUMMYFUNCTION("""COMPUTED_VALUE"""),1.0) -> 1 | H31: =IFERROR(__xludf.DUMMYFUNCTION("""COMPUTED_VALUE"""),0.606602574247684) -> 0.60660257 | I31: 0.39600766
A32: 0.17125984 | B32: 0 | D32: =IFERROR(__xludf.DUMMYFUNCTION("""COMPUTED_VALUE"""),"") | E32: =IFERROR(__xludf.DUMMYFUNCTION("""COMPUTED_VALUE"""),0.21404331870033824) -> 0.21404332 | F32: =IFERROR(__xludf.DUMMYFUNCTION("""COMPUTED_VALUE"""),1.0) -> 1 | G32: =IFERROR(__xludf.DUMMYFUNCTION("""COMPUTED_VALUE"""),1.0) -> 1 | H32: =IFERROR(__xludf.DUMMYFUNCTION("""COMPUTED_VALUE"""),0.3568361372236371) -> 0.35683614 | I32: 0.43919444
A33: 0.090909091 | B33: 1 | D33: =IFERROR(__xludf.DUMMYFUNCTION("""COMPUTED_VALUE"""),"") | E33: =IFERROR(__xludf.DUMMYFUNCTION("""COMPUTED_VALUE"""),1.0) -> 1 | F33: =IFERROR(__xludf.DUMMYFUNCTION("""COMPUTED_VALUE"""),1.0) -> 1 | G33: =IFERROR(__xludf.DUMMYFUNCTION("""COMPUTED_VALUE"""),1.0) -> 1 | H33: =IFERROR(__xludf.DUMMYFUNCTION("""COMPUTED_VALUE"""),0.8082208954445161) -> 0.8082209 | I33: 0.68082209
A34: 0.10719132 | B34: 0 | D34: =IFERROR(__xludf.DUMMYFUNCTION("""COMPUTED_VALUE"""),"") | E34: =IFERROR(__xludf.DUMMYFUNCTION("""COMPUTED_VALUE"""),0.9808551827008829) -> 0.98085518 | F34: =IFERROR(__xludf.DUMMYFUNCTION("""COMPUTED_VALUE"""),1.0) -> 1 | G34: =IFERROR(__xludf.DUMMYFUNCTION("""COMPUTED_VALUE"""),1.0) -> 1 | H34: =IFERROR(__xludf.DUMMYFUNCTION("""COMPUTED_VALUE"""),0.5991484674713998) -> 0.59914847 | I34: 0.65512864
A35: 0.074992156 | B35: 1 | D35: =IFERROR(__xludf.DUMMYFUNCTION("""COMPUTED_VALUE"""),"") | E35: =IFERROR(__xludf.DUMMYFUNCTION("""COMPUTED_VALUE"""),0.905291602379154) -> 0.9052916 | F35: =IFERROR(__xludf.DUMMYFUNCTION("""COMPUTED_VALUE"""),1.0) -> 1 | G35: =IFERROR(__xludf.DUMMYFUNCTION("""COMPUTED_VALUE"""),1.0) -> 1 | H35: =IFERROR(__xludf.DUMMYFUNCTION("""COMPUTED_VALUE"""),0.5070483768501975) -> 0.50704838 | I35: 0.62702774
A36: 0.15638575 | B36: 0 | D36: =IFERROR(__xludf.DUMMYFUNCTION("""COMPUTED_VALUE"""),"") | E36: =IFERROR(__xludf.DUMMYFUNCTION("""COMPUTED_VALUE"""),1.0) -> 1 | F36: =IFERROR(__xludf.DUMMYFUNCTION("""COMPUTED_VALUE"""),1.0) -> 1 | G36: =IFERROR(__xludf.DUMMYFUNCTION("""COMPUTED_VALUE"""),1.0) -> 1 | H36: =IFERROR(__xludf.DUMMYFUNCTION("""COMPUTED_VALUE"""),0.8985187633496309) -> 0.89851876 | I36: 0.68985188
A37: 0.046636086 | D37: =IFERROR(__xludf.DUMMYFUNCTION("""COMPUTED_VALUE"""),"") | E37: =IFERROR(__xludf.DUMMYFUNCTION("""COMPUTED_VALUE"""),0.3768340340141598) -> 0.37683403 | F37: =IFERROR(__xludf.DUMMYFUNCTION("""COMPUTED_VALUE"""),"") | G37: =IFERROR(__xludf.DUMMYFUNCTION("""COMPUTED_VALUE"""),1.0) -> 1 | H37: =IFERROR(__xludf.DUMMYFUNCTION("""COMPUTED_VALUE"""),0.5759602604370906) -> 0.57596026 | I37: 0.30180453
A38: 0.075988628 | B38: 0 | D38: =IFERROR(__xludf.DUMMYFUNCTION("""COMPUTED_VALUE"""),"") | E38: =IFERROR(__xludf.DUMMYFUNCTION("""COMPUTED_VALUE"""),0.6960865272992703) -> 0.69608653 | F38: =IFERROR(__xludf.DUMMYFUNCTION("""COMPUTED_VALUE"""),1.0) -> 1 | G38: =IFERROR(__xludf.DUMMYFUNCTION("""COMPUTED_VALUE"""),1.0) -> 1 | H38: =IFERROR(__xludf.DUMMYFUNCTION("""COMPUTED_VALUE"""),0.8948082015634227) -> 0.8948082 | I38: 0.61350245
A39: 0.12480253 | B39: 0 | D39: =IFERROR(__xludf.DUMMYFUNCTION("""COMPUTED_VALUE"""),"") | E39: =IFERROR(__xludf.DUMMYFUNCTION("""COMPUTED_VALUE"""),1.0) -> 1 | F39: =IFERROR(__xludf.DUMMYFUNCTION("""COMPUTED_VALUE"""),1.0) -> 1 | G39: =IFERROR(__xludf.DUMMYFUNCTION("""COMPUTED_VALUE"""),1.0) -> 1 | H39: =IFERROR(__xludf.DUMMYFUNCTION("""COMPUTED_VALUE"""),0.5070483768501975) -> 0.50704838 | I39: 0.65070484
A40: 0.049483649 | D40: =IFERROR(__xludf.DUMMYFUNCTION("""COMPUTED_VALUE"""),"") | E40: =IFERROR(__xludf.DUMMYFUNCTION("""COMPUTED_VALUE"""),0.7518563800998207) -> 0.75185638 | F40: =IFERROR(__xludf.DUMMYFUNCTION("""COMPUTED_VALUE"""),"") | G40: =IFERROR(__xludf.DUMMYFUNCTION("""COMPUTED_VALUE"""),1.0) -> 1 | H40: =IFERROR(__xludf.DUMMYFUNCTION("""COMPUTED_VALUE"""),0.7788377172062704) -> 0.77883772 | I40: 0.41584787
A41: 0.13698049 | B41: 0 | D41: =IFERROR(__xludf.DUMMYFUNCTION("""COMPUTED_VALUE"""),"") | E41: =IFERROR(__xludf.DUMMYFUNCTION("""COMPUTED_VALUE"""),0.43230913174650915) -> 0.43230913 | F41: =IFERROR(__xludf.DUMMYFUNCTION("""COMPUTED_VALUE"""),1.0) -> 1 | G41: =IFERROR(__xludf.DUMMYFUNCTION("""COMPUTED_VALUE"""),1.0) -> 1 | H41: =IFERROR(__xludf.DUMMYFUNCTION("""COMPUTED_VALUE"""),0.6833865756013802) -> 0.68338658 | I41: 0.52641594
D42: =IFERROR(__xludf.DUMMYFUNCTION("""COMPUTED_VALUE"""),"") | E42: =IFERROR(__xludf.DUMMYFUNCTION("""COMPUTED_VALUE"""),0.9226092522860491) -> 0.92260925 | F42: =IFERROR(__xludf.DUMMYFUNCTION("""COMPUTED_VALUE"""),"") | G42: =IFERROR(__xludf.DUMMYFUNCTION("""COMPUTED_VALUE"""),"") | H42: =IFERROR(__xludf.DUMMYFUNCTION("""COMPUTED_VALUE"""),0.4467820234631535) -> 0.44678202 | I42: 0.27533052
A43: 0.17634768 | D43: =IFERROR(__xludf.DUMMYFUNCTION("""COMPUTED_VALUE"""),"") | E43: =IFERROR(__xludf.DUMMYFUNCTION("""COMPUTED_VALUE"""),0.7552770036509245) -> 0.755277 | F43: =IFERROR(__xludf.DUMMYFUNCTION("""COMPUTED_VALUE"""),"") | G43: =IFERROR(__xludf.DUMMYFUNCTION("""COMPUTED_VALUE"""),1.0) -> 1 | H43: =IFERROR(__xludf.DUMMYFUNCTION("""COMPUTED_VALUE"""),0.7788377172062704) -> 0.77883772 | I43: 0.41670302
A44: 0.041666667 | B44: 1 | D44: =IFERROR(__xludf.DUMMYFUNCTION("""COMPUTED_VALUE"""),"") | E44: =IFERROR(__xludf.DUMMYFUNCTION("""COMPUTED_VALUE"""),0.5288716380402964) -> 0.52887164 | F44: =IFERROR(__xludf.DUMMYFUNCTION("""COMPUTED_VALUE"""),1.0) -> 1 | G44: =IFERROR(__xludf.DUMMYFUNCTION("""COMPUTED_VALUE"""),1.0) -> 1 | H44: =IFERROR(__xludf.DUMMYFUNCTION("""COMPUTED_VALUE"""),0.8036181606867903) -> 0.80361816 | I44: 0.56257973
A45: 0.14459122 | B45: 0 | D45: =IFERROR(__xludf.DUMMYFUNCTION("""COMPUTED_VALUE"""),"") | E45: =IFERROR(__xludf.DUMMYFUNCTION("""COMPUTED_VALUE"""),0.40566762681079266) -> 0.40566763 | F45: =IFERROR(__xludf.DUMMYFUNCTION("""COMPUTED_VALUE"""),1.0) -> 1 | G45: =IFERROR(__xludf.DUMMYFUNCTION("""COMPUTED_VALUE"""),1.0) -> 1 | H45: =IFERROR(__xludf.DUMMYFUNCTION("""COMPUTED_VALUE"""),0.6644979373420747) -> 0.66449794 | I45: 0.5178667
A46: 0.096700796 | D46: =IFERROR(__xludf.DUMMYFUNCTION("""COMPUTED_VALUE"""),"") | E46: =IFERROR(__xludf.DUMMYFUNCTION("""COMPUTED_VALUE"""),0.6486927451058364) -> 0.64869275 | F46: =IFERROR(__xludf.DUMMYFUNCTION("""COMPUTED_VALUE"""),"") | G46: =IFERROR(__xludf.DUMMYFUNCTION("""COMPUTED_VALUE"""),1.0) -> 1 | H46: =IFERROR(__xludf.DUMMYFUNCTION("""COMPUTED_VALUE"""),0.821734761995934) -> 0.82173476 | I46: 0.39434666
A47: 0.031393889 | D47: =IFERROR(__xludf.DUMMYFUNCTION("""COMPUTED_VALUE"""),"") | E47: =IFERROR(__xludf.DUMMYFUNCTION("""COMPUTED_VALUE"""),0.5658122078059921) -> 0.56581221 | F47: =IFERROR(__xludf.DUMMYFUNCTION("""COMPUTED_VALUE"""),"") | G47: =IFERROR(__xludf.DUMMYFUNCTION("""COMPUTED_VALUE"""),1.0) -> 1 | H47: =IFERROR(__xludf.DUMMYFUNCTION("""COMPUTED_VALUE"""),0.5342285193497109) -> 0.53422852 | I47: 0.3448759
A48: 0.12745098 | D48: =IFERROR(__xludf.DUMMYFUNCTION("""COMPUTED_VALUE"""),"") | E48: =IFERROR(__xludf.DUMMYFUNCTION("""COMPUTED_VALUE"""),0.7449133585076116) -> 0.74491336 | F48: =IFERROR(__xludf.DUMMYFUNCTION("""COMPUTED_VALUE"""),"") | G48: =IFERROR(__xludf.DUMMYFUNCTION("""COMPUTED_VALUE"""),1.0) -> 1 | H48: =IFERROR(__xludf.DUMMYFUNCTION("""COMPUTED_VALUE"""),0.7024742311529858) -> 0.70247423 | I48: 0.40647576
A49: 0.078470825 | B49: 0 | D49: =IFERROR(__xludf.DUMMYFUNCTION("""COMPUTED_VALUE"""),"") | E49: =IFERROR(__xludf.DUMMYFUNCTION("""COMPUTED_VALUE"""),0.945105144241996) -> 0.94510514 | F49: =IFERROR(__xludf.DUMMYFUNCTION("""COMPUTED_VALUE"""),1.0) -> 1 | G49: =IFERROR(__xludf.DUMMYFUNCTION("""COMPUTED_VALUE"""),1.0) -> 1 | H49: =IFERROR(__xludf.DUMMYFUNCTION("""COMPUTED_VALUE"""),0.8608655331288015) -> 0.86086553 | I49: 0.67236284
A50: 0.15988858 | D50: =IFERROR(__xludf.DUMMYFUNCTION("""COMPUTED_VALUE"""),"") | E50: =IFERROR(__xludf.DUMMYFUNCTION("""COMPUTED_VALUE"""),0.6532759624345169) -> 0.65327596 | F50: =IFERROR(__xludf.DUMMYFUNCTION("""COMPUTED_VALUE"""),"") | G50: =IFERROR(__xludf.DUMMYFUNCTION("""COMPUTED_VALUE"""),1.0) -> 1 | H50: =IFERROR(__xludf.DUMMYFUNCTION("""COMPUTED_VALUE"""),0.5070483768501975) -> 0.50704838 | I50: 0.36402383
A51: 0.14022436 | B51: 0 | D51: =IFERROR(__xludf.DUMMYFUNCTION("""COMPUTED_VALUE"""),"") | E51: =IFERROR(__xludf.DUMMYFUNCTION("""COMPUTED_VALUE"""),0.781503141717807) -> 0.78150314 | F51: =IFERROR(__xludf.DUMMYFUNCTION("""COMPUTED_VALUE"""),1.0) -> 1 | G51: =IFERROR(__xludf.DUMMYFUNCTION("""COMPUTED_VALUE"""),1.0) -> 1 | H51: =IFERROR(__xludf.DUMMYFUNCTION("""COMPUTED_VALUE"""),0.5838323782038936) -> 0.58383238 | I51: 0.60375902
A52: 0.12009063 | D52: =IFERROR(__xludf.DUMMYFUNCTION("""COMPUTED_VALUE"""),"") | E52: =IFERROR(__xludf.DUMMYFUNCTION("""COMPUTED_VALUE"""),0.9411208839467466) -> 0.94112088 | F52: =IFERROR(__xludf.DUMMYFUNCTION("""COMPUTED_VALUE"""),"") | G52: =IFERROR(__xludf.DUMMYFUNCTION("""COMPUTED_VALUE"""),1.0) -> 1 | H52: =IFERROR(__xludf.DUMMYFUNCTION("""COMPUTED_VALUE"""),0.7451280479689457) -> 0.74512805 | I52: 0.45979303
A53: 0.078717201 | D53: =IFERROR(__xludf.DUMMYFUNCTION("""COMPUTED_VALUE"""),"") | E53: =IFERROR(__xludf.DUMMYFUNCTION("""COMPUTED_VALUE"""),0.5716075650904038) -> 0.57160757 | F53: =IFERROR(__xludf.DUMMYFUNCTION("""COMPUTED_VALUE"""),"") | G53: =IFERROR(__xludf.DUMMYFUNCTION("""COMPUTED_VALUE"""),1.0) -> 1 | H53: =IFERROR(__xludf.DUMMYFUNCTION("""COMPUTED_VALUE"""),0.0) -> 0 | I53: 0.29290189
A54: 0.13 | D54: =IFERROR(__xludf.DUMMYFUNCTION("""COMPUTED_VALUE"""),"") | E54: =IFERROR(__xludf.DUMMYFUNCTION("""COMPUTED_VALUE"""),0.9808551827008829) -> 0.98085518 | F54: =IFERROR(__xludf.DUMMYFUNCTION("""COMPUTED_VALUE"""),"") | G54: =IFERROR(__xludf.DUMMYFUNCTION("""COMPUTED_VALUE"""),1.0) -> 1 | H54: =IFERROR(__xludf.DUMMYFUNCTION("""COMPUTED_VALUE"""),0.5253619594718052) -> 0.52536196 | I54: 0.44774999
D55: =IFERROR(__xludf.DUMMYFUNCTION("""COMPUTED_VALUE"""),"") | E55: =IFERROR(__xludf.DUMMYFUNCTION("""COMPUTED_VALUE"""),0.9204907495688482) -> 0.92049075 | F55: =IFERROR(__xludf.DUMMYFUNCTION("""COMPUTED_VALUE"""),"") | G55: =IFERROR(__xludf.DUMMYFUNCTION("""COMPUTED_VALUE"""),"") | H55: =IFERROR(__xludf.DUMMYFUNCTION("""COMPUTED_VALUE"""),0.8228415853356936) -> 0.82284159 | I55: 0.31240685
A56: 0.039482415 | D56: =IFERROR(__xludf.DUMMYFUNCTION("""COMPUTED_VALUE"""),"") | E56: =IFERROR(__xludf.DUMMYFUNCTION("""COMPUTED_VALUE"""),0.12364556257381001) -> 0.12364556 | F56: =IFERROR(__xludf.DUMMYFUNCTION("""COMPUTED_VALUE"""),"") | G56: =IFERROR(__xludf.DUMMYFUNCTION("""COMPUTED_VALUE"""),1.0) -> 1 | H56: =IFERROR(__xludf.DUMMYFUNCTION("""COMPUTED_VALUE"""),0.3951485412186882) -> 0.39514854 | I56: 0.22042624
D57: =IFERROR(__xludf.DUMMYFUNCTION("""COMPUTED_VALUE"""),"") | E57: =IFERROR(__xludf.DUMMYFUNCTION("""COMPUTED_VALUE"""),1.0) -> 1 | F57: =IFERROR(__xludf.DUMMYFUNCTION("""COMPUTED_VALUE"""),"") | G57: =IFERROR(__xludf.DUMMYFUNCTION("""COMPUTED_VALUE"""),"") | H57: =IFERROR(__xludf.DUMMYFUNCTION("""COMPUTED_VALUE"""),0.4130723542258289) -> 0.41307235 | I57: 0.29130724
D58: =IFERROR(__xludf.DUMMYFUNCTION("""COMPUTED_VALUE"""),"") | E58: =IFERROR(__xludf.DUMMYFUNCTION("""COMPUTED_VALUE"""),0.823149971850111) -> 0.82314997 | F58: =IFERROR(__xludf.DUMMYFUNCTION("""COMPUTED_VALUE"""),"") | G58: =IFERROR(__xludf.DUMMYFUNCTION("""COMPUTED_VALUE"""),"") | H58: =IFERROR(__xludf.DUMMYFUNCTION("""COMPUTED_VALUE"""),0.29191618910194683) -> 0.29191619 | I58: 0.23497911
A59: 0.22474625 | D59: =IFERROR(__xludf.DUMMYFUNCTION("""COMPUTED_VALUE"""),"") | E59: =IFERROR(__xludf.DUMMYFUNCTION("""COMPUTED_VALUE"""),0.7518563800998207) -> 0.75185638 | F59: =IFERROR(__xludf.DUMMYFUNCTION("""COMPUTED_VALUE"""),"") | G59: =IFERROR(__xludf.DUMMYFUNCTION("""COMPUTED_VALUE"""),1.0) -> 1 | H59: =IFERROR(__xludf.DUMMYFUNCTION("""COMPUTED_VALUE"""),0.5915600452615529) -> 0.59156005 | I59: 0.3971201
A60: 0.11637081 | B60: 0 | D60: =IFERROR(__xludf.DUMMYFUNCTION("""COMPUTED_VALUE"""),"") | E60: =IFERROR(__xludf.DUMMYFUNCTION("""COMPUTED_VALUE"""),0.7586645771823989) -> 0.75866458 | F60: =IFERROR(__xludf.DUMMYFUNCTION("""COMPUTED_VALUE"""),1.0) -> 1 | G60: =IFERROR(__xludf.DUMMYFUNCTION("""COMPUTED_VALUE"""),1.0) -> 1 | H60: =IFERROR(__xludf.DUMMYFUNCTION("""COMPUTED_VALUE"""),0.6870647303206351) -> 0.68706473 | I60: 0.60837262
D61: =IFERROR(__xludf.DUMMYFUNCTION("""COMPUTED_VALUE"""),"") | E61: =IFERROR(__xludf.DUMMYFUNCTION("""COMPUTED_VALUE"""),0.10238989523252559) -> 0.1023899 | F61: =IFERROR(__xludf.DUMMYFUNCTION("""COMPUTED_VALUE"""),"") | G61: =IFERROR(__xludf.DUMMYFUNCTION("""COMPUTED_VALUE"""),"") | H61: =IFERROR(__xludf.DUMMYFUNCTION("""COMPUTED_VALUE"""),0.23164983571490277) -> 0.23164984 | I61: 0.048762457
A62: 0.045704368 | D62: =IFERROR(__xludf.DUMMYFUNCTION("""COMPUTED_VALUE"""),"") | E62: =IFERROR(__xludf.DUMMYFUNCTION("""COMPUTED_VALUE"""),0.25886312191752414) -> 0.25886312 | F62: =IFERROR(__xludf.DUMMYFUNCTION("""COMPUTED_VALUE"""),"") | G62: =IFERROR(__xludf.DUMMYFUNCTION("""COMPUTED_VALUE"""),1.0) -> 1 | H62: =IFERROR(__xludf.DUMMYFUNCTION("""COMPUTED_VALUE"""),0.336288352872133) -> 0.33628835 | I62: 0.24834462
A63: 0.060270837 | D63: =IFERROR(__xludf.DUMMYFUNCTION("""COMPUTED_VALUE"""),"") | E63: =IFERROR(__xludf.DUMMYFUNCTION("""COMPUTED_VALUE"""),0.6753342500415529) -> 0.67533425 | F63: =IFERROR(__xludf.DUMMYFUNCTION("""COMPUTED_VALUE"""),"") | G63: =IFERROR(__xludf.DUMMYFUNCTION("""COMPUTED_VALUE"""),1.0) -> 1 | H63: =IFERROR(__xludf.DUMMYFUNCTION("""COMPUTED_VALUE"""),0.5597603386555386) -> 0.55976034 | I63: 0.3748096
A64: 0.12866604 | D64: =IFERROR(__xludf.DUMMYFUNCTION("""COMPUTED_VALUE"""),"") | E64: =IFERROR(__xludf.DUMMYFUNCTION("""COMPUTED_VALUE"""),0.9662442714017269) -> 0.96624427 | F64: =IFERROR(__xludf.DUMMYFUNCTION("""COMPUTED_VALUE"""),"") | G64: =IFERROR(__xludf.DUMMYFUNCTION("""COMPUTED_VALUE"""),1.0) -> 1 | H64: =IFERROR(__xludf.DUMMYFUNCTION("""COMPUTED_VALUE"""),0.4071821038264457) -> 0.4071821 | I64: 0.43227928
A65: 0.19244604 | B65: 1 | D65: =IFERROR(__xludf.DUMMYFUNCTION("""COMPUTED_VALUE"""),"") | E65: =IFERROR(__xludf.DUMMYFUNCTION("""COMPUTED_VALUE"""),0.7586645771823989) -> 0.75866458 | F65: =IFERROR(__xludf.DUMMYFUNCTION("""COMPUTED_VALUE"""),1.0) -> 1 | G65: =IFERROR(__xludf.DUMMYFUNCTION("""COMPUTED_VALUE"""),1.0) -> 1 | H65: =IFERROR(__xludf.DUMMYFUNCTION("""COMPUTED_VALUE"""),0.5342285193497109) -> 0.53422852 | I65: 0.593089
D66: =IFERROR(__xludf.DUMMYFUNCTION("""COMPUTED_VALUE"""),"") | E66: =IFERROR(__xludf.DUMMYFUNCTION("""COMPUTED_VALUE"""),1.0) -> 1 | F66: =IFERROR(__xludf.DUMMYFUNCTION("""COMPUTED_VALUE"""),"") | G66: =IFERROR(__xludf.DUMMYFUNCTION("""COMPUTED_VALUE"""),"") | H66: =IFERROR(__xludf.DUMMYFUNCTION("""COMPUTED_VALUE"""),0.8590437017151352) -> 0.8590437 | I66: 0.33590437
A67: 0.16947649 | B67: 0 | D67: =IFERROR(__xludf.DUMMYFUNCTION("""COMPUTED_VALUE"""),"") | E67: =IFERROR(__xludf.DUMMYFUNCTION("""COMPUTED_VALUE"""),1.0) -> 1 | F67: =IFERROR(__xludf.DUMMYFUNCTION("""COMPUTED_VALUE"""),1.0) -> 1 | G67: =IFERROR(__xludf.DUMMYFUNCTION("""COMPUTED_VALUE"""),1.0) -> 1 | H67: =IFERROR(__xludf.DUMMYFUNCTION("""COMPUTED_VALUE"""),0.5646860794664548) -> 0.56468608 | I67: 0.65646861
A68: 0.060218978 | D68: =IFERROR(__xludf.DUMMYFUNCTION("""COMPUTED_VALUE"""),"") | E68: =IFERROR(__xludf.DUMMYFUNCTION("""COMPUTED_VALUE"""),0.6096957991638974) -> 0.6096958 | F68: =IFERROR(__xludf.DUMMYFUNCTION("""COMPUTED_VALUE"""),"") | G68: =IFERROR(__xludf.DUMMYFUNCTION("""COMPUTED_VALUE"""),1.0) -> 1 | H68: =IFERROR(__xludf.DUMMYFUNCTION("""COMPUTED_VALUE"""),0.5471878814913675) -> 0.54718788 | I68: 0.35714274
A69: 0.15954119 | D69: =IFERROR(__xludf.DUMMYFUNCTION("""COMPUTED_VALUE"""),"") | E69: =IFERROR(__xludf.DUMMYFUNCTION("""COMPUTED_VALUE"""),0.8653797340426068) -> 0.86537973 | F69: =IFERROR(__xludf.DUMMYFUNCTION("""COMPUTED_VALUE"""),"") | G69: =IFERROR(__xludf.DUMMYFUNCTION("""COMPUTED_VALUE"""),1.0) -> 1 | H69: =IFERROR(__xludf.DUMMYFUNCTION("""COMPUTED_VALUE"""),0.873402343753667) -> 0.87340234 | I69: 0.45368517
A70: 0.061068702 | D70: =IFERROR(__xludf.DUMMYFUNCTION("""COMPUTED_VALUE"""),"") | E70: =IFERROR(__xludf.DUMMYFUNCTION("""COMPUTED_VALUE"""),0.0) -> 0 | F70: =IFERROR(__xludf.DUMMYFUNCTION("""COMPUTED_VALUE"""),"") | G70: =IFERROR(__xludf.DUMMYFUNCTION("""COMPUTED_VALUE"""),1.0) -> 1 | H70: =IFERROR(__xludf.DUMMYFUNCTION("""COMPUTED_VALUE"""),0.485446409123802) -> 0.48544641 | I70: 0.19854464
A71: 0.10730744 | B71: 0 | D71: =IFERROR(__xludf.DUMMYFUNCTION("""COMPUTED_VALUE"""),"") | E71: =IFERROR(__xludf.DUMMYFUNCTION("""COMPUTED_VALUE"""),0.9204907495688482) -> 0.92049075 | F71: =IFERROR(__xludf.DUMMYFUNCTION("""COMPUTED_VALUE"""),1.0) -> 1 | G71: =IFERROR(__xludf.DUMMYFUNCTION("""COMPUTED_VALUE"""),1.0) -> 1 | H71: =IFERROR(__xludf.DUMMYFUNCTION("""COMPUTED_VALUE"""),0.6010243994745663) -> 0.6010244 | I71: 0.64022513
A72: 0.041465767 | B72: 0 | D72: =IFERROR(__xludf.DUMMYFUNCTION("""COMPUTED_VALUE"""),"") | E72: =IFERROR(__xludf.DUMMYFUNCTION("""COMPUTED_VALUE"""),1.0) -> 1 | F72: =IFERROR(__xludf.DUMMYFUNCTION("""COMPUTED_VALUE"""),1.0) -> 1 | G72: =IFERROR(__xludf.DUMMYFUNCTION("""COMPUTED_VALUE"""),1.0) -> 1 | H72: =IFERROR(__xludf.DUMMYFUNCTION("""COMPUTED_VALUE"""),0.5342285193497109) -> 0.53422852 | I72: 0.65342285
A73: 0.059892606 | B73: 1 | D73: =IFERROR(__xludf.DUMMYFUNCTION("""COMPUTED_VALUE"""),"") | E73: =IFERROR(__xludf.DUMMYFUNCTION("""COMPUTED_VALUE"""),0.6753342500415529) -> 0.67533425 | F73: =IFERROR(__xludf.DUMMYFUNCTION("""COMPUTED_VALUE"""),1.0) -> 1 | G73: =IFERROR(__xludf.DUMMYFUNCTION("""COMPUTED_VALUE"""),1.0) -> 1 | H73: =IFERROR(__xludf.DUMMYFUNCTION("""COMPUTED_VALUE"""),0.7288655627113247) -> 0.72886556 | I73: 0.59172012
A74: 0.15520282 | B74: 1 | D74: =IFERROR(__xludf.DUMMYFUNCTION("""COMPUTED_VALUE"""),"") | E74: =IFERROR(__xludf.DUMMYFUNCTION("""COMPUTED_VALUE"""),0.7342340212618556) -> 0.73423402 | F74: =IFERROR(__xludf.DUMMYFUNCTION("""COMPUTED_VALUE"""),1.0) -> 1 | G74: =IFERROR(__xludf.DUMMYFUNCTION("""COMPUTED_VALUE"""),1.0) -> 1 | H74: =IFERROR(__xludf.DUMMYFUNCTION("""COMPUTED_VALUE"""),0.5289310150557403) -> 0.52893102 | I74: 0.58645161
A75: 0.035543608 | D75: =IFERROR(__xludf.DUMMYFUNCTION("""COMPUTED_VALUE"""),"") | E75: =IFERROR(__xludf.DUMMYFUNCTION("""COMPUTED_VALUE"""),0.3867110571043727) -> 0.38671106 | F75: =IFERROR(__xludf.DUMMYFUNCTION("""COMPUTED_VALUE"""),"") | G75: =IFERROR(__xludf.DUMMYFUNCTION("""COMPUTED_VALUE"""),1.0) -> 1 | H75: =IFERROR(__xludf.DUMMYFUNCTION("""COMPUTED_VALUE"""),0.0) -> 0 | I75: 0.24667776
A76: 0.15443335 | B76: 0 | D76: =IFERROR(__xludf.DUMMYFUNCTION("""COMPUTED_VALUE"""),"") | E76: =IFERROR(__xludf.DUMMYFUNCTION("""COMPUTED_VALUE"""),0.928889022542185) -> 0.92888902 | F76: =IFERROR(__xludf.DUMMYFUNCTION("""COMPUTED_VALUE"""),1.0) -> 1 | G76: =IFERROR(__xludf.DUMMYFUNCTION("""COMPUTED_VALUE"""),1.0) -> 1 | H76: =IFERROR(__xludf.DUMMYFUNCTION("""COMPUTED_VALUE"""),0.6961219834498718) -> 0.69612198 | I76: 0.65183445
A77: 0.1625 | B77: 1 | D77: =IFERROR(__xludf.DUMMYFUNCTION("""COMPUTED_VALUE"""),"") | E77: =IFERROR(__xludf.DUMMYFUNCTION("""COMPUTED_VALUE"""),0.7518563800998207) -> 0.75185638 | F77: =IFERROR(__xludf.DUMMYFUNCTION("""COMPUTED_VALUE"""),1.0) -> 1 | G77: =IFERROR(__xludf.DUMMYFUNCTION("""COMPUTED_VALUE"""),1.0) -> 1 | H77: =IFERROR(__xludf.DUMMYFUNCTION("""COMPUTED_VALUE"""),0.6400685952060838) -> 0.6400686 | I77: 0.60197095
A78: 0.056331471 | D78: =IFERROR(__xludf.DUMMYFUNCTION("""COMPUTED_VALUE"""),"") | E78: =IFERROR(__xludf.DUMMYFUNCTION("""COMPUTED_VALUE"""),1.0) -> 1 | F78: =IFERROR(__xludf.DUMMYFUNCTION("""COMPUTED_VALUE"""),"") | G78: =IFERROR(__xludf.DUMMYFUNCTION("""COMPUTED_VALUE"""),1.0) -> 1 | H78: =IFERROR(__xludf.DUMMYFUNCTION("""COMPUTED_VALUE"""),0.37642785751330293) -> 0.37642786 | I78: 0.43764279
A79: 0.064063685 | D79: =IFERROR(__xludf.DUMMYFUNCTION("""COMPUTED_VALUE"""),"") | E79: =IFERROR(__xludf.DUMMYFUNCTION("""COMPUTED_VALUE"""),0.7449133585076116) -> 0.74491336 | F79: =IFERROR(__xludf.DUMMYFUNCTION("""COMPUTED_VALUE"""),"") | G79: =IFERROR(__xludf.DUMMYFUNCTION("""COMPUTED_VALUE"""),1.0) -> 1 | H79: =IFERROR(__xludf.DUMMYFUNCTION("""COMPUTED_VALUE"""),0.6175420474412181) -> 0.61754205 | I79: 0.39798254
A80: 0.015368024 | D80: =IFERROR(__xludf.DUMMYFUNCTION("""COMPUTED_VALUE"""),"") | E80: =IFERROR(__xludf.DUMMYFUNCTION("""COMPUTED_VALUE"""),0.0) -> 0 | F80: =IFERROR(__xludf.DUMMYFUNCTION("""COMPUTED_VALUE"""),"") | G80: =IFERROR(__xludf.DUMMYFUNCTION("""COMPUTED_VALUE"""),1.0) -> 1 | H80: =IFERROR(__xludf.DUMMYFUNCTION("""COMPUTED_VALUE"""),0.5719683249718881) -> 0.57196833 | I80: 0.20719683
D81: =IFERROR(__xludf.DUMMYFUNCTION("""COMPUTED_VALUE"""),"") | E81: =IFERROR(__xludf.DUMMYFUNCTION("""COMPUTED_VALUE"""),0.937090826553437) -> 0.93709083 | F81: =IFERROR(__xludf.DUMMYFUNCTION("""COMPUTED_VALUE"""),"") | G81: =IFERROR(__xludf.DUMMYFUNCTION("""COMPUTED_VALUE"""),"") | H81: =IFERROR(__xludf.DUMMYFUNCTION("""COMPUTED_VALUE"""),0.5597603386555386) -> 0.55976034 | I81: 0.29024874
A82: 0.42673797 | B82: 0 | D82: =IFERROR(__xludf.DUMMYFUNCTION("""COMPUTED_VALUE"""),"") | E82: =IFERROR(__xludf.DUMMYFUNCTION("""COMPUTED_VALUE"""),0.9162149510524765) -> 0.91621495 | F82: =IFERROR(__xludf.DUMMYFUNCTION("""COMPUTED_VALUE"""),1.0) -> 1 | G82: =IFERROR(__xludf.DUMMYFUNCTION("""COMPUTED_VALUE"""),1.0) -> 1 | H82: =IFERROR(__xludf.DUMMYFUNCTION("""COMPUTED_VALUE"""),0.2094791359123752) -> 0.20947914 | I82: 0.60000165
A83: 0.10992366 | B83: 0 | D83: =IFERROR(__xludf.DUMMYFUNCTION("""COMPUTED_VALUE"""),"") | E83: =IFERROR(__xludf.DUMMYFUNCTION("""COMPUTED_VALUE"""),0.9330139069776836) -> 0.93301391 | F83: =IFERROR(__xludf.DUMMYFUNCTION("""COMPUTED_VALUE"""),1.0) -> 1 | G83: =IFERROR(__xludf.DUMMYFUNCTION("""COMPUTED_VALUE"""),1.0) -> 1 | H83: =IFERROR(__xludf.DUMMYFUNCTION("""COMPUTED_VALUE"""),0.7969543185154138) -> 0.79695432 | I83: 0.66294891
A84: 0.060980172 | D84: =IFERROR(__xludf.DUMMYFUNCTION("""COMPUTED_VALUE"""),"") | E84: =IFERROR(__xludf.DUMMYFUNCTION("""COMPUTED_VALUE"""),0.6393425607818837) -> 0.63934256 | F84: =IFERROR(__xludf.DUMMYFUNCTION("""COMPUTED_VALUE"""),"") | G84: =IFERROR(__xludf.DUMMYFUNCTION("""COMPUTED_VALUE"""),1.0) -> 1 | H84: =IFERROR(__xludf.DUMMYFUNCTION("""COMPUTED_VALUE"""),0.6990982929283924) -> 0.69909829 | I84: 0.37974547
A85: 0.041904387 | D85: =IFERROR(__xludf.DUMMYFUNCTION("""COMPUTED_VALUE"""),"") | E85: =IFERROR(__xludf.DUMMYFUNCTION("""COMPUTED_VALUE"""),0.77189675633534) -> 0.77189676 | F85: =IFERROR(__xludf.DUMMYFUNCTION("""COMPUTED_VALUE"""),"") | G85: =IFERROR(__xludf.DUMMYFUNCTION("""COMPUTED_VALUE"""),1.0) -> 1 | H85: =IFERROR(__xludf.DUMMYFUNCTION("""COMPUTED_VALUE"""),0.7597599030674651) -> 0.7597599 | I85: 0.41895018
A86: 0.020123839 | B86: 1 | D86: =IFERROR(__xludf.DUMMYFUNCTION("""COMPUTED_VALUE"""),"") | E86: =IFERROR(__xludf.DUMMYFUNCTION("""COMPUTED_VALUE"""),0.3227870895109485) -> 0.32278709 | F86: =IFERROR(__xludf.DUMMYFUNCTION("""COMPUTED_VALUE"""),1.0) -> 1 | G86: =IFERROR(__xludf.DUMMYFUNCTION("""COMPUTED_VALUE"""),1.0) -> 1 | H86: =IFERROR(__xludf.DUMMYFUNCTION("""COMPUTED_VALUE"""),0.648752326325584) -> 0.64875233 | I86: 0.49557201
A87: 0.035460993 | B87: 0 | D87: =IFERROR(__xludf.DUMMYFUNCTION("""COMPUTED_VALUE"""),"") | E87: =IFERROR(__xludf.DUMMYFUNCTION("""COMPUTED_VALUE"""),0.31090082806830316) -> 0.31090083 | F87: =IFERROR(__xludf.DUMMYFUNCTION("""COMPUTED_VALUE"""),1.0) -> 1 | G87: =IFERROR(__xludf.DUMMYFUNCTION("""COMPUTED_VALUE"""),1.0) -> 1 | H87: =IFERROR(__xludf.DUMMYFUNCTION("""COMPUTED_VALUE"""),0.8678764495390385) -> 0.86787645 | I87: 0.51451285
A88: 0.14934374 | D88: =IFERROR(__xludf.DUMMYFUNCTION("""COMPUTED_VALUE"""),"") | E88: =IFERROR(__xludf.DUMMYFUNCTION("""COMPUTED_VALUE"""),0.5884401318226129) -> 0.58844013 | F88: =IFERROR(__xludf.DUMMYFUNCTION("""COMPUTED_VALUE"""),"") | G88: =IFERROR(__xludf.DUMMYFUNCTION("""COMPUTED_VALUE"""),1.0) -> 1 | H88: =IFERROR(__xludf.DUMMYFUNCTION("""COMPUTED_VALUE"""),0.8454372130709235) -> 0.84543721 | I88: 0.38165375
A89: 0.053166898 | B89: 0 | D89: =IFERROR(__xludf.DUMMYFUNCTION("""COMPUTED_VALUE"""),"") | E89: =IFERROR(__xludf.DUMMYFUNCTION("""COMPUTED_VALUE"""),0.7342340212618556) -> 0.73423402 | F89: =IFERROR(__xludf.DUMMYFUNCTION("""COMPUTED_VALUE"""),1.0) -> 1 | G89: =IFERROR(__xludf.DUMMYFUNCTION("""COMPUTED_VALUE"""),1.0) -> 1 | H89: =IFERROR(__xludf.DUMMYFUNCTION("""COMPUTED_VALUE"""),0.6175420474412181) -> 0.61754205 | I89: 0.59531271
A90: 0.11078199 | B90: 0 | D90: =IFERROR(__xludf.DUMMYFUNCTION("""COMPUTED_VALUE"""),"") | E90: =IFERROR(__xludf.DUMMYFUNCTION("""COMPUTED_VALUE"""),0.8775973859947773) -> 0.87759739 | F90: =IFERROR(__xludf.DUMMYFUNCTION("""COMPUTED_VALUE"""),1.0) -> 1 | G90: =IFERROR(__xludf.DUMMYFUNCTION("""COMPUTED_VALUE"""),1.0) -> 1 | H90: =IFERROR(__xludf.DUMMYFUNCTION("""COMPUTED_VALUE"""),0.8985187633496309) -> 0.89851876 | I90: 0.65925122
D91: =IFERROR(__xludf.DUMMYFUNCTION("""COMPUTED_VALUE"""),"") | E91: =IFERROR(__xludf.DUMMYFUNCTION("""COMPUTED_VALUE"""),0.8628842706042471) -> 0.86288427 | F91: =IFERROR(__xludf.DUMMYFUNCTION("""COMPUTED_VALUE"""),"") | G91: =IFERROR(__xludf.DUMMYFUNCTION("""COMPUTED_VALUE"""),"") | H91: =IFERROR(__xludf.DUMMYFUNCTION("""COMPUTED_VALUE"""),0.7427283489499527) -> 0.74272835 | I91: 0.2899939
A92: 0.07306459 | D92: =IFERROR(__xludf.DUMMYFUNCTION("""COMPUTED_VALUE"""),"") | E92: =IFERROR(__xludf.DUMMYFUNCTION("""COMPUTED_VALUE"""),0.6198591523092037) -> 0.61985915 | F92: =IFERROR(__xludf.DUMMYFUNCTION("""COMPUTED_VALUE"""),"") | G92: =IFERROR(__xludf.DUMMYFUNCTION("""COMPUTED_VALUE"""),1.0) -> 1 | H92: =IFERROR(__xludf.DUMMYFUNCTION("""COMPUTED_VALUE"""),0.16552832889406768) -> 0.16552833 | I92: 0.32151762
D93: =IFERROR(__xludf.DUMMYFUNCTION("""COMPUTED_VALUE"""),"") | E93: =IFERROR(__xludf.DUMMYFUNCTION("""COMPUTED_VALUE"""),0.4570684369953818) -> 0.45706844 | F93: =IFERROR(__xludf.DUMMYFUNCTION("""COMPUTED_VALUE"""),"") | G93: =IFERROR(__xludf.DUMMYFUNCTION("""COMPUTED_VALUE"""),"") | H93: =IFERROR(__xludf.DUMMYFUNCTION("""COMPUTED_VALUE"""),0.4188813571978567) -> 0.41888136 | I93: 0.15615524
A94: 0.081233933 | B94: 0 | D94: =IFERROR(__xludf.DUMMYFUNCTION("""COMPUTED_VALUE"""),"") | E94: =IFERROR(__xludf.DUMMYFUNCTION("""COMPUTED_VALUE"""),0.9411208839467466) -> 0.94112088 | F94: =IFERROR(__xludf.DUMMYFUNCTION("""COMPUTED_VALUE"""),1.0) -> 1 | G94: =IFERROR(__xludf.DUMMYFUNCTION("""COMPUTED_VALUE"""),1.0) -> 1 | H94: =IFERROR(__xludf.DUMMYFUNCTION("""COMPUTED_VALUE"""),0.5526220993195275) -> 0.5526221 | I94: 0.64054243
A95: 0.039549741 | D95: =IFERROR(__xludf.DUMMYFUNCTION("""COMPUTED_VALUE"""),"") | E95: =IFERROR(__xludf.DUMMYFUNCTION("""COMPUTED_VALUE"""),0.8963010807295607) -> 0.89630108 | F95: =IFERROR(__xludf.DUMMYFUNCTION("""COMPUTED_VALUE"""),"") | G95: =IFERROR(__xludf.DUMMYFUNCTION("""COMPUTED_VALUE"""),1.0) -> 1 | H95: =IFERROR(__xludf.DUMMYFUNCTION("""COMPUTED_VALUE"""),0.7788377172062704) -> 0.77883772 | I95: 0.45195904
D96: =IFERROR(__xludf.DUMMYFUNCTION("""COMPUTED_VALUE"""),"") | E96: =IFERROR(__xludf.DUMMYFUNCTION("""COMPUTED_VALUE"""),0.5829185825435077) -> 0.58291858 | F96: =IFERROR(__xludf.DUMMYFUNCTION("""COMPUTED_VALUE"""),"") | G96: =IFERROR(__xludf.DUMMYFUNCTION("""COMPUTED_VALUE"""),"") | H96: =IFERROR(__xludf.DUMMYFUNCTION("""COMPUTED_VALUE"""),0.37642785751330293) -> 0.37642786 | I96: 0.18337243
A97: 0.027699265 | D97: =IFERROR(__xludf.DUMMYFUNCTION("""COMPUTED_VALUE"""),"") | E97: =IFERROR(__xludf.DUMMYFUNCTION("""COMPUTED_VALUE"""),0.5288716380402964) -> 0.52887164 | F97: =IFERROR(__xludf.DUMMYFUNCTION("""COMPUTED_VALUE"""),"") | G97: =IFERROR(__xludf.DUMMYFUNCTION("""COMPUTED_VALUE"""),1.0) -> 1 | H97: =IFERROR(__xludf.DUMMYFUNCTION("""COMPUTED_VALUE"""),0.0) -> 0 | I97: 0.28221791
A98: 0.10586177 | D98: =IFERROR(__xludf.DUMMYFUNCTION("""COMPUTED_VALUE"""),"") | E98: =IFERROR(__xludf.DUMMYFUNCTION("""COMPUTED_VALUE"""),0.0) -> 0 | F98: =IFERROR(__xludf.DUMMYFUNCTION("""COMPUTED_VALUE"""),"") | G98: =IFERROR(__xludf.DUMMYFUNCTION("""COMPUTED_VALUE"""),1.0) -> 1 | H98: =IFERROR(__xludf.DUMMYFUNCTION("""COMPUTED_VALUE"""),0.3951485412186882) -> 0.39514854 | I98: 0.18951485
A99: 0.07411859 | D99: =IFERROR(__xludf.DUMMYFUNCTION("""COMPUTED_VALUE"""),"") | E99: =IFERROR(__xludf.DUMMYFUNCTION("""COMPUTED_VALUE"""),0.614814300769033) -> 0.6148143 | F99: =IFERROR(__xludf.DUMMYFUNCTION("""COMPUTED_VALUE"""),"") | G99: =IFERROR(__xludf.DUMMYFUNCTION("""COMPUTED_VALUE"""),1.0) -> 1 | H99: =IFERROR(__xludf.DUMMYFUNCTION("""COMPUTED_VALUE"""),0.18607611324557238) -> 0.18607611 | I99: 0.32231119
A100: 0.072124756 | B100: 0 | D100: =IFERROR(__xludf.DUMMYFUNCTION("""COMPUTED_VALUE"""),"") | E100: =IFERROR(__xludf.DUMMYFUNCTION("""COMPUTED_VALUE"""),0.6198591523092037) -> 0.61985915 | F100: =IFERROR(__xludf.DUMMYFUNCTION("""COMPUTED_VALUE"""),1.0) -> 1 | G100: =IFERROR(__xludf.DUMMYFUNCTION("""COMPUTED_VALUE"""),1.0) -> 1 | H100: =IFERROR(__xludf.DUMMYFUNCTION("""COMPUTED_VALUE"""),0.26784414955359176) -> 0.26784415 | I100: 0.5317492
...

Sheet Papers
A1: mode | B1: paperId | C1: title | D1: publication_date | E1: year | F1: publication_types | G1: fields_of_study | H1: influential_citation_count | I1: citation_count | J1: abstract | K1: external_ids | L1: doi | M1: is_open_access | N1: open_access_pdf_url | O1: journal_pages_range | P1: pages_total | Q1: references_pages | R1: references_count | S1: _max_cited_year | T1: authors_hindex_list | U1: mean_author_hindex | V1: cites_per_day | W1: recency_delay_years | X1: pages_minus_refs | Y1: normalized_pages_minus_refs | Z1: normalized_references_count | AA1: normalized_recency_delay | AB1: normalized_cites_per_day | AC1: normalized_mean_author_hindex | AD1: composite_score | AE1: excluded (reason)
A2: PRECISE | B2: d7d9107de19eba8228bc599f53f013245760caee | C2: A Survey of Data Mining and Machine Learning Methods for Cyber Security Intrusion Detection | D2: 42838 | E2: 2017 | F2: Review | G2: Engineering | H2: 106 | I2: 1461 | K2: {"CorpusId": 44606951, "MAG": "2605388774"} | M2: FALSE | O2: 406-412 | P2: 7 | R2: 14 | T2: 1; 2; 1; 2 | U2: 1.5 | V2: 0.47281553 | Z2: 0.079761971 | AB2: 1 | AC2: 0 | AD2: 0.16994049 | AE2: non-OA
A3: PRECISE | B3: dab11c890b9924c8bfcb09bf8a9b1fbd1e2bbffc | C3: Processing flows of information: From data stream to complex event processing | D3: 41061 | E3: 2012 | F3: JournalArticle; Review | G3: Computer Science | H3: 84 | I3: 995 | K3: {"CorpusId": 8728283, "DBLP": "journals/csur/CugolaM12", "DOI": "10.1145/2187671.2187677", "MAG": "1973026225"} | L3: 10.1145/2187671.2187677 | M3: FALSE | O3: 15:1-15:62 | R3: 181 | T3: 35; 24 | U3: 29.5 | V3: 0.20443805 | Z3: 0.9548721 | AB3: 1 | AC3: 0.80592582 | AD3: 0.46931061 | AE3: non-OA
A4: PRECISE | B4: e195d061b90b07cd4e2997346b185fa4a7dae656 | C4: A Survey on SVM Classifiers for Intrusion Detection | D4: 41838 | E4: 2014 | F4: Review | G4: Computer Science | H4: 3 | I4: 28 | K4: {"CorpusId": 12782418, "DOI": "10.5120/17294-7779", "MAG": "2125408776"} | L4: 10.5120/17294-7779 | M4: TRUE | N4: https://doi.org/10.5120/17294-7779 | O4: 34-44 | P4: 11 | R4: 39 | T4: 2; 1; 8 | U4: 3.6666667 | V4: 0.0068459658 | Z4: 0.42365163 | AB4: 1 | AC4: 0.015316089 | AD4: 0.25744452 | AE4: Included
A5: PRECISE | B5: 4db2f23a5ad2259b90aa9b0545d27cd44337515a | C5: Intrusion detection system: A comprehensive review | F5: JournalArticle; Review | G5: Computer Science | H5: 71 | I5: 1426 | K5: {"CorpusId": 18434328, "DBLP": "journals/jnca/LiaoLLT13", "DOI": "10.1016/j.jnca.2012.09.004", "MAG": "433644524"} | L5: 10.1016/j.jnca.2012.09.004 | M5: FALSE | O5: 16-24 | P5: 9 | R5: 71 | T5: 2; 15; 4; 4 | U5: 6.25 | Z5: 0.62973618 | AC5: 0.20085468 | AD5: 0.17751951 | AE5: non-OA
A6: PRECISE | B6: e467ff1ea3a0c535a0cef87f7e0daa414d524d9d | C6: Network Anomaly Detection: Methods, Systems and Tools | D6: 41660 | E6: 2014 | F6: JournalArticle; Review | G6: Computer Science | H6: 71 | I6: 1184 | K6: {"CorpusId": 4937576, "DBLP": "journals/comsur/BhuyanBK14", "DOI": "10.1109/SURV.2013.052213.00046", "MAG": "1966809779"} | L6: 10.1109/surv.2013.052213.00046 | M6: FALSE | O6: 303-336 | P6: 34 | R6: 227 | T6: 21; 39; 44 | U6: 34.666667 | V6: 0.27741331 | Z6: 1 | AB6: 1 | AC6: 0.8718309 | AD6: 0.48718309 | AE6: non-OA
A7: PRECISE | B7: f3707a07c3dc0152391a1ad434e83e55609b4ee6 | C7: Intrusion Detection System: A Review | D7: 42155 | E7: 2015 | F7: Review | G7: Engineering | H7: 3 | I7: 33 | K7: {"CorpusId": 10549267, "DOI": "10.14257/IJSIA.2015.9.5.07", "MAG": "2289716850"} | L7: 10.14257/ijsia.2015.9.5.07 | M7: TRUE | N7: https://doi.org/10.14257/ijsia.2015.9.5.07 | O7: 69-76 | P7: 8 | R7: 26 | T7: 5; 2 | U7: 3.5 | V7: 0.0087463557 | Z7: 0.28584652 | AB7: 1 | AC7: 0 | AD7: 0.22146163 | AE7: Included
A8: PRECISE | B8: 1c65649ffb61144f867aa1dc526ddaac19b3cecd | C8: A survey of intrusion detection in Internet of Things | D8: 42840 | E8: 2017 | F8: JournalArticle; Review | G8: Computer Science | H8: 47 | I8: 891 | K8: {"CorpusId": 31714, "DBLP": "journals/jnca/ZarpelaoMKA17", "DOI": "10.1016/j.jnca.2017.02.009", "MAG": "2590373591"} | L8: 10.1016/j.jnca.2017.02.009 | M8: FALSE | O8: 25-37 | P8: 13 | R8: 90 | T8: 16; 11; 3; 3 | U8: 8.25 | V8: 0.28853627 | Z8: 0.71184698 | AB8: 1 | AC8: 0.30345516 | AD8: 0.35830726 | AE8: non-OA
A9: PRECISE | B9: 2eea41136efeea6e1426c631fa1ac0a221fe6978 | C9: Deep learning approach for Network Intrusion Detection in Software Defined Networking | D9: 42644 | E9: 2016 | F9: Conference; JournalArticle; Review | G9: Computer Science | H9: 47 | I9: 635 | K9: {"CorpusId": 15987982, "DBLP": "conf/wincom/TangMMZG16", "DOI": "10.1109/WINCOM.2016.7777224", "MAG": "2560162835"} | L9: 10.1109/wincom.2016.7777224 | M9: TRUE | N9: http://eprints.whiterose.ac.uk/106836/8/Tuan%20Tang_WINCOM16.pdf | O9: 258-263 | P9: 6 | R9: 20 | T9: 5; 17; 28; 25; 39 | U9: 22.8 | V9: 0.19336175 | Z9: 0.19773288 | AB9: 1 | AC9: 0.70146429 | AD9: 0.26957965 | AE9: unsure
A10: PRECISE | B10: 8e2527113c652a25dad5a8af72a67f2d0bbb2706 | C10: A Survey of Intrusion Detection Systems in Wireless Sensor Networks | D10: 41660 | E10: 2014 | F10: JournalArticle; Review | G10: Computer Science | H10: 41 | I10: 922 | K10: {"CorpusId": 14636557, "DBLP": "journals/comsur/ButunMS14", "DOI": "10.1109/SURV.2013.050113.00191", "MAG": "2011778831"} | L10: 10.1109/surv.2013.050113.00191 | M10: FALSE | O10: 266-282 | P10: 17 | R10: 73 | T10: 22; 23; 23 | U10: 22.666667 | V10: 0.21602624 | Z10: 0.63934256 | AB10: 1 | AC10: 0.69909829 | AD10: 0.37974547 | AE10: non-OA
A11: PRECISE | B11: 05ebbd7487e50f28ee1f19f5303d1ee6c20f24fb | C11: Dealing with Security Alert Flooding: Using Machine Learning for Domain-independent Alert Aggregation | D11: 44649 | E11: 2022 | F11: JournalArticle; Review | G11: Computer Science | H11: 3 | I11: 20 | J11: Intrusion Detection Systems (IDS) secure all kinds of IT infrastructures through automatic detection of malicious activities. Unfortunately, they are known to produce large numbers of alerts that often become overwhelming for manual analysis. Therefore, aggregation methods have been developed for filtering, grouping, and correlating alerts. However, existing techniques either rely on manually defined attack scenarios or require specific alert formats, such as IDMEF that include IP addresses. This makes the application of existing aggregation methods infeasible for alerts from host-based or anomaly-based IDSs that frequently lack such network-related data. In this paper, we therefore present a domain-independent alert aggregation technique. We introduce similarity measures and merging strategies for arbitrary semi-structured alerts and alert groups. Based on these metrics and techniques we propose an incremental procedure for the generation of abstract alert patterns that enable continuous classification of incoming alerts. Evaluations show that our approach is capable of reducing the number of alert groups for human review by around \( 80\% \) and assigning attack classifiers to the groups with true positive rates of \( 80\% \) and false positive rates lower than \( 5\% \) . | K11: {"CorpusId": 247765608, "DBLP": "journals/tissec/LandauerSWR22", "DOI": "10.1145/3510581"} | L11: 10.1145/3510581 | M11: TRUE | N11: https://dl.acm.org/doi/pdf/10.1145/3510581 | O11: 1 - 36 | P11: 36 | R11: 40 | T11: 13; 28; 15; 43 | U11: 24.75 | V11: 0.015637217 | Z11: 0.43230913 | AB11: 1 | AC11: 0.73462914 | AD11: 0.3315402 | AE11: Included
A12: PRECISE | B12: 6bd85cfce9eeee059b1ee73851711e9ec847a31b | C12: The Evolution of MAC Protocols in Wireless Sensor Networks: A Survey | D12: 41295 | E12: 2013 | F12: JournalArticle; Review | G12: Computer Science | H12: 37 | I12: 602 | K12: {"CorpusId": 25576812, "DBLP": "journals/comsur/HuangXSMX13", "DOI": "10.1109/SURV.2012.040412.00105", "MAG": "2170044052"} | L12: 10.1109/surv.2012.040412.00105 | M12: FALSE | O12: 101-120 | P12: 20 | R12: 78 | T12: 14; 39; 5; 32; 42 | U12: 26.4 | V12: 0.12993741 | Z12: 0.66226648 | AB12: 1 | AC12: 0.76078584 | AD12: 0.3916452 | AE12: non-OA
A13: PRECISE | B13: ea5f9c473fe187e9db6251a07504eeb7f71116c1 | C13: NLP Methods in Host-based Intrusion Detection Systems: A Systematic Review and Future Directions | D13: 44581 | E13: 2022 | F13: JournalArticle; Review | G13: Computer Science | H13: 3 | I13: 23 | K13: {"ArXiv": "2201.08066", "CorpusId": 246063653, "DBLP": "journals/corr/abs-2201-08066", "DOI": "10.1016/j.jnca.2023.103761"} | L13: 10.1016/j.jnca.2023.103761 | M13: TRUE | N13: https://doi.org/10.1016/j.jnca.2023.103761 | O13: 103761 | R13: 228 | S13: 2022 | T13: 7; 2; 54 | U13: 21 | V13: 0.017074981 | W13: 0 | Z13: 1 | AA13: 1 | AB13: 1 | AC13: 0.66834405 | AD13: 0.6668344 | AE13: Included
A14: PRECISE | B14: 67f3df0846e89da5dfc7c25980d9189c7df50292 | C14: CoSDEO 2016 Keynote: A decade later — Challenges: Device-free passive localization for wireless environments | D14: 42443 | E14: 2016 | F14: Conference; JournalArticle; Review | G14: Computer Science | H14: 34 | I14: 417 | K14: {"CorpusId": 34643949, "DBLP": "conf/percom/Youssef16", "DOI": "10.1109/PERCOMW.2016.7457113", "MAG": "2337900948"} | L14: 10.1109/percomw.2016.7457113 | M14: FALSE | O14: 1-2 | P14: 2 | R14: 45 | T14: 43 | U14: 43 | V14: 0.11965567 | Z14: 0.47265372 | AB14: 1 | AC14: 0.96026024 | AD14: 0.36418945 | AE14: non-OA
A15: PRECISE | B15: 692fb7c661cb83356d803b5013b1890eb1b1c838 | C15: A Systematic Review of Defensive and Offensive Cybersecurity with Machine Learning | D15: 44044 | E15: 2020 | F15: Review | G15: Computer Science | H15: 3 | I15: 34 | J15: This is a systematic review of over one hundred research papers about machine learning methods applied to defensive and offensive cybersecurity. In contrast to previous reviews, which focused on several fragments of research topics in this area, this paper systematically and comprehensively combines domain knowledge into a single review. Ultimately, this paper seeks to provide a base for researchers that wish to delve into the field of machine learning for cybersecurity. Our findings identify the frequently used machine learning methods within supervised, unsupervised, and semi-supervised machine learning, the most useful data sets for evaluating intrusion detection methods within supervised learning, and methods from machine learning that have shown promise in tackling various threats in defensive and offensive cybersecurity. | K15: {"CorpusId": 225303304, "DOI": "10.3390/app10175811", "MAG": "3080664025"} | L15: 10.3390/app10175811 | M15: TRUE | N15: https://www.mdpi.com/2076-3417/10/17/5811/pdf?version=1598087537 | R15: 136 | S15: 2019 | T15: 3; 7; 28 | U15: 12.666667 | V15: 0.018046709 | W15: 1 | Z15: 0.85528951 | AA15: 1 | AB15: 1 | AC15: 0.46784371 | AD15: 0.61060675 | AE15: Included
A16: PRECISE | B16: 2caa42c15671810c8236ac553753eec1d83f7e48 | C16: On Generating Network Traffic Datasets with Synthetic Attacks for Intrusion Detection | D16: 43586 | E16: 2019 | F16: JournalArticle; Review | G16: Computer Science | H16: 3 | I16: 64 | J16: Most research in the field of network intrusion detection heavily relies on datasets. Datasets in this field, however, are scarce and difficult to reproduce. To compare, evaluate, and test related work, researchers usually need the same datasets or at least datasets with similar characteristics as the ones used in related work. In this work, we present concepts and the Intrusion Detection Dataset Toolkit (ID2T) to alleviate the problem of reproducing datasets with desired characteristics to enable an accurate replication of scientific results. Intrusion Detection Dataset Toolkit (ID2T) facilitates the creation of labeled datasets by injecting synthetic attacks into background traffic. The injected synthetic attacks created by ID2T blend with the background traffic by mimicking the background traffic’s properties. This article has three core contributions. First, we present a comprehensive survey on intrusion detection datasets. In the survey, we propose a classification to group the negative qualities found in the datasets. Second, the architecture of ID2T is revised, improved, and expanded in comparison to previous work. The architectural changes enable ID2T to inject recent and advanced attacks, such as the EternalBlue exploit or a peer-to-peer botnet. ID2T’s functionality provides a set of tests, known as TIDED, that helps identify potential defects in the background traffic into which attacks are injected. Third, we illustrate how ID2T is used in different use-case scenarios to replicate scientific results with the help of reproducible datasets. ID2T is open source software and is made available to the community to expand its arsenal of attacks and capabilities. | K16: {"ArXiv": "1905.00304", "CorpusId": 141459303, "DBLP": "journals/tissec/CorderoVWMN21", "DOI": "10.1145/3424155", "MAG": "2942566426"} | L16: 10.1145/3424155 | M16: TRUE | N16: https://dl.acm.org/doi/pdf/10.1145/3424155 | O16: 1 - 39 | P16: 39 | R16: 74 | S16: 2018 | T16: 8; 17; 7; 48; 30 | U16: 22 | V16: 0.027327071 | W16: 1 | Z16: 0.64404882 | AA16: 1 | AB16: 1 | AC16: 0.68706473 | AD16: 0.57971868 | AE16: Included
A17: PRECISE | B17: 8c6f39039d72951db9d2c6073018258ed9306c06 | C17: A GAN and Feature Selection-Based Oversampling Technique for Intrusion Detection | D17: 44382 | E17: 2021 | F17: JournalArticle; Review | G17: Computer Science | H17: 3 | I17: 48 | J17: In recent years, there have been numerous cyber security issues that have caused considerable damage to the society. The development of efficient and reliable Intrusion Detection Systems (IDSs) is an effective countermeasure against the growing cyber threats. In modern high-bandwidth, large-scale network environments, traditional IDSs suffer from a high rate of missed and false alarms. Researchers have introduced machine learning techniques into intrusion detection with good results. However, due to the scarcity of attack data, such methods’ training sets are usually unbalanced, affecting the analysis performance. In this paper, we survey and analyze the design principles and shortcomings of existing oversampling methods. Based on the findings, we take the perspective of imbalance and high dimensionality of datasets in the field of intrusion detection and propose an oversampling technique based on Generative Adversarial Networks (GAN) and feature selection. Specifically, we model the complex high-dimensional distribution of attacks based on Gradient Penalty Wasserstein GAN (WGAN-GP) to generate additional attack samples. We then select a subset of features representing the entire dataset based on analysis of variance, ultimately generating a rebalanced low-dimensional dataset for machine learning training. To evaluate the effectiveness of our proposal, we conducted experiments based on the NSL-KDD, UNSW-NB15, and CICIDS-2017 datasets. The experimental results show that our method can effectively improve the detection performance of machine learning models and outperform the baselines. | K17: {"CorpusId": 235800401, "DBLP": "journals/scn/LiuLZWLY21", "DOI": "10.1155/2021/9947059"} | L17: 10.1155/2021/9947059 | M17: TRUE | N17: https://downloads.hindawi.com/journals/scn/2021/9947059.pdf | O17: 9947059:1-9947059:15 | R17: 42 | S17: 2021 | T17: 5; 11; 6; 8; 6; 8 | U17: 7.3333333 | V17: 0.031047865 | W17: 0 | Z17: 0.44900806 | AA17: 1 | AB17: 1 | AC17: 0.25950435 | AD17: 0.48820245 | AE17: Included
A18: PRECISE | B18: cead00c7b3384653ce8013139a5d4543d96fcd07 | C18: Fault Injection Attacks on Cryptographic Devices: Theory, Practice, and Countermeasures | D18: 41004 | E18: 2012 | F18: JournalArticle; Review | G18: Computer Science; Engineering | H18: 30 | I18: 553 | K18: {"CorpusId": 1762526, "DBLP": "journals/pieee/BarenghiBKN12", "DOI": "10.1109/JPROC.2012.2188769", "MAG": "2085992264"} | L18: 10.1109/jproc.2012.2188769 | M18: TRUE | N18: http://euler.ecs.umass.edu/research/bbkn-IEEEP-2012.pdf | O18: 3056-3076 | P18: 21 | R18: 94 | T18: 26; 27; 44; 39 | U18: 34 | V18: 0.11230707 | Z18: 0.72692936 | AB18: 1 | AC18: 0.86388451 | AD18: 0.41812079 | AE18: unsure
A19: PRECISE | B19: 25cd96cc105927efa772f690426e955f080f72ff | C19: A Scheme for Generating a Dataset for Anomalous Activity Detection in IoT Networks | D19: 43964 | E19: 2020 | F19: Conference; JournalArticle; Review | G19: Computer Science | H19: 27 | I19: 218 | K19: {"CorpusId": 218539986, "DBLP": "conf/ai/UllahM20", "DOI": "10.1007/978-3-030-47358-7_52", "MAG": "3022604549"} | L19: 10.1007/978-3-030-47358-7_52 | M19: FALSE | O19: 508-520 | P19: 13 | R19: 15 | T19: 13; 38 | U19: 25.5 | V19: 0.11099796 | Z19: 0.1023899 | AB19: 1 | AC19: 0.74672028 | AD19: 0.2502695 | AE19: non-OA
A20: PRECISE | B20: f4ba147e57beee5e57cc4548feb130cbe16c9192 | C20: Network Intrusion Detection for IoT Security Based on Learning Techniques | D20: 43495 | E20: 2019 | F20: JournalArticle; Review | G20: Computer Science | H20: 27 | I20: 666 | J20: Pervasive growth of Internet of Things (IoT) is visible across the globe. The 2016 Dyn cyberattack exposed the critical fault-lines among smart networks. Security of IoT has become a critical concern. The danger exposed by infested Internet-connected Things not only affects the security of IoT but also threatens the complete Internet eco-system which can possibly exploit the vulnerable Things (smart devices) deployed as botnets. Mirai malware compromised the video surveillance devices and paralyzed Internet via distributed denial of service attacks. In the recent past, security attack vectors have evolved bothways, in terms of complexity and diversity. Hence, to identify and prevent or detect novel attacks, it is important to analyze techniques in IoT context. This survey classifies the IoT security threats and challenges for IoT networks by evaluating existing defense techniques. Our main focus is on network intrusion detection systems (NIDSs); hence, this paper reviews existing NIDS implementation tools and datasets as well as free and open-source network sniffing software. Then, it surveys, analyzes, and compares state-of-the-art NIDS proposals in the IoT context in terms of architecture, detection methodologies, validation strategies, treated threats, and algorithm deployments. The review deals with both traditional and machine learning (ML) NIDS techniques and discusses future directions. In this survey, our focus is on IoT NIDS deployed via ML since learning algorithms have a good success rate in security and privacy. The survey provides a comprehensive review of NIDSs deploying different aspects of learning techniques for IoT, unlike other top surveys targeting the traditional systems. We believe that, this paper will be useful for academia and industry research, first, to identify IoT threats and challenges, second, to implement their own NIDS and finally to propose new smart techniques in IoT context considering IoT limitations. Moreover, the survey will enable security individuals differentiate IoT NIDS from traditional ones. | K20: {"CorpusId": 86720272, "DBLP": "journals/comsur/ChaabouniMZSF19", "DOI": "10.1109/COMST.2019.2896380", "MAG": "2911505293"} | L20: 10.1109/comst.2019.2896380 | M20: FALSE | O20: 2671-2701 | P20: 31 | R20: 134 | T20: 3; 21; 16; 3; 16 | U20: 11.8 | V20: 0.27373613 | Z20: 0.85013337 | AB20: 1 | AC20: 0.4402525 | AD20: 0.40655859 | AE20: non-OA
A21: PRECISE | B21: 6d7b1e32a3c8bb8cf4f51f4c0561146c437bc766 | C21: A Survey on Anomaly Based Host Intrusion Detection System | D21: 43191 | E21: 2018 | F21: Review | G21: Computer Science; Physics | H21: 3 | I21: 95 | J21: An intrusion detection system (IDS) is hardware, software or a combination of two, for monitoring network or system activities to detect malicious signs. In computer security, designing a robust intrusion detection system is one of the most fundamental and important problems. The primary function of system is detecting intrusion and gives alerts when user tries to intrusion on timely manner. In these techniques when IDS find out intrusion it will send alert massage to the system administrator. Anomaly detection is an important problem that has been researched within diverse research areas and application domains. This survey tries to provide a structured and comprehensive overview of the research on anomaly detection. From the existing anomaly detection techniques, each technique has relative strengths and weaknesses. The current state of the experiment practice in the field of anomaly-based intrusion detection is reviewed and survey recent studies in this. This survey provides a study of existing anomaly detection techniques, and how the techniques used in one area can be applied in another application domain. | K21: {"CorpusId": 65090834, "DOI": "10.1088/1742-6596/1000/1/012049", "MAG": "2801256139"} | L21: 10.1088/1742-6596/1000/1/012049 | M21: TRUE | N21: https://iopscience.iop.org/article/10.1088/1742-6596/1000/1/012049/pdf | R21: 42 | S21: 2016 | T21: 2; 6; 4; 2 | U21: 3.5 | V21: 0.034709536 | W21: 2 | Z21: 0.44900806 | AA21: 1 | AB21: 1 | AC21: 0 | AD21: 0.46225201 | AE21: Included
A22: PRECISE | B22: abc1e735b100dd464c0de6b71d319b29bddbfc36 | C22: Data Mining Techniques in Intrusion Detection Systems: A Systematic Literature Review | D22: 43371 | E22: 2018 | F22: JournalArticle; Review | G22: Computer Science | H22: 3 | I22: 94 | J22: The continued ability to detect malicious network intrusions has become an exercise in scalability, in which data mining techniques are playing an increasingly important role. We survey and categorize the fields of data mining and intrusion detection systems, providing a systematic treatment of methodologies and techniques. We apply a criterion-based approach to select 95 relevant articles from 2007 to 2017. We identified 19 separate data mining techniques used for intrusion detection, and our analysis encompasses rich information for future research based on the strengths and weaknesses of these techniques. Furthermore, we observed a research gap in establishing the effectiveness of classifiers to identify intrusions in modern network traffic when trained with aging data sets. Our review points to the need for more empirical experiments addressing real-time solutions for big data against contemporary attacks. | K22: {"CorpusId": 53042988, "DBLP": "journals/access/SaloINSE18", "DOI": "10.1109/ACCESS.2018.2872784", "MAG": "2893123663"} | L22: 10.1109/access.2018.2872784 | M22: TRUE | N22: https://doi.org/10.1109/access.2018.2872784 | O22: 56046-56058 | P22: 13 | R22: 108 | S22: 2018 | T22: 6; 15; 37; 48; 17 | U22: 24.6 | V22: 0.03676183 | W22: 0 | Z22: 0.77512822 | AA22: 1 | AB22: 1 | AC22: 0.73216869 | AD22: 0.61699892 | AE22: Included
A23: PRECISE | B23: cf003fbb1609c1457701cb7d698a5361be1d16b1 | C23: An intrusion detection and prevention system in cloud computing: A systematic review | F23: JournalArticle; Review | G23: Computer Science | H23: 24 | I23: 443 | K23: {"CorpusId": 34668439, "DBLP": "journals/jnca/PatelTBJ13", "DOI": "10.1016/j.jnca.2012.08.007", "MAG": "2139836766"} | L23: 10.1016/j.jnca.2012.08.007 | M23: FALSE | O23: 25-41 | P23: 17 | R23: 90 | T23: 22; 14; 14; 16 | U23: 16.5 | Z23: 0.71184698 | AC23: 0.57196832 | AD23: 0.23515858 | AE23: non-OA
A24: PRECISE | B24: 2313d55f4e7739de529e966521018c9043c3fe45 | C24: Survey on Misbehavior Detection in Cooperative Intelligent Transportation Systems | D24: 42664 | E24: 2016 | F24: JournalArticle; Review | G24: Computer Science | H24: 23 | I24: 218 | J24: Cooperative intelligent transportation systems (cITS) are a promising technology to enhance driving safety and efficiency. Vehicles communicate wirelessly with other vehicles and infrastructure, thereby creating a highly dynamic and heterogeneously managed ad-hoc network. It is these network properties that make it a challenging task to protect integrity of the data and guarantee its correctness. A major component is the problem that traditional security mechanisms like public key infrastructure (PKI)-based asymmetric cryptography only exclude outsider attackers that do not possess key material. However, because attackers can be insiders within the network (i.e., possess valid key material), this approach cannot detect all possible attacks. In this survey, we present misbehavior detection mechanisms that can detect such insider attacks based on attacker behavior and information analysis. In contrast to well-known intrusion detection for classical IT systems, these misbehavior detection mechanisms analyze information semantics to detect attacks, which aligns better with highly application-tailored communication protocols foreseen for cITS. In our survey, we provide an extensive introduction to the cITS ecosystem and discuss shortcomings of PKI-based security. We derive and discuss a classification for misbehavior detection mechanisms, provide an in-depth overview of seminal papers on the topic, and highlight open issues and possible future research trends. | K24: {"ArXiv": "1610.06810", "CorpusId": 8876979, "DBLP": "journals/comsur/HeijdenDLK19", "DOI": "10.1109/COMST.2018.2873088", "MAG": "2963030364"} | L24: 10.1109/comst.2018.2873088 | M24: TRUE | N24: https://arxiv.org/pdf/1610.06810 | O24: 779-811 | P24: 33 | R24: 138 | S24: 2016 | T24: 3; 15; 21; 47 | U24: 21.5 | V24: 0.066789216 | W24: 0 | Z24: 0.86037092 | AA24: 1 | AB24: 1 | AC24: 0.6778084 | AD24: 0.63287357 | AE24: not-Topic
A25: PRECISE | B25: 1be5bb9bb07835f63509d384ac75d7cf5bf22fb9 | C25: A Survey of Network Attacks on Cyber-Physical Systems | D25: 43892 | E25: 2020 | F25: JournalArticle; Review | G25: Computer Science | H25: 3 | I25: 85 | J25: A cyber-physical system (CPS) typically consists of the plant, sensors, actuators, the controller and a communication network. The communication network connects the individual components to achieve the computing and communication in the CPS. It also makes the CPS vulnerable to network attacks. How to deal with the network attacks in CPSs has become a research hotspot. This paper surveys the types of network attacks in CPSs, the intrusion detection methods and the attack defense strategies. The future research directions of CPSs network security are also presented. | K25: {"CorpusId": 212705246, "DBLP": "journals/access/CaoJZWYX20", "DOI": "10.1109/ACCESS.2020.2977423", "MAG": "3010490819"} | L25: 10.1109/access.2020.2977423 | M25: TRUE | N25: https://ieeexplore.ieee.org/ielx7/6287639/8948470/09019636.pdf | O25: 44219-44227 | P25: 9 | R25: 84 | S25: 2020 | T25: 1; 7; 1; 21; 16; 1 | U25: 7.8333333 | V25: 0.041748527 | W25: 0 | Z25: 0.68793241 | AA25: 1 | AB25: 1 | AC25: 0.28404407 | AD25: 0.55038751 | AE25: Included
A26: PRECISE | B26: 922b6fb164f5b9d774d16cb14c31f5cb68a02046 | C26: Game theory meets network security and privacy | D26: 41426 | E26: 2013 | F26: JournalArticle; Review | G26: Computer Science | H26: 23 | I26: 797 | K26: {"CorpusId": 207203993, "DBLP": "journals/csur/ManshaeiZABH13", "DOI": "10.1145/2480741.2480742", "MAG": "2067064328"} | L26: 10.1145/2480741.2480742 | M26: TRUE | N26: http://infoscience.epfl.ch/record/151965/files/Game%20Sec-ACM%20Survey.pdf | O26: 25:1-25:39 | R26: 136 | T26: 24; 51; 48; 96; 87 | U26: 61.2 | V26: 0.17703243 | Z26: 0.85528951 | AB26: 1 | AC26: 1 | AD26: 0.46382238 | AE26: unsure
A27: PRECISE | B27: de3ddfdb3c8c995cff057e010db6ac70e06ef5b5 | C27: Data stream clustering: A survey | D27: 41548 | E27: 2013 | F27: JournalArticle; Review | G27: Computer Science | H27: 23 | I27: 547 | K27: {"CorpusId": 3346652, "DBLP": "journals/csur/SilvaFBHCG13", "DOI": "10.1145/2522968.2522981", "MAG": "2088340225"} | L27: 10.1145/2522968.2522981 | M27: TRUE | N27: http://repositorio.inesctec.pt/bitstreams/5cd9346a-c309-4fdb-b2b2-20148318a05c/download | O27: 13:1-13:31 | R27: 134 | T27: 15; 10; 29; 33; 47; 61 | U27: 32.5 | V27: 0.12488584 | Z27: 0.85013337 | AB27: 1 | AC27: 0.84543721 | AD27: 0.44707706 | AE27: not-Topic
